Workbook
Name \\\\: #REF!
Name \\\\\: #REF!
Name \0: #REF!
Name \A: #REF!
Name \A: #REF!
Name \A: #REF!
Name \b: #REF!
Name \c: #REF!
Name \c: #REF!
Name \Ch1: #REF!
Name \d: #REF!
Name \DS: #REF!
Name \e: #REF!
Name \e: #REF!
Name \f: #REF!
Name \GGO: #REF!
Name \h: #REF!
Name \i: #REF!
Name \l: #REF!
Name \l: #REF!
Name \M: #REF!
Name \M: #REF!
Name \mm: #REF!
Name \N: #REF!
Name \N: #REF!
Name \o: #REF!
Name \o: #REF!
Name \OPCOES: #REF!
Name \P: #REF!
Name \P: #REF!
Name \pop: #REF!
Name \q: #REF!
Name \r: #REF!
Name \s: #REF!
Name \s: #REF!
Name \t: #REF!
Name \u: #REF!
Name \v: #REF!
Name \w: #REF!
Name \x: #REF!
Name \y: #REF!
Name \z: #REF!
Name _: #REF!
Name _.: #REF!
Name __: #REF!
Name ___: #REF!
Name ____: #REF!
Name _____: #REF!
Name ______: #REF!
Name _______: #REF!
Name _______res1: #REF!
Name _______res1: #REF!
Name _______res1: #REF!
Name _______res1: #REF!
Name _______res1: #REF!
Name _______res1: #REF!
Name _______res1: [1]Sheet7!#REF!
Name _______sft2: #REF!
Name _______sft2: #REF!
Name _______sft2: #REF!

Sheet Resume
G3: =Pricing!G3 -> Description
F4: =Pricing!F4 -> Client: CTS | G4: =Pricing!G4 -> Offer: 251.1009.R03
F5: =Pricing!F5 -> Responsible: QS Manager | G5: =Pricing!G5 -> Date: 31/10/2025
A7: # | E7: Item | F7: Description | I7: Total Price | J7: %
A8: # | I8: =IF(G8<>0,#REF!+#REF!,"")
A9: # | E9: 216 | F9: =+VLOOKUP(E9,Pricing!E:M,2,0) -> Administration / supervision | I9: =VLOOKUP(E9,Pricing!E:M,9,0) -> 40885876 | J9: =I9/$I$31 -> 0.17433402
A10: # | E10: 211 | F10: =+VLOOKUP(E10,Pricing!E:M,2,0) -> Logistics | I10: =VLOOKUP(E10,Pricing!E:M,9,0) -> 0 | J10: =I10/$I$31 -> 0
A11: # | E11: 419 | F11: =+VLOOKUP(E11,Pricing!E:M,2,0) -> Commisioning | I11: =VLOOKUP(E11,Pricing!E:M,9,0) -> 10636532 | J11: =I11/$I$31 -> 0.045353299
A12: # | E12: 218 | F12: =+VLOOKUP(E12,Pricing!E:M,2,0) -> Site infrastruckture | I12: =VLOOKUP(E12,Pricing!E:M,9,0) -> 6650953.5 | J12: =I12/$I$31 -> 0.028359121
A13: # | E13: 411 | F13: =+VLOOKUP(E13,Pricing!E:M,2,0) -> Containment | I13: =VLOOKUP(E13,Pricing!E:M,9,0) -> 60103897 | J13: =I13/$I$31 -> 0.25627809
A14: # | E14: 412 | F14: =+VLOOKUP(E14,Pricing!E:M,2,0) -> Earthing inside, outside and underground | I14: =VLOOKUP(E14,Pricing!E:M,9,0) -> 8917705.6 | J14: =I14/$I$31 -> 0.038024366
A15: # | E15: 413 | F15: =+VLOOKUP(E15,Pricing!E:M,2,0) -> Lightning protection | I15: =VLOOKUP(E15,Pricing!E:M,9,0) -> 2756131.2 | J15: =I15/$I$31 -> 0.011751917
A16: # | E16: 414 | F16: =+VLOOKUP(E16,Pricing!E:M,2,0) -> Equipment installation | I16: =VLOOKUP(E16,Pricing!E:M,9,0) -> 2538511.9 | J16: =I16/$I$31 -> 0.010824007
A17: # | E17: 429 | F17: =+VLOOKUP(E17,Pricing!E:M,2,0) -> Cables MV | I17: =VLOOKUP(E17,Pricing!E:M,9,0) -> 0 | J17: =I17/$I$31 -> 0
A18: # | E18: 431 | F18: =+VLOOKUP(E18,Pricing!E:M,2,0) -> Busbars | I18: =VLOOKUP(E18,Pricing!E:M,9,0) -> 0 | J18: =I18/$I$31 -> 0
A19: # | E19: 432 | F19: =+VLOOKUP(E19,Pricing!E:M,2,0) -> Cables LV | I19: =VLOOKUP(E19,Pricing!E:M,9,0) -> 42802556 | J19: =I19/$I$31 -> 0.18250659
A20: # | E20: 433 | F20: =+VLOOKUP(E20,Pricing!E:M,2,0) -> Small power | I20: =VLOOKUP(E20,Pricing!E:M,9,0) -> 4680321.8 | J20: =I20/$I$31 -> 0.019956508
... A29: # | E29: 21 | F29: =+VLOOKUP(E29,Pricing!E:M,2,0) -> Fibre Optic | I29: =VLOOKUP(E29,Pricing!E:M,9,0) -> 0 | J29: =I29/$I$31 -> 0
A30: # | E30: 22 | F30: Roxtec | I30: =VLOOKUP(E30,Pricing!E:M,9,0) -> 4211871.3 | J30: =I30/$I$31 -> 0.017959074
A31: # | F31: Total | I31: =SUBTOTAL(9,I8:I30) -> 2.3452609e+08 | J31: =SUM(J9:J30) -> 1
F33: Add VAT at the legal rate, if applicable.
F35: EXCLUDE:
F36: Any and all equipment and work not mentioned in the proposal
F38: PAYMENT CONDITIONS:
F39: 20%: at Purchase Order signature
F40: 75%: within 30 days - working progress
F41: 5%: within 30 days - after completion of the work
F43: Trond Nygaard
F44: Velox Electro Nordics AS

Sheet Pricing
M1: =M508 -> 2.3452609e+08 | AD1: =SUM(AD8:AD508) -> 2217.9769 | AE1: Persons | AF1: Week | AG1: Months
AE2: =AD1/AF2 -> 42.653403 | AF2: =52 -> 52 | AG2: =AF2/4.2 -> 12.380952
G3: Description | M3: Prices in NOK
F4: ='Project Input'!B2 & " " &'Project Input'!C2 -> Client: CTS | G4: Offer: 251.1009.R03 | P4: =SUBTOTAL(9,P8:P507) -> 92490232 | U4: =SUM(U8:U508) -> 1.0418915e+08 | W4: =SUBTOTAL(9,W8:W507) -> 1.9667939e+08 | Z4: =SUBTOTAL(9,Z8:Z508) -> 100547.4 | AA4: =SUBTOTAL(9,AA8:AA508) -> 27975.44 | AB4: =SUBTOTAL(9,AB8:AB508) -> 31171.5 | AC4: =SUBTOTAL(9,AC8:AC508) -> 159694.34
F5: ='Project Input'!B3 & " " &'Project Input'!C3 -> Responsible: QS Manager | G5: Date: 31/10/2025 | P5: =P4/W4 -> 0.47025891 | U5: =U4/W4 -> 0.52974109
I6: Material | K6: Labor | O6: Material | R6: Manpower | W6: Total Cost | Z6: Sum Hours | AA6: Sum Hours | AB6: Sum Hours | AC6: Sum Hours
E7: Item | F7: Description | G7: Qt. | H7: Unit. | I7: Unit. Price | J7: Total Price | K7: Unit. Price | L7: Total Price | M7: Total Price | O7: Unit. Cost | P7: Sum Cost | R7: Average | S7: Electrician | T7: Test/Commiss | U7: Sum Cost | X7: OBS.: | Z7: Average | AA7: Electrician | AB7: Test/Commiss | AD7: 1 HR/1Wk
I8: =IF(G8<>"",O8/(1-($O$1+#REF!)),"") | J8: =IF(G8<>"",G8*I8,"") | K8: =IF(G8<>0,(U8/G8)/(1-('Project Input'!$C$16+'Project Input'!$C$17)),"") | L8: =IF(G8<>0,K8*G8,"") | M8: =IF(G8<>0,J8+L8,"") | P8: =IF(G8<>"",G8*O8,"") | U8: =IF(G8<>"",(R8*G8*'Project Input'!$C$47)+(S8*G8*'Project Input'!$C$46)+(T8*G8*'Project Input'!$C$45),"") | W8: =IF(G8<>"",U8+P8,"") | Z8: =R8*G8 -> 0 | AA8: =S8*G8 -> 0 | AB8: =T8*G8 -> 0 | AC8: =SUM(Z8:AB8) -> 0 | AD8: =IF(G8<>"",AC8/'Project Input'!$C$41,"")
E9: 216 | F9: Administration / supervision | J9: =IF(G9<>"",G9*I9,"") | K9: =IF(H9<>"",H9*J9,"") | L9: =IF(I9<>"",I9*K9,"") | M9: =SUBTOTAL(9,M10:M26) -> 40885876 | P9: =IF(G9<>"",G9*O9,"") | U9: =IF(G9<>"",(R9*G9*'Project Input'!$C$47)+(S9*G9*'Project Input'!$C$46)+(T9*G9*'Project Input'!$C$45),"") | W9: =IF(G9<>"",U9+P9,"") | Z9: =R9*G9 -> 0 | AA9: =S9*G9 -> 0 | AB9: =T9*G9 -> 0 | AC9: =SUM(Z9:AB9) -> 0 | AD9: =IF(G9<>"",AC9/'Project Input'!$C$41,"")
I10: =IF(G10<>"",O10/(1-('Project Input'!$C$20+'Project Input'!$C$21)),"") | J10: =IF(G10<>"",G10*I10,"") | K10: =IF(G10<>0,(U10/G10)/(1-('Project Input'!$C$20+'Project Input'!$C$21)),"") | L10: =IF(G10<>0,K10*G10,"") | M10: =IF(G10<>0,J10+L10,"") | P10: =IF(G10<>"",G10*O10,"") | U10: =IF(G10<>"",(R10*G10*'Project Input'!$C$47)+(S10*G10*'Project Input'!$C$46)+(T10*G10*'Project Input'!$C$45),"") | W10: =IF(G10<>"",U10+P10,"") | Z10: =R10*G10 -> 0 | AA10: =S10*G10 -> 0 | AB10: =T10*G10 -> 0 | AC10: =SUM(Z10:AB10) -> 0 | AD10: =IF(G10<>"",AC10/'Project Input'!$C$41,"")
F11: Project managment(Project director and manager) | G11: 1 | H11: un | I11: =IF(G11<>"",O11/(1-('Project Input'!$C$20+'Project Input'!$C$21)),"") -> 0 | J11: =IF(G11<>"",G11*I11,"") -> 0 | K11: =IF(G11<>0,(U11/G11)/(1-('Project Input'!$C$20+'Project Input'!$C$21)),"") -> 3358164.5 | L11: =IF(G11<>0,K11*G11,"") -> 3358164.5 | M11: =IF(G11<>0,J11+L11,"") -> 3358164.5 | P11: =IF(G11<>"",G11*O11,"") -> 0 | T11: 3500 | U11: =IF(G11<>"",(R11*G11*'Project Input'!$C$47)+(S11*G11*'Project Input'!$C$46)+(T11*G11*'Project Input'!$C$45),"") -> 2817500 | W11: =IF(G11<>"",U11+P11,"") -> 2817500 | Z11: =R11*G11 -> 0 | AA11: =S11*G11 -> 0 | AB11: =T11*G11 -> 3500 | AC11: =SUM(Z11:AB11) -> 3500 | AD11: =IF(G11<>"",AC11/'Project Input'!$C$41,"") -> 48.611111
F12: Site electrical engineers | G12: 3 | H12: un | I12: =IF(G12<>"",O12/(1-('Project Input'!$C$20+'Project Input'!$C$21)),"") -> 0 | J12: =IF(G12<>"",G12*I12,"") -> 0 | K12: =IF(G12<>0,(U12/G12)/(1-('Project Input'!$C$20+'Project Input'!$C$21)),"") -> 2398688.9 | L12: =IF(G12<>0,K12*G12,"") -> 7196066.7 | M12: =IF(G12<>0,J12+L12,"") -> 7196066.7 | T12: 2500 | U12: =IF(G12<>"",(R12*G12*'Project Input'!$C$47)+(S12*G12*'Project Input'!$C$46)+(T12*G12*'Project Input'!$C$45),"") -> 6037500 | W12: =IF(G12<>"",U12+P12,"") -> 6037500 | Z12: =R12*G12 -> 0 | AA12: =S12*G12 -> 0 | AB12: =T12*G12 -> 7500 | AC12: =SUM(Z12:AB12) -> 7500 | AD12: =IF(G12<>"",AC12/'Project Input'!$C$41,"") -> 104.16667
F13: Design support engineers | G13: 1 | H13: un | I13: =IF(G13<>"",O13/(1-('Project Input'!$C$20+'Project Input'!$C$21)),"") -> 0 | J13: =IF(G13<>"",G13*I13,"") -> 0 | K13: =IF(G13<>0,(U13/G13)/(1-('Project Input'!$C$20+'Project Input'!$C$21)),"") -> 2206793.8 | L13: =IF(G13<>0,K13*G13,"") -> 2206793.8 | M13: =IF(G13<>0,J13+L13,"") -> 2206793.8 | P13: =IF(G13<>"",G13*O13,"") -> 0 | T13: 2300 | U13: =IF(G13<>"",(R13*G13*'Project Input'!$C$47)+(S13*G13*'Project Input'!$C$46)+(T13*G13*'Project Input'!$C$45),"") -> 1851500 | W13: =IF(G13<>"",U13+P13,"") -> 1851500 | Z13: =R13*G13 -> 0 | AA13: =S13*G13 -> 0 | AB13: =T13*G13 -> 2300 | AC13: =SUM(Z13:AB13) -> 2300 | AD13: =IF(G13<>"",AC13/'Project Input'!$C$41,"") -> 31.944444
F14: Procurment officer | G14: 1 | H14: un | I14: =IF(G14<>"",O14/(1-('Project Input'!$C$20+'Project Input'!$C$21)),"") -> 0 | J14: =IF(G14<>"",G14*I14,"") -> 0 | K14: =IF(G14<>0,(U14/G14)/(1-('Project Input'!$C$20+'Project Input'!$C$21)),"") -> 2398688.9 | L14: =IF(G14<>0,K14*G14,"") -> 2398688.9 | M14: =IF(G14<>0,J14+L14,"") -> 2398688.9 | P14: =IF(G14<>"",G14*O14,"") -> 0 | T14: 2500 | U14: =IF(G14<>"",(R14*G14*'Project Input'!$C$47)+(S14*G14*'Project Input'!$C$46)+(T14*G14*'Project Input'!$C$45),"") -> 2012500 | W14: =IF(G14<>"",U14+P14,"") -> 2012500 | Z14: =R14*G14 -> 0 | AA14: =S14*G14 -> 0 | AB14: =T14*G14 -> 2500 | AC14: =SUM(Z14:AB14) -> 2500 | AD14: =IF(G14<>"",AC14/'Project Input'!$C$41,"") -> 34.722222
F15: Planner and document controller | G15: 1 | H15: un | I15: =IF(G15<>"",O15/(1-('Project Input'!$C$20+'Project Input'!$C$21)),"") -> 0 | J15: =IF(G15<>"",G15*I15,"") -> 0 | K15: =IF(G15<>0,(U15/G15)/(1-('Project Input'!$C$20+'Project Input'!$C$21)),"") -> 722884.39 | L15: =IF(G15<>0,K15*G15,"") -> 722884.39 | M15: =IF(G15<>0,J15+L15,"") -> 722884.39 | P15: =IF(G15<>"",G15*O15,"") -> 0 | R15: 1000 | U15: =IF(G15<>"",(R15*G15*'Project Input'!$C$47)+(S15*G15*'Project Input'!$C$46)+(T15*G15*'Project Input'!$C$45),"") -> 606500 | W15: =IF(G15<>"",U15+P15,"") -> 606500 | Z15: =R15*G15 -> 1000 | AA15: =S15*G15 -> 0 | AB15: =T15*G15 -> 0 | AC15: =SUM(Z15:AB15) -> 1000 | AD15: =IF(G15<>"",AC15/'Project Input'!$C$41,"") -> 13.888889
F16: Site Supervisors | G16: 4 | H16: un | I16: =IF(G16<>"",O16/(1-('Project Input'!$C$20+'Project Input'!$C$21)),"") -> 0 | J16: =IF(G16<>"",G16*I16,"") -> 0 | K16: =IF(G16<>0,(U16/G16)/(1-('Project Input'!$C$20+'Project Input'!$C$21)),"") -> 1929380.2 | L16: =IF(G16<>0,K16*G16,"") -> 7717520.9 | M16: =IF(G16<>0,J16+L16,"") -> 7717520.9 | P16: =IF(G16<>"",G16*O16,"") -> 0 | S16: 2500 | U16: =IF(G16<>"",(R16*G16*'Project Input'!$C$47)+(S16*G16*'Project Input'!$C$46)+(T16*G16*'Project Input'!$C$45),"") -> 6475000 | W16: =IF(G16<>"",U16+P16,"") -> 6475000 | Z16: =R16*G16 -> 0 | AA16: =S16*G16 -> 10000 | AB16: =T16*G16 -> 0 | AC16: =SUM(Z16:AB16) -> 10000 | AD16: =IF(G16<>"",AC16/'Project Input'!$C$41,"") -> 138.88889
F17: Formen/team leaders | G17: 1 | H17: un | I17: =IF(G17<>"",O17/(1-('Project Input'!$C$20+'Project Input'!$C$21)),"") -> 0 | J17: =IF(G17<>"",G17*I17,"") -> 0 | K17: =IF(G17<>0,(U17/G17)/(1-('Project Input'!$C$20+'Project Input'!$C$21)),"") -> 771752.09 | L17: =IF(G17<>0,K17*G17,"") -> 771752.09 | M17: =IF(G17<>0,J17+L17,"") -> 771752.09 | P17: =IF(G17<>"",G17*O17,"") -> 0 | S17: 1000 | U17: =IF(G17<>"",(R17*G17*'Project Input'!$C$47)+(S17*G17*'Project Input'!$C$46)+(T17*G17*'Project Input'!$C$45),"") -> 647500 | W17: =IF(G17<>"",U17+P17,"") -> 647500 | Z17: =R17*G17 -> 0 | AA17: =S17*G17 -> 1000 | AB17: =T17*G17 -> 0 | AC17: =SUM(Z17:AB17) -> 1000 | AD17: =IF(G17<>"",AC17/'Project Input'!$C$41,"") -> 13.888889
F18: HSE officers | G18: 3 | H18: un | I18: =IF(G18<>"",O18/(1-('Project Input'!$C$20+'Project Input'!$C$21)),"") -> 0 | J18: =IF(G18<>"",G18*I18,"") -> 0 | K18: =IF(G18<>0,(U18/G18)/(1-('Project Input'!$C$20+'Project Input'!$C$21)),"") -> 1807211 | L18: =IF(G18<>0,K18*G18,"") -> 5421632.9 | M18: =IF(G18<>0,J18+L18,"") -> 5421632.9 | P18: =IF(G18<>"",G18*O18,"") -> 0 | R18: 2500 | U18: =IF(G18<>"",(R18*G18*'Project Input'!$C$47)+(S18*G18*'Project Input'!$C$46)+(T18*G18*'Project Input'!$C$45),"") -> 4548750 | W18: =IF(G18<>"",U18+P18,"") -> 4548750 | Z18: =R18*G18 -> 7500 | AA18: =S18*G18 -> 0 | AB18: =T18*G18 -> 0 | AC18: =SUM(Z18:AB18) -> 7500 | AD18: =IF(G18<>"",AC18/'Project Input'!$C$41,"") -> 104.16667
F19: PPE and HSE equipment | G19: 1 | H19: un | I19: =IF(G19<>"",O19/(1-('Project Input'!$C$20+'Project Input'!$C$21)),"") -> 893921.33 | J19: =IF(G19<>"",G19*I19,"") -> 893921.33 | K19: =IF(G19<>0,(U19/G19)/(1-('Project Input'!$C$20+'Project Input'!$C$21)),"") -> 0 | L19: =IF(G19<>0,K19*G19,"") -> 0 | M19: =IF(G19<>0,J19+L19,"") -> 893921.33 | O19: 750000 | P19: =IF(G19<>"",G19*O19,"") -> 750000 | U19: =IF(G19<>"",(R19*G19*'Project Input'!$C$47)+(S19*G19*'Project Input'!$C$46)+(T19*G19*'Project Input'!$C$45),"") -> 0 | W19: =IF(G19<>"",U19+P19,"") -> 750000 | Z19: =R19*G19 -> 0 | AA19: =S19*G19 -> 0 | AB19: =T19*G19 -> 0 | AC19: =SUM(Z19:AB19) -> 0 | AD19: =IF(G19<>"",AC19/'Project Input'!$C$41,"") -> 0
F20: Logistics officer | G20: 1 | H20: un | I20: =IF(G20<>"",O20/(1-('Project Input'!$C$20+'Project Input'!$C$21)),"") -> 0 | J20: =IF(G20<>"",G20*I20,"") -> 0 | K20: =IF(G20<>0,(U20/G20)/(1-('Project Input'!$C$20+'Project Input'!$C$21)),"") -> 479737.78 | L20: =IF(G20<>0,K20*G20,"") -> 479737.78 | M20: =IF(G20<>0,J20+L20,"") -> 479737.78 | P20: =IF(G20<>"",G20*O20,"") -> 0 | T20: 500 | U20: =IF(G20<>"",(R20*G20*'Project Input'!$C$47)+(S20*G20*'Project Input'!$C$46)+(T20*G20*'Project Input'!$C$45),"") -> 402500 | W20: =IF(G20<>"",U20+P20,"") -> 402500 | Z20: =R20*G20 -> 0 | AA20: =S20*G20 -> 0 | AB20: =T20*G20 -> 500 | AC20: =SUM(Z20:AB20) -> 500 | AD20: =IF(G20<>"",AC20/'Project Input'!$C$41,"") -> 6.9444444
F21: Workshop operator / Spotters | G21: 8 | H21: un | I21: =IF(G21<>"",O21/(1-('Project Input'!$C$20+'Project Input'!$C$21)),"") -> 0 | J21: =IF(G21<>"",G21*I21,"") -> 0 | K21: =IF(G21<>0,(U21/G21)/(1-('Project Input'!$C$20+'Project Input'!$C$21)),"") -> 361442.19 | L21: =IF(G21<>0,K21*G21,"") -> 2891537.5 | M21: =IF(G21<>0,J21+L21,"") -> 2891537.5 | P21: =IF(G21<>"",G21*O21,"") -> 0 | R21: 500 | U21: =IF(G21<>"",(R21*G21*'Project Input'!$C$47)+(S21*G21*'Project Input'!$C$46)+(T21*G21*'Project Input'!$C$45),"") -> 2426000 | W21: =IF(G21<>"",U21+P21,"") -> 2426000 | Z21: =R21*G21 -> 4000 | AA21: =S21*G21 -> 0 | AB21: =T21*G21 -> 0 | AC21: =SUM(Z21:AB21) -> 4000 | AD21: =IF(G21<>"",AC21/'Project Input'!$C$41,"") -> 55.555556
F22: Safety Supervisor LV (AFA) | G22: 1 | H22: un | I22: =IF(G22<>"",O22/(1-('Project Input'!$C$20+'Project Input'!$C$21)),"") -> 0 | J22: =IF(G22<>"",G22*I22,"") -> 0 | K22: =IF(G22<>0,(U22/G22)/(1-('Project Input'!$C$20+'Project Input'!$C$21)),"") -> 1439213.3 | L22: =IF(G22<>0,K22*G22,"") -> 1439213.3 | M22: =IF(G22<>0,J22+L22,"") -> 1439213.3 | P22: =IF(G22<>"",G22*O22,"") -> 0 | T22: 1500 | U22: =IF(G22<>"",(R22*G22*'Project Input'!$C$47)+(S22*G22*'Project Input'!$C$46)+(T22*G22*'Project Input'!$C$45),"") -> 1207500 | W22: =IF(G22<>"",U22+P22,"") -> 1207500 | Z22: =R22*G22 -> 0 | AA22: =S22*G22 -> 0 | AB22: =T22*G22 -> 1500 | AC22: =SUM(Z22:AB22) -> 1500 | AD22: =IF(G22<>"",AC22/'Project Input'!$C$41,"") -> 20.833333
F23: QA (Quality assurance specialists) | G23: 1 | I23: =IF(G23<>"",O23/(1-('Project Input'!$C$20+'Project Input'!$C$21)),"") -> 0 | J23: =IF(G23<>"",G23*I23,"") -> 0 | K23: =IF(G23<>0,(U23/G23)/(1-('Project Input'!$C$20+'Project Input'!$C$21)),"") -> 1439213.3 | L23: =IF(G23<>0,K23*G23,"") -> 1439213.3 | M23: =IF(G23<>0,J23+L23,"") -> 1439213.3 | P23: =IF(G23<>"",G23*O23,"") -> 0 | T23: 1500 | U23: =IF(G23<>"",(R23*G23*'Project Input'!$C$47)+(S23*G23*'Project Input'!$C$46)+(T23*G23*'Project Input'!$C$45),"") -> 1207500 | W23: =IF(G23<>"",U23+P23,"") -> 1207500 | Z23: =R23*G23 -> 0 | AA23: =S23*G23 -> 0 | AB23: =T23*G23 -> 1500 | AC23: =SUM(Z23:AB23) -> 1500 | AD23: =IF(G23<>"",AC23/'Project Input'!$C$41,"") -> 20.833333
F24: SJA, DRA, PTW and toolbox talks | G24: 1 | H24: ls | I24: =IF(G24<>"",O24/(1-('Project Input'!$C$20+'Project Input'!$C$21)),"") -> 0 | J24: =IF(G24<>"",G24*I24,"") -> 0 | K24: =IF(G24<>0,(U24/G24)/(1-('Project Input'!$C$20+'Project Input'!$C$21)),"") -> 3948748.5 | L24: =IF(G24<>0,K24*G24,"") -> 3948748.5 | M24: =IF(G24<>0,J24+L24,"") -> 3948748.5 | P24: =IF(G24<>"",G24*O24,"") -> 0 | R24: 2000 | S24: 2000 | T24: 1000 | U24: =IF(G24<>"",(R24*G24*'Project Input'!$C$47)+(S24*G24*'Project Input'!$C$46)+(T24*G24*'Project Input'!$C$45),"") -> 3313000 | W24: =IF(G24<>"",U24+P24,"") -> 3313000 | Z24: =R24*G24 -> 2000 | AA24: =S24*G24 -> 2000 | AB24: =T24*G24 -> 1000 | AC24: =SUM(Z24:AB24) -> 5000 | AD24: =IF(G24<>"",AC24/'Project Input'!$C$41,"") -> 69.444444
I25: =IF(G25<>"",O25/(1-('Project Input'!$C$20+'Project Input'!$C$21)),"") | J25: =IF(G25<>"",G25*I25,"") | K25: =IF(G25<>0,(U25/G25)/(1-('Project Input'!$C$20+'Project Input'!$C$21)),"") | L25: =IF(G25<>0,K25*G25,"") | M25: =IF(G25<>0,J25+L25,"") | P25: =IF(G25<>"",G25*O25,"") | U25: =IF(G25<>"",(R25*G25*'Project Input'!$C$47)+(S25*G25*'Project Input'!$C$46)+(T25*G25*'Project Input'!$C$45),"") | W25: =IF(G25<>"",U25+P25,"") | Z25: =R25*G25 -> 0 | AA25: =S25*G25 -> 0 | AB25: =T25*G25 -> 0 | AC25: =SUM(Z25:AB25) -> 0 | AD25: =IF(G25<>"",AC25/'Project Input'!$C$41,"")
I26: =IF(G26<>"",O26/(1-('Project Input'!$C$20+'Project Input'!$C$21)),"") | J26: =IF(G26<>"",G26*I26,"") | K26: =IF(G26<>0,(U26/G26)/(1-('Project Input'!$C$20+'Project Input'!$C$21)),"") | L26: =IF(G26<>0,K26*G26,"") | M26: =IF(G26<>0,J26+L26,"") | P26: =IF(G26<>"",G26*O26,"") | U26: =IF(G26<>"",(R26*G26*'Project Input'!$C$47)+(S26*G26*'Project Input'!$C$46)+(T26*G26*'Project Input'!$C$45),"") | W26: =IF(G26<>"",U26+P26,"") | Z26: =R26*G26 -> 0 | AA26: =S26*G26 -> 0 | AB26: =T26*G26 -> 0 | AC26: =SUM(Z26:AB26) -> 0 | AD26: =IF(G26<>"",AC26/'Project Input'!$C$41,"")
E27: 211 | F27: Logistics | L27: =IF(I27<>"",I27*K27,"") | M27: =SUBTOTAL(9,M28:M33) -> 0 | P27: =IF(G27<>"",G27*O27,"") | U27: =IF(G27<>"",(R27*G27*'Project Input'!$C$47)+(S27*G27*'Project Input'!$C$46)+(T27*G27*'Project Input'!$C$45),"") | W27: =IF(G27<>"",U27+P27,"") | Z27: =R27*G27 -> 0 | AA27: =S27*G27 -> 0 | AB27: =T27*G27 -> 0 | AC27: =SUM(Z27:AB27) -> 0 | AD27: =IF(G27<>"",AC27/'Project Input'!$C$41,"")
F28: travel rotation /person | G28: 0 | H28: month | I28: =IF(G28<>"",O28/(1-('Project Input'!$C$20+'Project Input'!$C$21)),"") -> 0 | J28: =IF(G28<>"",G28*I28,"") -> 0 | K28: =IF(G28<>0,(U28/G28)/(1-('Project Input'!$C$20+'Project Input'!$C$21)),"") | L28: =IF(G28<>0,K28*G28,"") | M28: =IF(G28<>0,J28+L28,"") | P28: =IF(G28<>"",G28*O28,"") -> 0 | U28: =IF(G28<>"",(R28*G28*'Project Input'!$C$47)+(S28*G28*'Project Input'!$C$46)+(T28*G28*'Project Input'!$C$45),"") -> 0 | W28: =IF(G28<>"",U28+P28,"") -> 0 | Z28: =R28*G28 -> 0 | AA28: =S28*G28 -> 0 | AB28: =T28*G28 -> 0 | AC28: =SUM(Z28:AB28) -> 0 | AD28: =IF(G28<>"",AC28/'Project Input'!$C$41,"") -> 0
F29: local travel / person | G29: 0 | H29: month | I29: =IF(G29<>"",O29/(1-('Project Input'!$C$20+'Project Input'!$C$21)),"") -> 0 | J29: =IF(G29<>"",G29*I29,"") -> 0 | K29: =IF(G29<>0,(U29/G29)/(1-('Project Input'!$C$20+'Project Input'!$C$21)),"") | L29: =IF(G29<>0,K29*G29,"") | M29: =IF(G29<>0,J29+L29,"") | P29: =IF(G29<>"",G29*O29,"") -> 0 | U29: =IF(G29<>"",(R29*G29*'Project Input'!$C$47)+(S29*G29*'Project Input'!$C$46)+(T29*G29*'Project Input'!$C$45),"") -> 0 | W29: =IF(G29<>"",U29+P29,"") -> 0 | Z29: =R29*G29 -> 0 | AA29: =S29*G29 -> 0 | AB29: =T29*G29 -> 0 | AC29: =SUM(Z29:AB29) -> 0 | AD29: =IF(G29<>"",AC29/'Project Input'!$C$41,"") -> 0
G30: 0 | H30: day | I30: =IF(G30<>"",O30/(1-('Project Input'!$C$20+'Project Input'!$C$21)),"") -> 0 | J30: =IF(G30<>"",G30*I30,"") -> 0 | K30: =IF(G30<>0,(U30/G30)/(1-('Project Input'!$C$20+'Project Input'!$C$21)),"") | L30: =IF(G30<>0,K30*G30,"") | M30: =IF(G30<>0,J30+L30,"") | P30: =IF(G30<>"",G30*O30,"") -> 0 | U30: =IF(G30<>"",(R30*G30*'Project Input'!$C$47)+(S30*G30*'Project Input'!$C$46)+(T30*G30*'Project Input'!$C$45),"") -> 0 | W30: =IF(G30<>"",U30+P30,"") -> 0 | Z30: =R30*G30 -> 0 | AA30: =S30*G30 -> 0 | AB30: =T30*G30 -> 0 | AC30: =SUM(Z30:AB30) -> 0 | AD30: =IF(G30<>"",AC30/'Project Input'!$C$41,"") -> 0
F31: Food/meal day person by CTS | G31: 0 | H31: day | I31: =IF(G31<>"",O31/(1-('Project Input'!$C$20+'Project Input'!$C$21)),"") -> 0 | J31: =IF(G31<>"",G31*I31,"") -> 0 | K31: =IF(G31<>0,(U31/G31)/(1-('Project Input'!$C$20+'Project Input'!$C$21)),"") | L31: =IF(G31<>0,K31*G31,"") | M31: =IF(G31<>0,J31+L31,"") | P31: =IF(G31<>"",G31*O31,"") -> 0 | U31: =IF(G31<>"",(R31*G31*'Project Input'!$C$47)+(S31*G31*'Project Input'!$C$46)+(T31*G31*'Project Input'!$C$45),"") -> 0 | W31: =IF(G31<>"",U31+P31,"") -> 0 | Z31: =R31*G31 -> 0 | AA31: =S31*G31 -> 0 | AB31: =T31*G31 -> 0 | AC31: =SUM(Z31:AB31) -> 0 | AD31: =IF(G31<>"",AC31/'Project Input'!$C$41,"") -> 0
I32: =IF(G32<>"",O32/(1-('Project Input'!$C$20+'Project Input'!$C$21)),"") | J32: =IF(G32<>"",G32*I32,"") | K32: =IF(G32<>0,(U32/G32)/(1-('Project Input'!$C$20+'Project Input'!$C$21)),"") | L32: =IF(G32<>0,K32*G32,"") | M32: =IF(G32<>0,J32+L32,"") | P32: =IF(G32<>"",G32*O32,"") | U32: =IF(G32<>"",(R32*G32*'Project Input'!$C$47)+(S32*G32*'Project Input'!$C$46)+(T32*G32*'Project Input'!$C$45),"") | W32: =IF(G32<>"",U32+P32,"") | Z32: =R32*G32 -> 0 | AA32: =S32*G32 -> 0 | AB32: =T32*G32 -> 0 | AC32: =SUM(Z32:AB32) -> 0 | AD32: =IF(G32<>"",AC32/'Project Input'!$C$41,"")
I33: =IF(G33<>"",O33/(1-('Project Input'!$C$20+'Project Input'!$C$21)),"") | J33: =IF(G33<>"",G33*I33,"") | K33: =IF(G33<>0,(U33/G33)/(1-('Project Input'!$C$20+'Project Input'!$C$21)),"") | L33: =IF(G33<>0,K33*G33,"") | M33: =IF(G33<>0,J33+L33,"") | P33: =IF(G33<>"",G33*O33,"") | U33: =IF(G33<>"",(R33*G33*'Project Input'!$C$47)+(S33*G33*'Project Input'!$C$46)+(T33*G33*'Project Input'!$C$45),"") | W33: =IF(G33<>"",U33+P33,"") | Z33: =R33*G33 -> 0 | AA33: =S33*G33 -> 0 | AB33: =T33*G33 -> 0 | AC33: =SUM(Z33:AB33) -> 0 | AD33: =IF(G33<>"",AC33/'Project Input'!$C$41,"")
E34: 419 | F34: Commisioning | L34: =IF(I34<>"",I34*K34,"") | M34: =SUBTOTAL(9,M35:M44) -> 10636532 | P34: =IF(G34<>"",G34*O34,"") | U34: =IF(G34<>"",(R34*G34*'Project Input'!$C$47)+(S34*G34*'Project Input'!$C$46)+(T34*G34*'Project Input'!$C$45),"") | W34: =IF(G34<>"",U34+P34,"") | Z34: =R34*G34 -> 0 | AA34: =S34*G34 -> 0 | AB34: =T34*G34 -> 0 | AC34: =SUM(Z34:AB34) -> 0 | AD34: =IF(G34<>"",AC34/'Project Input'!$C$41,"")
F35: Commissioning - Level 1, Level 2, Level 3 | G35: 1 | I35: =IF(G35<>"",O35/(1-('Project Input'!$C$20+'Project Input'!$C$21)),"") -> 357568.53 | J35: =IF(G35<>"",G35*I35,"") -> 357568.53 | K35: =IF(G35<>0,(U35/G35)/(1-('Project Input'!$C$20+'Project Input'!$C$21)),"") -> 6716329 | L35: =IF(G35<>0,K35*G35,"") -> 6716329 | M35: =IF(G35<>0,J35+L35,"") -> 7073897.5 | O35: 300000 | P35: =IF(G35<>"",G35*O35,"") -> 300000 | T35: 7000 | U35: =IF(G35<>"",(R35*G35*'Project Input'!$C$47)+(S35*G35*'Project Input'!$C$46)+(T35*G35*'Project Input'!$C$45),"") -> 5635000 | W35: =IF(G35<>"",U35+P35,"") -> 5935000 | Z35: =R35*G35 -> 0 | AA35: =S35*G35 -> 0 | AB35: =T35*G35 -> 7000 | AC35: =SUM(Z35:AB35) -> 7000 | AD35: =IF(G35<>"",AC35/'Project Input'!$C$41,"") -> 97.222222
F36: LOTO system | G36: 1 | I36: =IF(G36<>"",O36/(1-('Project Input'!$C$20+'Project Input'!$C$21)),"") -> 119189.51 | J36: =IF(G36<>"",G36*I36,"") -> 119189.51 | K36: =IF(G36<>0,(U36/G36)/(1-('Project Input'!$C$20+'Project Input'!$C$21)),"") -> 154350.42 | L36: =IF(G36<>0,K36*G36,"") -> 154350.42 | M36: =IF(G36<>0,J36+L36,"") -> 273539.93 | O36: 100000 | P36: =IF(G36<>"",G36*O36,"") -> 100000 | S36: 200 | U36: =IF(G36<>"",(R36*G36*'Project Input'!$C$47)+(S36*G36*'Project Input'!$C$46)+(T36*G36*'Project Input'!$C$45),"") -> 129500 | W36: =IF(G36<>"",U36+P36,"") -> 229500 | Z36: =R36*G36 -> 0 | AA36: =S36*G36 -> 200 | AB36: =T36*G36 -> 0 | AC36: =SUM(Z36:AB36) -> 200 | AD36: =IF(G36<>"",AC36/'Project Input'!$C$41,"") -> 2.7777778
I37: =IF(G37<>"",O37/(1-('Project Input'!$C$20+'Project Input'!$C$21)),"") | J37: =IF(G37<>"",G37*I37,"") | K37: =IF(G37<>0,(U37/G37)/(1-('Project Input'!$C$20+'Project Input'!$C$21)),"") | L37: =IF(G37<>0,K37*G37,"") | M37: =IF(G37<>0,J37+L37,"") | P37: =IF(G37<>"",G37*O37,"") | U37: =IF(G37<>"",(R37*G37*'Project Input'!$C$47)+(S37*G37*'Project Input'!$C$46)+(T37*G37*'Project Input'!$C$45),"") | W37: =IF(G37<>"",U37+P37,"") | Z37: =R37*G37 -> 0 | AA37: =S37*G37 -> 0 | AB37: =T37*G37 -> 0 | AC37: =SUM(Z37:AB37) -> 0 | AD37: =IF(G37<>"",AC37/'Project Input'!$C$41,"")
F38: Documentation, red-marks, manuals | G38: 1 | I38: =IF(G38<>"",O38/(1-('Project Input'!$C$20+'Project Input'!$C$21)),"") -> 119189.51 | J38: =IF(G38<>"",G38*I38,"") -> 119189.51 | K38: =IF(G38<>0,(U38/G38)/(1-('Project Input'!$C$20+'Project Input'!$C$21)),"") -> 287842.67 | L38: =IF(G38<>0,K38*G38,"") -> 287842.67 | M38: =IF(G38<>0,J38+L38,"") -> 407032.18 | O38: 100000 | P38: =IF(G38<>"",G38*O38,"") -> 100000 | T38: 300 | U38: =IF(G38<>"",(R38*G38*'Project Input'!$C$47)+(S38*G38*'Project Input'!$C$46)+(T38*G38*'Project Input'!$C$45),"") -> 241500 | W38: =IF(G38<>"",U38+P38,"") -> 341500 | Z38: =R38*G38 -> 0 | AA38: =S38*G38 -> 0 | AB38: =T38*G38 -> 300 | AC38: =SUM(Z38:AB38) -> 300 | AD38: =IF(G38<>"",AC38/'Project Input'!$C$41,"") -> 4.1666667
F39: Labeling of equipment | G39: 1 | I39: =IF(G39<>"",O39/(1-('Project Input'!$C$20+'Project Input'!$C$21)),"") -> 297973.78 | J39: =IF(G39<>"",G39*I39,"") -> 297973.78 | K39: =IF(G39<>0,(U39/G39)/(1-('Project Input'!$C$20+'Project Input'!$C$21)),"") -> 361442.19 | L39: =IF(G39<>0,K39*G39,"") -> 361442.19 | M39: =IF(G39<>0,J39+L39,"") -> 659415.97 | O39: 250000 | P39: =IF(G39<>"",G39*O39,"") -> 250000 | R39: 500 | U39: =IF(G39<>"",(R39*G39*'Project Input'!$C$47)+(S39*G39*'Project Input'!$C$46)+(T39*G39*'Project Input'!$C$45),"") -> 303250 | W39: =IF(G39<>"",U39+P39,"") -> 553250 | Z39: =R39*G39 -> 500 | AA39: =S39*G39 -> 0 | AB39: =T39*G39 -> 0 | AC39: =SUM(Z39:AB39) -> 500 | AD39: =IF(G39<>"",AC39/'Project Input'!$C$41,"") -> 6.9444444
I40: =IF(G40<>"",O40/(1-('Project Input'!$C$20+'Project Input'!$C$21)),"") | J40: =IF(G40<>"",G40*I40,"") | K40: =IF(G40<>0,(U40/G40)/(1-('Project Input'!$C$20+'Project Input'!$C$21)),"") | L40: =IF(G40<>0,K40*G40,"") | M40: =IF(G40<>0,J40+L40,"") | P40: =IF(G40<>"",G40*O40,"") | U40: =IF(G40<>"",(R40*G40*'Project Input'!$C$47)+(S40*G40*'Project Input'!$C$46)+(T40*G40*'Project Input'!$C$45),"") | W40: =IF(G40<>"",U40+P40,"") | Z40: =R40*G40 -> 0 | AA40: =S40*G40 -> 0 | AB40: =T40*G40 -> 0 | AC40: =SUM(Z40:AB40) -> 0 | AD40: =IF(G40<>"",AC40/'Project Input'!$C$41,"")
F41: lvl4 and lvl 5 support - Loadbanktesting | G41: 24 | I41: =IF(G41<>"",O41/(1-('Project Input'!$C$20+'Project Input'!$C$21)),"") -> 0 | J41: =IF(G41<>"",G41*I41,"") -> 0 | K41: =IF(G41<>0,(U41/G41)/(1-('Project Input'!$C$20+'Project Input'!$C$21)),"") -> 92610.25 | L41: =IF(G41<>0,K41*G41,"") -> 2222646 | M41: =IF(G41<>0,J41+L41,"") -> 2222646 | P41: =IF(G41<>"",G41*O41,"") -> 0 | S41: 120 | U41: =IF(G41<>"",(R41*G41*'Project Input'!$C$47)+(S41*G41*'Project Input'!$C$46)+(T41*G41*'Project Input'!$C$45),"") -> 1864800 | W41: =IF(G41<>"",U41+P41,"") -> 1864800 | Z41: =R41*G41 -> 0 | AA41: =S41*G41 -> 2880 | AB41: =T41*G41 -> 0 | AC41: =SUM(Z41:AB41) -> 2880 | AD41: =IF(G41<>"",AC41/'Project Input'!$C$41,"") -> 40
F42: Loandbanktesting of white space busbars | G42: 1 | I42: =IF(G42<>"",O42/(1-('Project Input'!$C$20+'Project Input'!$C$21)),"") -> 0 | J42: =IF(G42<>"",G42*I42,"") -> 0 | K42: =IF(G42<>0,(U42/G42)/(1-('Project Input'!$C$20+'Project Input'!$C$21)),"") -> 0 | L42: =IF(G42<>0,K42*G42,"") -> 0 | M42: =IF(G42<>0,J42+L42,"") -> 0 | P42: =IF(G42<>"",G42*O42,"") -> 0 | U42: =IF(G42<>"",(R42*G42*'Project Input'!$C$47)+(S42*G42*'Project Input'!$C$46)+(T42*G42*'Project Input'!$C$45),"") -> 0 | W42: =IF(G42<>"",U42+P42,"") -> 0 | Z42: =R42*G42 -> 0 | AA42: =S42*G42 -> 0 | AB42: =T42*G42 -> 0 | AC42: =SUM(Z42:AB42) -> 0 | AD42: =IF(G42<>"",AC42/'Project Input'!$C$41,"") -> 0
I43: =IF(G43<>"",O43/(1-('Project Input'!$C$20+'Project Input'!$C$21)),"") | J43: =IF(G43<>"",G43*I43,"") | K43: =IF(G43<>0,(U43/G43)/(1-('Project Input'!$C$20+'Project Input'!$C$21)),"") | L43: =IF(G43<>0,K43*G43,"") | M43: =IF(G43<>0,J43+L43,"") | P43: =IF(G43<>"",G43*O43,"") | U43: =IF(G43<>"",(R43*G43*'Project Input'!$C$47)+(S43*G43*'Project Input'!$C$46)+(T43*G43*'Project Input'!$C$45),"") | W43: =IF(G43<>"",U43+P43,"") | Z43: =R43*G43 -> 0 | AA43: =S43*G43 -> 0 | AB43: =T43*G43 -> 0 | AC43: =SUM(Z43:AB43) -> 0 | AD43: =IF(G43<>"",AC43/'Project Input'!$C$41,"")
I44: =IF(G44<>"",O44/(1-('Project Input'!$C$20+'Project Input'!$C$21)),"") | J44: =IF(G44<>"",G44*I44,"") | K44: =IF(G44<>0,(U44/G44)/(1-('Project Input'!$C$20+'Project Input'!$C$21)),"") | L44: =IF(G44<>0,K44*G44,"") | M44: =IF(G44<>0,J44+L44,"") | P44: =IF(G44<>"",G44*O44,"") | U44: =IF(G44<>"",(R44*G44*'Project Input'!$C$47)+(S44*G44*'Project Input'!$C$46)+(T44*G44*'Project Input'!$C$45),"") | W44: =IF(G44<>"",U44+P44,"") | Z44: =R44*G44 -> 0 | AA44: =S44*G44 -> 0 | AB44: =T44*G44 -> 0 | AC44: =SUM(Z44:AB44) -> 0 | AD44: =IF(G44<>"",AC44/'Project Input'!$C$41,"")
E45: 218 | F45: Site infrastruckture | L45: =IF(I45<>"",I45*K45,"") | M45: =SUBTOTAL(9,M46:M55) -> 6650953.5 | P45: =IF(G45<>"",G45*O45,"") | U45: =IF(G45<>"",(R45*G45*'Project Input'!$C$47)+(S45*G45*'Project Input'!$C$46)+(T45*G45*'Project Input'!$C$45),"") | W45: =IF(G45<>"",U45+P45,"") | Z45: =R45*G45 -> 0 | AA45: =S45*G45 -> 0 | AB45: =T45*G45 -> 0 | AC45: =SUM(Z45:AB45) -> 0 | AD45: =IF(G45<>"",AC45/'Project Input'!$C$41,"")
I46: =IF(G46<>"",O46/(1-('Project Input'!$C$20+'Project Input'!$C$21)),"") | J46: =IF(G46<>"",G46*I46,"") | K46: =IF(G46<>0,(U46/G46)/(1-('Project Input'!$C$20+'Project Input'!$C$21)),"") | L46: =IF(G46<>0,K46*G46,"") | M46: =IF(G46<>0,J46+L46,"") | P46: =IF(G46<>"",G46*O46,"") | U46: =IF(G46<>"",(R46*G46*'Project Input'!$C$47)+(S46*G46*'Project Input'!$C$46)+(T46*G46*'Project Input'!$C$45),"") | W46: =IF(G46<>"",U46+P46,"") | Z46: =R46*G46 -> 0 | AA46: =S46*G46 -> 0 | AB46: =T46*G46 -> 0 | AC46: =SUM(Z46:AB46) -> 0 | AD46: =IF(G46<>"",AC46/'Project Input'!$C$41,"")
F47: Workshop, container, waste management/ tent facilities inside, tool containers, transport of Velox equipment to/from site | G47: 1 | H47: ls | I47: =IF(G47<>"",O47/(1-('Project Input'!$C$20+'Project Input'!$C$21)),"") -> 2383790.2 | J47: =IF(G47<>"",G47*I47,"") -> 2383790.2 | K47: =IF(G47<>0,(U47/G47)/(1-('Project Input'!$C$20+'Project Input'!$C$21)),"") -> 1807211 | L47: =IF(G47<>0,K47*G47,"") -> 1807211 | M47: =IF(G47<>0,J47+L47,"") -> 4191001.2 | O47: 2000000 | P47: =IF(G47<>"",G47*O47,"") -> 2000000 | R47: 2500 | U47: =IF(G47<>"",(R47*G47*'Project Input'!$C$47)+(S47*G47*'Project Input'!$C$46)+(T47*G47*'Project Input'!$C$45),"") -> 1516250 | W47: =IF(G47<>"",U47+P47,"") -> 3516250 | Z47: =R47*G47 -> 2500 | AA47: =S47*G47 -> 0 | AB47: =T47*G47 -> 0 | AC47: =SUM(Z47:AB47) -> 2500 | AD47: =IF(G47<>"",AC47/'Project Input'!$C$41,"") -> 34.722222
F48: Scissor lifts - indoor | G48: 1 | H48: ls | I48: =IF(G48<>"",O48/(1-('Project Input'!$C$20+'Project Input'!$C$21)),"") -> 595947.56 | J48: =IF(G48<>"",G48*I48,"") -> 595947.56 | K48: =IF(G48<>0,(U48/G48)/(1-('Project Input'!$C$20+'Project Input'!$C$21)),"") -> 144576.88 | L48: =IF(G48<>0,K48*G48,"") -> 144576.88 | M48: =IF(G48<>0,J48+L48,"") -> 740524.43 | O48: 500000 | P48: =IF(G48<>"",G48*O48,"") -> 500000 | R48: 200 | U48: =IF(G48<>"",(R48*G48*'Project Input'!$C$47)+(S48*G48*'Project Input'!$C$46)+(T48*G48*'Project Input'!$C$45),"") -> 121300 | W48: =IF(G48<>"",U48+P48,"") -> 621300 | Z48: =R48*G48 -> 200 | AA48: =S48*G48 -> 0 | AB48: =T48*G48 -> 0 | AC48: =SUM(Z48:AB48) -> 200 | AD48: =IF(G48<>"",AC48/'Project Input'!$C$41,"") -> 2.7777778
F49: Scissor lifts - outdoor | G49: 1 | H49: ls | I49: =IF(G49<>"",O49/(1-('Project Input'!$C$20+'Project Input'!$C$21)),"") -> 476758.05 | J49: =IF(G49<>"",G49*I49,"") -> 476758.05 | K49: =IF(G49<>0,(U49/G49)/(1-('Project Input'!$C$20+'Project Input'!$C$21)),"") -> 144576.88 | L49: =IF(G49<>0,K49*G49,"") -> 144576.88 | M49: =IF(G49<>0,J49+L49,"") -> 621334.92 | O49: 400000 | P49: =IF(G49<>"",G49*O49,"") -> 400000 | R49: 200 | U49: =IF(G49<>"",(R49*G49*'Project Input'!$C$47)+(S49*G49*'Project Input'!$C$46)+(T49*G49*'Project Input'!$C$45),"") -> 121300 | W49: =IF(G49<>"",U49+P49,"") -> 521300 | Z49: =R49*G49 -> 200 | AA49: =S49*G49 -> 0 | AB49: =T49*G49 -> 0 | AC49: =SUM(Z49:AB49) -> 200 | AD49: =IF(G49<>"",AC49/'Project Input'!$C$41,"") -> 2.7777778
I50: =IF(G50<>"",O50/(1-('Project Input'!$C$20+'Project Input'!$C$21)),"") | J50: =IF(G50<>"",G50*I50,"") | K50: =IF(G50<>0,(U50/G50)/(1-('Project Input'!$C$20+'Project Input'!$C$21)),"") | L50: =IF(G50<>0,K50*G50,"") | M50: =IF(G50<>0,J50+L50,"") | P50: =IF(G50<>"",G50*O50,"") | U50: =IF(G50<>"",(R50*G50*'Project Input'!$C$47)+(S50*G50*'Project Input'!$C$46)+(T50*G50*'Project Input'!$C$45),"") | W50: =IF(G50<>"",U50+P50,"") | Z50: =R50*G50 -> 0 | AA50: =S50*G50 -> 0 | AB50: =T50*G50 -> 0 | AC50: =SUM(Z50:AB50) -> 0 | AD50: =IF(G50<>"",AC50/'Project Input'!$C$41,"")
F51: Forklift ( manitu 3500T, Manitu forklift) | G51: 2 | H51: un | I51: =IF(G51<>"",O51/(1-('Project Input'!$C$20+'Project Input'!$C$21)),"") -> 476758.05 | J51: =IF(G51<>"",G51*I51,"") -> 953516.09 | K51: =IF(G51<>0,(U51/G51)/(1-('Project Input'!$C$20+'Project Input'!$C$21)),"") -> 72288.439 | L51: =IF(G51<>0,K51*G51,"") -> 144576.88 | M51: =IF(G51<>0,J51+L51,"") -> 1098093 | O51: 400000 | P51: =IF(G51<>"",G51*O51,"") -> 800000 | R51: 100 | U51: =IF(G51<>"",(R51*G51*'Project Input'!$C$47)+(S51*G51*'Project Input'!$C$46)+(T51*G51*'Project Input'!$C$45),"") -> 121300 | W51: =IF(G51<>"",U51+P51,"") -> 921300 | Z51: =R51*G51 -> 200 | AA51: =S51*G51 -> 0 | AB51: =T51*G51 -> 0 | AC51: =SUM(Z51:AB51) -> 200 | AD51: =IF(G51<>"",AC51/'Project Input'!$C$41,"") -> 2.7777778
I52: =IF(G52<>"",O52/(1-('Project Input'!$C$20+'Project Input'!$C$21)),"") | J52: =IF(G52<>"",G52*I52,"") | K52: =IF(G52<>0,(U52/G52)/(1-('Project Input'!$C$20+'Project Input'!$C$21)),"") | L52: =IF(G52<>0,K52*G52,"") | M52: =IF(G52<>0,J52+L52,"") | P52: =IF(G52<>"",G52*O52,"") | U52: =IF(G52<>"",(R52*G52*'Project Input'!$C$47)+(S52*G52*'Project Input'!$C$46)+(T52*G52*'Project Input'!$C$45),"") | W52: =IF(G52<>"",U52+P52,"") | Z52: =R52*G52 -> 0 | AA52: =S52*G52 -> 0 | AB52: =T52*G52 -> 0 | AC52: =SUM(Z52:AB52) -> 0 | AD52: =IF(G52<>"",AC52/'Project Input'!$C$41,"")
I53: =IF(G53<>"",O53/(1-('Project Input'!$C$20+'Project Input'!$C$21)),"") | J53: =IF(G53<>"",G53*I53,"") | K53: =IF(G53<>0,(U53/G53)/(1-('Project Input'!$C$20+'Project Input'!$C$21)),"") | L53: =IF(G53<>0,K53*G53,"") | M53: =IF(G53<>0,J53+L53,"") | P53: =IF(G53<>"",G53*O53,"") | U53: =IF(G53<>"",(R53*G53*'Project Input'!$C$47)+(S53*G53*'Project Input'!$C$46)+(T53*G53*'Project Input'!$C$45),"") | W53: =IF(G53<>"",U53+P53,"") | Z53: =R53*G53 -> 0 | AA53: =S53*G53 -> 0 | AB53: =T53*G53 -> 0 | AC53: =SUM(Z53:AB53) -> 0 | AD53: =IF(G53<>"",AC53/'Project Input'!$C$41,"")
I54: =IF(G54<>"",O54/(1-('Project Input'!$C$20+'Project Input'!$C$21)),"") | J54: =IF(G54<>"",G54*I54,"") | K54: =IF(G54<>0,(U54/G54)/(1-('Project Input'!$C$20+'Project Input'!$C$21)),"") | L54: =IF(G54<>0,K54*G54,"") | M54: =IF(G54<>0,J54+L54,"") | P54: =IF(G54<>"",G54*O54,"") | U54: =IF(G54<>"",(R54*G54*'Project Input'!$C$47)+(S54*G54*'Project Input'!$C$46)+(T54*G54*'Project Input'!$C$45),"") | W54: =IF(G54<>"",U54+P54,"") | Z54: =R54*G54 -> 0 | AA54: =S54*G54 -> 0 | AB54: =T54*G54 -> 0 | AC54: =SUM(Z54:AB54) -> 0 | AD54: =IF(G54<>"",AC54/'Project Input'!$C$41,"")
I55: =IF(G55<>"",O55/(1-('Project Input'!$C$20+'Project Input'!$C$21)),"") | J55: =IF(G55<>"",G55*I55,"") | K55: =IF(G55<>0,(U55/G55)/(1-('Project Input'!$C$20+'Project Input'!$C$21)),"") | L55: =IF(G55<>0,K55*G55,"") | M55: =IF(G55<>0,J55+L55,"") | P55: =IF(G55<>"",G55*O55,"") | U55: =IF(G55<>"",(R55*G55*'Project Input'!$C$47)+(S55*G55*'Project Input'!$C$46)+(T55*G55*'Project Input'!$C$45),"") | W55: =IF(G55<>"",U55+P55,"") | Z55: =R55*G55 -> 0 | AA55: =S55*G55 -> 0 | AB55: =T55*G55 -> 0 | AC55: =SUM(Z55:AB55) -> 0 | AD55: =IF(G55<>"",AC55/'Project Input'!$C$41,"")
E56: 411 | F56: Containment | L56: =IF(I56<>"",I56*K56,"") | M56: =SUBTOTAL(9,M57:M112) -> 60103897 | P56: =IF(G56<>"",G56*O56,"") | U56: =IF(G56<>"",(R56*G56*'Project Input'!$C$47)+(S56*G56*'Project Input'!$C$46)+(T56*G56*'Project Input'!$C$45),"") | W56: =IF(G56<>"",U56+P56,"") | Z56: =R56*G56 -> 0 | AA56: =S56*G56 -> 0 | AB56: =T56*G56 -> 0 | AC56: =SUM(Z56:AB56) -> 0 | AD56: =IF(G56<>"",AC56/'Project Input'!$C$41,"")
I57: =IF(G57<>"",O57/(1-('Project Input'!$C$20+'Project Input'!$C$21)),"") | J57: =IF(G57<>"",G57*I57,"") | K57: =IF(G57<>0,(U57/G57)/(1-('Project Input'!$C$20+'Project Input'!$C$21)),"") | L57: =IF(G57<>0,K57*G57,"") | M57: =IF(G57<>0,J57+L57,"") | P57: =IF(G57<>"",G57*O57,"") | U57: =IF(G57<>"",(R57*G57*'Project Input'!$C$47)+(S57*G57*'Project Input'!$C$46)+(T57*G57*'Project Input'!$C$45),"") | W57: =IF(G57<>"",U57+P57,"") | Z57: =R57*G57 -> 0 | AA57: =S57*G57 -> 0 | AB57: =T57*G57 -> 0 | AC57: =SUM(Z57:AB57) -> 0 | AD57: =IF(G57<>"",AC57/'Project Input'!$C$41,"")
F58: Outside containment | I58: =IF(G58<>"",O58/(1-('Project Input'!$C$20+'Project Input'!$C$21)),"") | J58: =IF(G58<>"",G58*I58,"") | K58: =IF(G58<>0,(U58/G58)/(1-('Project Input'!$C$20+'Project Input'!$C$21)),"") | L58: =IF(G58<>0,K58*G58,"") | M58: =IF(G58<>0,J58+L58,"") | P58: =IF(G58<>"",G58*O58,"") | U58: =IF(G58<>"",(R58*G58*'Project Input'!$C$47)+(S58*G58*'Project Input'!$C$46)+(T58*G58*'Project Input'!$C$45),"") | W58: =IF(G58<>"",U58+P58,"") | Z58: =R58*G58 -> 0 | AA58: =S58*G58 -> 0 | AB58: =T58*G58 -> 0 | AC58: =SUM(Z58:AB58) -> 0 | AD58: =IF(G58<>"",AC58/'Project Input'!$C$41,"")
F59: Ladder HDG 900x125 | G59: =1100*1.2 -> 1320 | H59: m | I59: =IF(G59<>"",O59/(1-('Project Input'!$C$20+'Project Input'!$C$21)),"") -> 1668.6532 | J59: =IF(G59<>"",G59*I59,"") -> 2202622.2 | K59: =IF(G59<>0,(U59/G59)/(1-('Project Input'!$C$20+'Project Input'!$C$21)),"") -> 1048.1824 | L59: =IF(G59<>0,K59*G59,"") -> 1383600.7 | M59: =IF(G59<>0,J59+L59,"") -> 3586222.9 | O59: 1400 | P59: =IF(G59<>"",G59*O59,"") -> 1848000 | R59: 1.45 | U59: =IF(G59<>"",(R59*G59*'Project Input'!$C$47)+(S59*G59*'Project Input'!$C$46)+(T59*G59*'Project Input'!$C$45),"") -> 1160841 | W59: =IF(G59<>"",U59+P59,"") -> 3008841 | Z59: =R59*G59 -> 1914 | AA59: =S59*G59 -> 0 | AB59: =T59*G59 -> 0 | AC59: =SUM(Z59:AB59) -> 1914 | AD59: =IF(G59<>"",AC59/'Project Input'!$C$41,"") -> 26.583333
F60: Ladder HDG 600x125 | G60: 350 | H60: m | I60: =IF(G60<>"",O60/(1-('Project Input'!$C$20+'Project Input'!$C$21)),"") -> 1483.9094 | J60: =IF(G60<>"",G60*I60,"") -> 519368.3 | K60: =IF(G60<>0,(U60/G60)/(1-('Project Input'!$C$20+'Project Input'!$C$21)),"") -> 939.7497 | L60: =IF(G60<>0,K60*G60,"") -> 328912.4 | M60: =IF(G60<>0,J60+L60,"") -> 848280.69 | O60: 1245 | P60: =IF(G60<>"",G60*O60,"") -> 435750 | R60: 1.3 | U60: =IF(G60<>"",(R60*G60*'Project Input'!$C$47)+(S60*G60*'Project Input'!$C$46)+(T60*G60*'Project Input'!$C$45),"") -> 275957.5 | W60: =IF(G60<>"",U60+P60,"") -> 711707.5 | Z60: =R60*G60 -> 455 | AA60: =S60*G60 -> 0 | AB60: =T60*G60 -> 0 | AC60: =SUM(Z60:AB60) -> 455 | AD60: =IF(G60<>"",AC60/'Project Input'!$C$41,"") -> 6.3194444
F61: Ladder HDG 300x125 | G61: 350 | H61: m | I61: =IF(G61<>"",O61/(1-('Project Input'!$C$20+'Project Input'!$C$21)),"") -> 1311.0846 | J61: =IF(G61<>"",G61*I61,"") -> 458879.62 | K61: =IF(G61<>0,(U61/G61)/(1-('Project Input'!$C$20+'Project Input'!$C$21)),"") -> 831.31704 | L61: =IF(G61<>0,K61*G61,"") -> 290960.97 | M61: =IF(G61<>0,J61+L61,"") -> 749840.58 | O61: 1100 | P61: =IF(G61<>"",G61*O61,"") -> 385000 | R61: 1.15 | U61: =IF(G61<>"",(R61*G61*'Project Input'!$C$47)+(S61*G61*'Project Input'!$C$46)+(T61*G61*'Project Input'!$C$45),"") -> 244116.25 | W61: =IF(G61<>"",U61+P61,"") -> 629116.25 | Z61: =R61*G61 -> 402.5 | AA61: =S61*G61 -> 0 | AB61: =T61*G61 -> 0 | AC61: =SUM(Z61:AB61) -> 402.5 | AD61: =IF(G61<>"",AC61/'Project Input'!$C$41,"") -> 5.5902778
F62: Ladder HDG 100x125 | G62: 200 | H62: m | I62: =IF(G62<>"",O62/(1-('Project Input'!$C$20+'Project Input'!$C$21)),"") -> 1191.8951 | J62: =IF(G62<>"",G62*I62,"") -> 238379.02 | K62: =IF(G62<>0,(U62/G62)/(1-('Project Input'!$C$20+'Project Input'!$C$21)),"") -> 831.31704 | L62: =IF(G62<>0,K62*G62,"") -> 166263.41 | M62: =IF(G62<>0,J62+L62,"") -> 404642.43 | O62: 1000 | P62: =IF(G62<>"",G62*O62,"") -> 200000 | R62: 1.15 | U62: =IF(G62<>"",(R62*G62*'Project Input'!$C$47)+(S62*G62*'Project Input'!$C$46)+(T62*G62*'Project Input'!$C$45),"") -> 139495 | W62: =IF(G62<>"",U62+P62,"") -> 339495 | Z62: =R62*G62 -> 230 | AA62: =S62*G62 -> 0 | AB62: =T62*G62 -> 0 | AC62: =SUM(Z62:AB62) -> 230 | AD62: =IF(G62<>"",AC62/'Project Input'!$C$41,"") -> 3.1944444
I63: =IF(G63<>"",O63/(1-('Project Input'!$C$20+'Project Input'!$C$21)),"") | J63: =IF(G63<>"",G63*I63,"") | K63: =IF(G63<>0,(U63/G63)/(1-('Project Input'!$C$20+'Project Input'!$C$21)),"") | L63: =IF(G63<>0,K63*G63,"") | M63: =IF(G63<>0,J63+L63,"") | P63: =IF(G63<>"",G63*O63,"") | U63: =IF(G63<>"",(R63*G63*'Project Input'!$C$47)+(S63*G63*'Project Input'!$C$46)+(T63*G63*'Project Input'!$C$45),"") | W63: =IF(G63<>"",U63+P63,"") | Z63: =R63*G63 -> 0 | AA63: =S63*G63 -> 0 | AB63: =T63*G63 -> 0 | AC63: =SUM(Z63:AB63) -> 0 | AD63: =IF(G63<>"",AC63/'Project Input'!$C$41,"")
F64: Mechanical protections / Lids for cabletrays | H64: m | I64: =IF(G64<>"",O64/(1-('Project Input'!$C$20+'Project Input'!$C$21)),"") | J64: =IF(G64<>"",G64*I64,"") | K64: =IF(G64<>0,(U64/G64)/(1-('Project Input'!$C$20+'Project Input'!$C$21)),"") | L64: =IF(G64<>0,K64*G64,"") | M64: =IF(G64<>0,J64+L64,"") | P64: =IF(G64<>"",G64*O64,"") | U64: =IF(G64<>"",(R64*G64*'Project Input'!$C$47)+(S64*G64*'Project Input'!$C$46)+(T64*G64*'Project Input'!$C$45),"") | W64: =IF(G64<>"",U64+P64,"") | Z64: =R64*G64 -> 0 | AA64: =S64*G64 -> 0 | AB64: =T64*G64 -> 0 | AC64: =SUM(Z64:AB64) -> 0 | AD64: =IF(G64<>"",AC64/'Project Input'!$C$41,"")
I65: =IF(G65<>"",O65/(1-('Project Input'!$C$20+'Project Input'!$C$21)),"") | J65: =IF(G65<>"",G65*I65,"") | K65: =IF(G65<>0,(U65/G65)/(1-('Project Input'!$C$20+'Project Input'!$C$21)),"") | L65: =IF(G65<>0,K65*G65,"") | M65: =IF(G65<>0,J65+L65,"") | P65: =IF(G65<>"",G65*O65,"") | U65: =IF(G65<>"",(R65*G65*'Project Input'!$C$47)+(S65*G65*'Project Input'!$C$46)+(T65*G65*'Project Input'!$C$45),"") | W65: =IF(G65<>"",U65+P65,"") | Z65: =R65*G65 -> 0 | AA65: =S65*G65 -> 0 | AB65: =T65*G65 -> 0 | AC65: =SUM(Z65:AB65) -> 0 | AD65: =IF(G65<>"",AC65/'Project Input'!$C$41,"")
I66: =IF(G66<>"",O66/(1-('Project Input'!$C$20+'Project Input'!$C$21)),"") | J66: =IF(G66<>"",G66*I66,"") | K66: =IF(G66<>0,(U66/G66)/(1-('Project Input'!$C$20+'Project Input'!$C$21)),"") | L66: =IF(G66<>0,K66*G66,"") | M66: =IF(G66<>0,J66+L66,"") | P66: =IF(G66<>"",G66*O66,"") | U66: =IF(G66<>"",(R66*G66*'Project Input'!$C$47)+(S66*G66*'Project Input'!$C$46)+(T66*G66*'Project Input'!$C$45),"") | W66: =IF(G66<>"",U66+P66,"") | Z66: =R66*G66 -> 0 | AA66: =S66*G66 -> 0 | AB66: =T66*G66 -> 0 | AC66: =SUM(Z66:AB66) -> 0 | AD66: =IF(G66<>"",AC66/'Project Input'!$C$41,"")
F67: Cable tray HDG 300x100 - BMS | G67: 1000 | H67: m | I67: =IF(G67<>"",O67/(1-('Project Input'!$C$20+'Project Input'!$C$21)),"") -> 756.8534 | J67: =IF(G67<>"",G67*I67,"") -> 756853.4 | K67: =IF(G67<>0,(U67/G67)/(1-('Project Input'!$C$20+'Project Input'!$C$21)),"") -> 469.87485 | L67: =IF(G67<>0,K67*G67,"") -> 469874.85 | M67: =IF(G67<>0,J67+L67,"") -> 1226728.2 | O67: 635 | P67: =IF(G67<>"",G67*O67,"") -> 635000 | R67: 0.65 | U67: =IF(G67<>"",(R67*G67*'Project Input'!$C$47)+(S67*G67*'Project Input'!$C$46)+(T67*G67*'Project Input'!$C$45),"") -> 394225 | W67: =IF(G67<>"",U67+P67,"") -> 1029225 | Z67: =R67*G67 -> 650 | AA67: =S67*G67 -> 0 | AB67: =T67*G67 -> 0 | AC67: =SUM(Z67:AB67) -> 650 | AD67: =IF(G67<>"",AC67/'Project Input'!$C$41,"") -> 9.0277778
F68: Cable tray HDG 300x100 - SPL | G68: 1000 | H68: m | I68: =IF(G68<>"",O68/(1-('Project Input'!$C$20+'Project Input'!$C$21)),"") -> 756.8534 | J68: =IF(G68<>"",G68*I68,"") -> 756853.4 | K68: =IF(G68<>0,(U68/G68)/(1-('Project Input'!$C$20+'Project Input'!$C$21)),"") -> 469.87485 | L68: =IF(G68<>0,K68*G68,"") -> 469874.85 | M68: =IF(G68<>0,J68+L68,"") -> 1226728.2 | O68: 635 | P68: =IF(G68<>"",G68*O68,"") -> 635000 | R68: 0.65 | U68: =IF(G68<>"",(R68*G68*'Project Input'!$C$47)+(S68*G68*'Project Input'!$C$46)+(T68*G68*'Project Input'!$C$45),"") -> 394225 | W68: =IF(G68<>"",U68+P68,"") -> 1029225 | Z68: =R68*G68 -> 650 | AA68: =S68*G68 -> 0 | AB68: =T68*G68 -> 0 | AC68: =SUM(Z68:AB68) -> 650 | AD68: =IF(G68<>"",AC68/'Project Input'!$C$41,"") -> 9.0277778
F69: Cable trays 100x50 - light tray | G69: 1000 | H69: m | I69: =IF(G69<>"",O69/(1-('Project Input'!$C$20+'Project Input'!$C$21)),"") -> 595.94756 | J69: =IF(G69<>"",G69*I69,"") -> 595947.56 | K69: =IF(G69<>0,(U69/G69)/(1-('Project Input'!$C$20+'Project Input'!$C$21)),"") -> 433.73063 | L69: =IF(G69<>0,K69*G69,"") -> 433730.63 | M69: =IF(G69<>0,J69+L69,"") -> 1029678.2 | O69: 500 | P69: =IF(G69<>"",G69*O69,"") -> 500000 | R69: 0.6 | U69: =IF(G69<>"",(R69*G69*'Project Input'!$C$47)+(S69*G69*'Project Input'!$C$46)+(T69*G69*'Project Input'!$C$45),"") -> 363900 | W69: =IF(G69<>"",U69+P69,"") -> 863900 | Z69: =R69*G69 -> 600 | AA69: =S69*G69 -> 0 | AB69: =T69*G69 -> 0 | AC69: =SUM(Z69:AB69) -> 600 | AD69: =IF(G69<>"",AC69/'Project Input'!$C$41,"") -> 8.3333333
I70: =IF(G70<>"",O70/(1-('Project Input'!$C$20+'Project Input'!$C$21)),"") | J70: =IF(G70<>"",G70*I70,"") | K70: =IF(G70<>0,(U70/G70)/(1-('Project Input'!$C$20+'Project Input'!$C$21)),"") | L70: =IF(G70<>0,K70*G70,"") | M70: =IF(G70<>0,J70+L70,"") | P70: =IF(G70<>"",G70*O70,"") | U70: =IF(G70<>"",(R70*G70*'Project Input'!$C$47)+(S70*G70*'Project Input'!$C$46)+(T70*G70*'Project Input'!$C$45),"") | W70: =IF(G70<>"",U70+P70,"") | Z70: =R70*G70 -> 0 | AA70: =S70*G70 -> 0 | AB70: =T70*G70 -> 0 | AC70: =SUM(Z70:AB70) -> 0 | AD70: =IF(G70<>"",AC70/'Project Input'!$C$41,"")
I71: =IF(G71<>"",O71/(1-('Project Input'!$C$20+'Project Input'!$C$21)),"") | J71: =IF(G71<>"",G71*I71,"") | K71: =IF(G71<>0,(U71/G71)/(1-('Project Input'!$C$20+'Project Input'!$C$21)),"") | L71: =IF(G71<>0,K71*G71,"") | M71: =IF(G71<>0,J71+L71,"") | P71: =IF(G71<>"",G71*O71,"") | U71: =IF(G71<>"",(R71*G71*'Project Input'!$C$47)+(S71*G71*'Project Input'!$C$46)+(T71*G71*'Project Input'!$C$45),"") | W71: =IF(G71<>"",U71+P71,"") | Z71: =R71*G71 -> 0 | AA71: =S71*G71 -> 0 | AB71: =T71*G71 -> 0 | AC71: =SUM(Z71:AB71) -> 0 | AD71: =IF(G71<>"",AC71/'Project Input'!$C$41,"")
F72: Outside roof containment | I72: =IF(G72<>"",O72/(1-('Project Input'!$C$20+'Project Input'!$C$21)),"") | J72: =IF(G72<>"",G72*I72,"") | K72: =IF(G72<>0,(U72/G72)/(1-('Project Input'!$C$20+'Project Input'!$C$21)),"") | L72: =IF(G72<>0,K72*G72,"") | M72: =IF(G72<>0,J72+L72,"") | P72: =IF(G72<>"",G72*O72,"") | U72: =IF(G72<>"",(R72*G72*'Project Input'!$C$47)+(S72*G72*'Project Input'!$C$46)+(T72*G72*'Project Input'!$C$45),"") | W72: =IF(G72<>"",U72+P72,"") | Z72: =R72*G72 -> 0 | AA72: =S72*G72 -> 0 | AB72: =T72*G72 -> 0 | AC72: =SUM(Z72:AB72) -> 0 | AD72: =IF(G72<>"",AC72/'Project Input'!$C$41,"")
F73: Ladder HDG 600x125 | G73: 600 | H73: m | I73: =IF(G73<>"",O73/(1-('Project Input'!$C$20+'Project Input'!$C$21)),"") -> 1483.9094 | J73: =IF(G73<>"",G73*I73,"") -> 890345.65 | K73: =IF(G73<>0,(U73/G73)/(1-('Project Input'!$C$20+'Project Input'!$C$21)),"") -> 939.7497 | L73: =IF(G73<>0,K73*G73,"") -> 563849.82 | M73: =IF(G73<>0,J73+L73,"") -> 1454195.5 | O73: 1245 | P73: =IF(G73<>"",G73*O73,"") -> 747000 | R73: 1.3 | U73: =IF(G73<>"",(R73*G73*'Project Input'!$C$47)+(S73*G73*'Project Input'!$C$46)+(T73*G73*'Project Input'!$C$45),"") -> 473070 | W73: =IF(G73<>"",U73+P73,"") -> 1220070 | Z73: =R73*G73 -> 780 | AA73: =S73*G73 -> 0 | AB73: =T73*G73 -> 0 | AC73: =SUM(Z73:AB73) -> 780 | AD73: =IF(G73<>"",AC73/'Project Input'!$C$41,"") -> 10.833333
F74: Ladder HDG 300x125 | G74: 800 | H74: m | I74: =IF(G74<>"",O74/(1-('Project Input'!$C$20+'Project Input'!$C$21)),"") -> 1311.0846 | J74: =IF(G74<>"",G74*I74,"") -> 1048867.7 | K74: =IF(G74<>0,(U74/G74)/(1-('Project Input'!$C$20+'Project Input'!$C$21)),"") -> 831.31704 | L74: =IF(G74<>0,K74*G74,"") -> 665053.64 | M74: =IF(G74<>0,J74+L74,"") -> 1713921.3 | O74: 1100 | P74: =IF(G74<>"",G74*O74,"") -> 880000 | R74: 1.15 | U74: =IF(G74<>"",(R74*G74*'Project Input'!$C$47)+(S74*G74*'Project Input'!$C$46)+(T74*G74*'Project Input'!$C$45),"") -> 557980 | W74: =IF(G74<>"",U74+P74,"") -> 1437980 | Z74: =R74*G74 -> 920 | AA74: =S74*G74 -> 0 | AB74: =T74*G74 -> 0 | AC74: =SUM(Z74:AB74) -> 920 | AD74: =IF(G74<>"",AC74/'Project Input'!$C$41,"") -> 12.777778
I75: =IF(G75<>"",O75/(1-('Project Input'!$C$20+'Project Input'!$C$21)),"") | J75: =IF(G75<>"",G75*I75,"") | K75: =IF(G75<>0,(U75/G75)/(1-('Project Input'!$C$20+'Project Input'!$C$21)),"") | L75: =IF(G75<>0,K75*G75,"") | M75: =IF(G75<>0,J75+L75,"") | P75: =IF(G75<>"",G75*O75,"") | U75: =IF(G75<>"",(R75*G75*'Project Input'!$C$47)+(S75*G75*'Project Input'!$C$46)+(T75*G75*'Project Input'!$C$45),"") | W75: =IF(G75<>"",U75+P75,"") | Z75: =R75*G75 -> 0 | AA75: =S75*G75 -> 0 | AB75: =T75*G75 -> 0 | AC75: =SUM(Z75:AB75) -> 0 | AD75: =IF(G75<>"",AC75/'Project Input'!$C$41,"")
F76: Cable tray HDG 300x100 - BMS | G76: 750 | H76: m | I76: =IF(G76<>"",O76/(1-('Project Input'!$C$20+'Project Input'!$C$21)),"") -> 756.8534 | J76: =IF(G76<>"",G76*I76,"") -> 567640.05 | K76: =IF(G76<>0,(U76/G76)/(1-('Project Input'!$C$20+'Project Input'!$C$21)),"") -> 469.87485 | L76: =IF(G76<>0,K76*G76,"") -> 352406.14 | M76: =IF(G76<>0,J76+L76,"") -> 920046.19 | O76: 635 | P76: =IF(G76<>"",G76*O76,"") -> 476250 | R76: 0.65 | U76: =IF(G76<>"",(R76*G76*'Project Input'!$C$47)+(S76*G76*'Project Input'!$C$46)+(T76*G76*'Project Input'!$C$45),"") -> 295668.75 | W76: =IF(G76<>"",U76+P76,"") -> 771918.75 | Z76: =R76*G76 -> 487.5 | AA76: =S76*G76 -> 0 | AB76: =T76*G76 -> 0 | AC76: =SUM(Z76:AB76) -> 487.5 | AD76: =IF(G76<>"",AC76/'Project Input'!$C$41,"") -> 6.7708333
F77: Cable tray HDG 300x100 - SPL | G77: 750 | H77: m | I77: =IF(G77<>"",O77/(1-('Project Input'!$C$20+'Project Input'!$C$21)),"") -> 756.8534 | J77: =IF(G77<>"",G77*I77,"") -> 567640.05 | K77: =IF(G77<>0,(U77/G77)/(1-('Project Input'!$C$20+'Project Input'!$C$21)),"") -> 469.87485 | L77: =IF(G77<>0,K77*G77,"") -> 352406.14 | M77: =IF(G77<>0,J77+L77,"") -> 920046.19 | O77: 635 | P77: =IF(G77<>"",G77*O77,"") -> 476250 | R77: 0.65 | U77: =IF(G77<>"",(R77*G77*'Project Input'!$C$47)+(S77*G77*'Project Input'!$C$46)+(T77*G77*'Project Input'!$C$45),"") -> 295668.75 | W77: =IF(G77<>"",U77+P77,"") -> 771918.75 | Z77: =R77*G77 -> 487.5 | AA77: =S77*G77 -> 0 | AB77: =T77*G77 -> 0 | AC77: =SUM(Z77:AB77) -> 487.5 | AD77: =IF(G77<>"",AC77/'Project Input'!$C$41,"") -> 6.7708333
F78: Cable trays 100x50 - light tray | G78: 750 | H78: m | I78: =IF(G78<>"",O78/(1-('Project Input'!$C$20+'Project Input'!$C$21)),"") -> 595.94756 | J78: =IF(G78<>"",G78*I78,"") -> 446960.67 | K78: =IF(G78<>0,(U78/G78)/(1-('Project Input'!$C$20+'Project Input'!$C$21)),"") -> 433.73063 | L78: =IF(G78<>0,K78*G78,"") -> 325297.97 | M78: =IF(G78<>0,J78+L78,"") -> 772258.64 | O78: 500 | P78: =IF(G78<>"",G78*O78,"") -> 375000 | R78: 0.6 | U78: =IF(G78<>"",(R78*G78*'Project Input'!$C$47)+(S78*G78*'Project Input'!$C$46)+(T78*G78*'Project Input'!$C$45),"") -> 272925 | W78: =IF(G78<>"",U78+P78,"") -> 647925 | Z78: =R78*G78 -> 450 | AA78: =S78*G78 -> 0 | AB78: =T78*G78 -> 0 | AC78: =SUM(Z78:AB78) -> 450 | AD78: =IF(G78<>"",AC78/'Project Input'!$C$41,"") -> 6.25
I79: =IF(G79<>"",O79/(1-('Project Input'!$C$20+'Project Input'!$C$21)),"") | J79: =IF(G79<>"",G79*I79,"") | K79: =IF(G79<>0,(U79/G79)/(1-('Project Input'!$C$20+'Project Input'!$C$21)),"") | L79: =IF(G79<>0,K79*G79,"") | M79: =IF(G79<>0,J79+L79,"") | P79: =IF(G79<>"",G79*O79,"") | U79: =IF(G79<>"",(R79*G79*'Project Input'!$C$47)+(S79*G79*'Project Input'!$C$46)+(T79*G79*'Project Input'!$C$45),"") | W79: =IF(G79<>"",U79+P79,"") | Z79: =R79*G79 -> 0 | AA79: =S79*G79 -> 0 | AB79: =T79*G79 -> 0 | AC79: =SUM(Z79:AB79) -> 0 | AD79: =IF(G79<>"",AC79/'Project Input'!$C$41,"")
F80: Technical and white space | I80: =IF(G80<>"",O80/(1-('Project Input'!$C$20+'Project Input'!$C$21)),"") | J80: =IF(G80<>"",G80*I80,"") | K80: =IF(G80<>0,(U80/G80)/(1-('Project Input'!$C$20+'Project Input'!$C$21)),"") | L80: =IF(G80<>0,K80*G80,"") | M80: =IF(G80<>0,J80+L80,"") | P80: =IF(G80<>"",G80*O80,"") | U80: =IF(G80<>"",(R80*G80*'Project Input'!$C$47)+(S80*G80*'Project Input'!$C$46)+(T80*G80*'Project Input'!$C$45),"") | W80: =IF(G80<>"",U80+P80,"") | Z80: =R80*G80 -> 0 | AA80: =S80*G80 -> 0 | AB80: =T80*G80 -> 0 | AC80: =SUM(Z80:AB80) -> 0 | AD80: =IF(G80<>"",AC80/'Project Input'!$C$41,"")
F81: Ladder PG 600x100mm | G81: 3000 | H81: m | I81: =IF(G81<>"",O81/(1-('Project Input'!$C$20+'Project Input'!$C$21)),"") -> 1162.0977 | J81: =IF(G81<>"",G81*I81,"") -> 3486293.2 | K81: =IF(G81<>0,(U81/G81)/(1-('Project Input'!$C$20+'Project Input'!$C$21)),"") -> 2168.6532 | L81: =IF(G81<>0,K81*G81,"") -> 6505959.5 | M81: =IF(G81<>0,J81+L81,"") -> 9992252.7 | O81: 975 | P81: =IF(G81<>"",G81*O81,"") -> 2925000 | R81: 3 | U81: =IF(G81<>"",(R81*G81*'Project Input'!$C$47)+(S81*G81*'Project Input'!$C$46)+(T81*G81*'Project Input'!$C$45),"") -> 5458500 | W81: =IF(G81<>"",U81+P81,"") -> 8383500 | Z81: =R81*G81 -> 9000 | AA81: =S81*G81 -> 0 | AB81: =T81*G81 -> 0 | AC81: =SUM(Z81:AB81) -> 9000 | AD81: =IF(G81<>"",AC81/'Project Input'!$C$41,"") -> 125
F82: Ladder PG 300x100mm | G82: =24*45+950+270 -> 2300 | H82: m | I82: =IF(G82<>"",O82/(1-('Project Input'!$C$20+'Project Input'!$C$21)),"") -> 1179.9762 | J82: =IF(G82<>"",G82*I82,"") -> 2713945.2 | K82: =IF(G82<>0,(U82/G82)/(1-('Project Input'!$C$20+'Project Input'!$C$21)),"") -> 831.31704 | L82: =IF(G82<>0,K82*G82,"") -> 1912029.2 | M82: =IF(G82<>0,J82+L82,"") -> 4625974.4 | O82: 990 | P82: =IF(G82<>"",G82*O82,"") -> 2277000 | R82: 1.15 | U82: =IF(G82<>"",(R82*G82*'Project Input'!$C$47)+(S82*G82*'Project Input'!$C$46)+(T82*G82*'Project Input'!$C$45),"") -> 1604192.5 | W82: =IF(G82<>"",U82+P82,"") -> 3881192.5 | Z82: =R82*G82 -> 2645 | AA82: =S82*G82 -> 0 | AB82: =T82*G82 -> 0 | AC82: =SUM(Z82:AB82) -> 2645 | AD82: =IF(G82<>"",AC82/'Project Input'!$C$41,"") -> 36.736111
I83: =IF(G83<>"",O83/(1-('Project Input'!$C$20+'Project Input'!$C$21)),"") | J83: =IF(G83<>"",G83*I83,"") | K83: =IF(G83<>0,(U83/G83)/(1-('Project Input'!$C$20+'Project Input'!$C$21)),"") | L83: =IF(G83<>0,K83*G83,"") | M83: =IF(G83<>0,J83+L83,"") | P83: =IF(G83<>"",G83*O83,"") | U83: =IF(G83<>"",(R83*G83*'Project Input'!$C$47)+(S83*G83*'Project Input'!$C$46)+(T83*G83*'Project Input'!$C$45),"") | W83: =IF(G83<>"",U83+P83,"") | Z83: =R83*G83 -> 0 | AA83: =S83*G83 -> 0 | AB83: =T83*G83 -> 0 | AC83: =SUM(Z83:AB83) -> 0 | AD83: =IF(G83<>"",AC83/'Project Input'!$C$41,"")
F84: Basket Mesh 900x150 - Fiber | G84: 600 | H84: m | I84: =IF(G84<>"",O84/(1-('Project Input'!$C$20+'Project Input'!$C$21)),"") -> 1871.2753 | J84: =IF(G84<>"",G84*I84,"") -> 1122765.2 | K84: =IF(G84<>0,(U84/G84)/(1-('Project Input'!$C$20+'Project Input'!$C$21)),"") -> 1084.3266 | L84: =IF(G84<>0,K84*G84,"") -> 650595.95 | M84: =IF(G84<>0,J84+L84,"") -> 1773361.1 | O84: 1570 | P84: =IF(G84<>"",G84*O84,"") -> 942000 | R84: 1.5 | U84: =IF(G84<>"",(R84*G84*'Project Input'!$C$47)+(S84*G84*'Project Input'!$C$46)+(T84*G84*'Project Input'!$C$45),"") -> 545850 | W84: =IF(G84<>"",U84+P84,"") -> 1487850 | Z84: =R84*G84 -> 900 | AA84: =S84*G84 -> 0 | AB84: =T84*G84 -> 0 | AC84: =SUM(Z84:AB84) -> 900 | AD84: =IF(G84<>"",AC84/'Project Input'!$C$41,"") -> 12.5
F85: Basket Mesh 300x100 | H85: m | I85: =IF(G85<>"",O85/(1-('Project Input'!$C$20+'Project Input'!$C$21)),"") | J85: =IF(G85<>"",G85*I85,"") | K85: =IF(G85<>0,(U85/G85)/(1-('Project Input'!$C$20+'Project Input'!$C$21)),"") | L85: =IF(G85<>0,K85*G85,"") | M85: =IF(G85<>0,J85+L85,"") | P85: =IF(G85<>"",G85*O85,"") | U85: =IF(G85<>"",(R85*G85*'Project Input'!$C$47)+(S85*G85*'Project Input'!$C$46)+(T85*G85*'Project Input'!$C$45),"") | W85: =IF(G85<>"",U85+P85,"") | Z85: =R85*G85 -> 0 | AA85: =S85*G85 -> 0 | AB85: =T85*G85 -> 0 | AC85: =SUM(Z85:AB85) -> 0 | AD85: =IF(G85<>"",AC85/'Project Input'!$C$41,"")
F86: Basket Mesh 75x60 | H86: m | I86: =IF(G86<>"",O86/(1-('Project Input'!$C$20+'Project Input'!$C$21)),"") | J86: =IF(G86<>"",G86*I86,"") | K86: =IF(G86<>0,(U86/G86)/(1-('Project Input'!$C$20+'Project Input'!$C$21)),"") | L86: =IF(G86<>0,K86*G86,"") | M86: =IF(G86<>0,J86+L86,"") | P86: =IF(G86<>"",G86*O86,"") | U86: =IF(G86<>"",(R86*G86*'Project Input'!$C$47)+(S86*G86*'Project Input'!$C$46)+(T86*G86*'Project Input'!$C$45),"") | W86: =IF(G86<>"",U86+P86,"") | Z86: =R86*G86 -> 0 | AA86: =S86*G86 -> 0 | AB86: =T86*G86 -> 0 | AC86: =SUM(Z86:AB86) -> 0 | AD86: =IF(G86<>"",AC86/'Project Input'!$C$41,"")
I87: =IF(G87<>"",O87/(1-('Project Input'!$C$20+'Project Input'!$C$21)),"") | J87: =IF(G87<>"",G87*I87,"") | K87: =IF(G87<>0,(U87/G87)/(1-('Project Input'!$C$20+'Project Input'!$C$21)),"") | L87: =IF(G87<>0,K87*G87,"") | M87: =IF(G87<>0,J87+L87,"") | P87: =IF(G87<>"",G87*O87,"") | U87: =IF(G87<>"",(R87*G87*'Project Input'!$C$47)+(S87*G87*'Project Input'!$C$46)+(T87*G87*'Project Input'!$C$45),"") | W87: =IF(G87<>"",U87+P87,"") | Z87: =R87*G87 -> 0 | AA87: =S87*G87 -> 0 | AB87: =T87*G87 -> 0 | AC87: =SUM(Z87:AB87) -> 0 | AD87: =IF(G87<>"",AC87/'Project Input'!$C$41,"")
F88: Cable trays 600x100mm | G88: 3000 | H88: m | I88: =IF(G88<>"",O88/(1-('Project Input'!$C$20+'Project Input'!$C$21)),"") -> 995.23242 | J88: =IF(G88<>"",G88*I88,"") -> 2985697.3 | K88: =IF(G88<>0,(U88/G88)/(1-('Project Input'!$C$20+'Project Input'!$C$21)),"") -> 939.7497 | L88: =IF(G88<>0,K88*G88,"") -> 2819249.1 | M88: =IF(G88<>0,J88+L88,"") -> 5804946.4 | O88: 835 | P88: =IF(G88<>"",G88*O88,"") -> 2505000 | R88: 1.3 | U88: =IF(G88<>"",(R88*G88*'Project Input'!$C$47)+(S88*G88*'Project Input'!$C$46)+(T88*G88*'Project Input'!$C$45),"") -> 2365350 | W88: =IF(G88<>"",U88+P88,"") -> 4870350 | Z88: =R88*G88 -> 3900 | AA88: =S88*G88 -> 0 | AB88: =T88*G88 -> 0 | AC88: =SUM(Z88:AB88) -> 3900 | AD88: =IF(G88<>"",AC88/'Project Input'!$C$41,"") -> 54.166667
F89: Cable trays 300x100mm - BMS | G89: 2250 | H89: m | I89: =IF(G89<>"",O89/(1-('Project Input'!$C$20+'Project Input'!$C$21)),"") -> 756.8534 | J89: =IF(G89<>"",G89*I89,"") -> 1702920.1 | K89: =IF(G89<>0,(U89/G89)/(1-('Project Input'!$C$20+'Project Input'!$C$21)),"") -> 469.87485 | L89: =IF(G89<>0,K89*G89,"") -> 1057218.4 | M89: =IF(G89<>0,J89+L89,"") -> 2760138.6 | O89: 635 | P89: =IF(G89<>"",G89*O89,"") -> 1428750 | R89: 0.65 | U89: =IF(G89<>"",(R89*G89*'Project Input'!$C$47)+(S89*G89*'Project Input'!$C$46)+(T89*G89*'Project Input'!$C$45),"") -> 887006.25 | W89: =IF(G89<>"",U89+P89,"") -> 2315756.2 | Z89: =R89*G89 -> 1462.5 | AA89: =S89*G89 -> 0 | AB89: =T89*G89 -> 0 | AC89: =SUM(Z89:AB89) -> 1462.5 | AD89: =IF(G89<>"",AC89/'Project Input'!$C$41,"") -> 20.3125
F90: Cable trays 300x100mm - SPL | G90: 2250 | H90: m | I90: =IF(G90<>"",O90/(1-('Project Input'!$C$20+'Project Input'!$C$21)),"") -> 756.8534 | J90: =IF(G90<>"",G90*I90,"") -> 1702920.1 | K90: =IF(G90<>0,(U90/G90)/(1-('Project Input'!$C$20+'Project Input'!$C$21)),"") -> 469.87485 | L90: =IF(G90<>0,K90*G90,"") -> 1057218.4 | M90: =IF(G90<>0,J90+L90,"") -> 2760138.6 | O90: 635 | P90: =IF(G90<>"",G90*O90,"") -> 1428750 | R90: 0.65 | U90: =IF(G90<>"",(R90*G90*'Project Input'!$C$47)+(S90*G90*'Project Input'!$C$46)+(T90*G90*'Project Input'!$C$45),"") -> 887006.25 | W90: =IF(G90<>"",U90+P90,"") -> 2315756.2 | Z90: =R90*G90 -> 1462.5 | AA90: =S90*G90 -> 0 | AB90: =T90*G90 -> 0 | AC90: =SUM(Z90:AB90) -> 1462.5 | AD90: =IF(G90<>"",AC90/'Project Input'!$C$41,"") -> 20.3125
F91: Cable trays 100x50 - light tray | G91: 1200 | H91: m | I91: =IF(G91<>"",O91/(1-('Project Input'!$C$20+'Project Input'!$C$21)),"") -> 595.94756 | J91: =IF(G91<>"",G91*I91,"") -> 715137.07 | K91: =IF(G91<>0,(U91/G91)/(1-('Project Input'!$C$20+'Project Input'!$C$21)),"") -> 433.73063 | L91: =IF(G91<>0,K91*G91,"") -> 520476.76 | M91: =IF(G91<>0,J91+L91,"") -> 1235613.8 | O91: 500 | P91: =IF(G91<>"",G91*O91,"") -> 600000 | R91: 0.6 | U91: =IF(G91<>"",(R91*G91*'Project Input'!$C$47)+(S91*G91*'Project Input'!$C$46)+(T91*G91*'Project Input'!$C$45),"") -> 436680 | W91: =IF(G91<>"",U91+P91,"") -> 1036680 | Z91: =R91*G91 -> 720 | AA91: =S91*G91 -> 0 | AB91: =T91*G91 -> 0 | AC91: =SUM(Z91:AB91) -> 720 | AD91: =IF(G91<>"",AC91/'Project Input'!$C$41,"") -> 10
I92: =IF(G92<>"",O92/(1-('Project Input'!$C$20+'Project Input'!$C$21)),"") | J92: =IF(G92<>"",G92*I92,"") | K92: =IF(G92<>0,(U92/G92)/(1-('Project Input'!$C$20+'Project Input'!$C$21)),"") | L92: =IF(G92<>0,K92*G92,"") | M92: =IF(G92<>0,J92+L92,"") | P92: =IF(G92<>"",G92*O92,"") | U92: =IF(G92<>"",(R92*G92*'Project Input'!$C$47)+(S92*G92*'Project Input'!$C$46)+(T92*G92*'Project Input'!$C$45),"") | W92: =IF(G92<>"",U92+P92,"") | Z92: =R92*G92 -> 0 | AA92: =S92*G92 -> 0 | AB92: =T92*G92 -> 0 | AC92: =SUM(Z92:AB92) -> 0 | AD92: =IF(G92<>"",AC92/'Project Input'!$C$41,"")
F93: Secundary cable trays to Instruments | I93: =IF(G93<>"",O93/(1-('Project Input'!$C$20+'Project Input'!$C$21)),"") | J93: =IF(G93<>"",G93*I93,"") | K93: =IF(G93<>0,(U93/G93)/(1-('Project Input'!$C$20+'Project Input'!$C$21)),"") | L93: =IF(G93<>0,K93*G93,"") | M93: =IF(G93<>0,J93+L93,"") | P93: =IF(G93<>"",G93*O93,"") | U93: =IF(G93<>"",(R93*G93*'Project Input'!$C$47)+(S93*G93*'Project Input'!$C$46)+(T93*G93*'Project Input'!$C$45),"") | W93: =IF(G93<>"",U93+P93,"") | Z93: =R93*G93 -> 0 | AA93: =S93*G93 -> 0 | AB93: =T93*G93 -> 0 | AC93: =SUM(Z93:AB93) -> 0 | AD93: =IF(G93<>"",AC93/'Project Input'!$C$41,"")
F94: Cable mesh 300x100mm | G94: 1000 | H94: m | I94: =IF(G94<>"",O94/(1-('Project Input'!$C$20+'Project Input'!$C$21)),"") -> 810.48868 | J94: =IF(G94<>"",G94*I94,"") -> 810488.68 | K94: =IF(G94<>0,(U94/G94)/(1-('Project Input'!$C$20+'Project Input'!$C$21)),"") -> 469.87485 | L94: =IF(G94<>0,K94*G94,"") -> 469874.85 | M94: =IF(G94<>0,J94+L94,"") -> 1280363.5 | O94: 680 | P94: =IF(G94<>"",G94*O94,"") -> 680000 | R94: 0.65 | U94: =IF(G94<>"",(R94*G94*'Project Input'!$C$47)+(S94*G94*'Project Input'!$C$46)+(T94*G94*'Project Input'!$C$45),"") -> 394225 | W94: =IF(G94<>"",U94+P94,"") -> 1074225 | Z94: =R94*G94 -> 650 | AA94: =S94*G94 -> 0 | AB94: =T94*G94 -> 0 | AC94: =SUM(Z94:AB94) -> 650 | AD94: =IF(G94<>"",AC94/'Project Input'!$C$41,"") -> 9.0277778
F95: Cable mesh 100x50mm | G95: 2000 | H95: m | I95: =IF(G95<>"",O95/(1-('Project Input'!$C$20+'Project Input'!$C$21)),"") -> 595.94756 | J95: =IF(G95<>"",G95*I95,"") -> 1191895.1 | K95: =IF(G95<>0,(U95/G95)/(1-('Project Input'!$C$20+'Project Input'!$C$21)),"") -> 433.73063 | L95: =IF(G95<>0,K95*G95,"") -> 867461.26 | M95: =IF(G95<>0,J95+L95,"") -> 2059356.4 | O95: 500 | P95: =IF(G95<>"",G95*O95,"") -> 1000000 | R95: 0.6 | U95: =IF(G95<>"",(R95*G95*'Project Input'!$C$47)+(S95*G95*'Project Input'!$C$46)+(T95*G95*'Project Input'!$C$45),"") -> 727800 | W95: =IF(G95<>"",U95+P95,"") -> 1727800 | Z95: =R95*G95 -> 1200 | AA95: =S95*G95 -> 0 | AB95: =T95*G95 -> 0 | AC95: =SUM(Z95:AB95) -> 1200 | AD95: =IF(G95<>"",AC95/'Project Input'!$C$41,"") -> 16.666667
F96: Basket Mesh 75x60 | G96: 3000 | H96: m | I96: =IF(G96<>"",O96/(1-('Project Input'!$C$20+'Project Input'!$C$21)),"") -> 417.16329 | J96: =IF(G96<>"",G96*I96,"") -> 1251489.9 | K96: =IF(G96<>0,(U96/G96)/(1-('Project Input'!$C$20+'Project Input'!$C$21)),"") -> 253.00954 | L96: =IF(G96<>0,K96*G96,"") -> 759028.61 | M96: =IF(G96<>0,J96+L96,"") -> 2010518.5 | O96: 350 | P96: =IF(G96<>"",G96*O96,"") -> 1050000 | R96: 0.35 | U96: =IF(G96<>"",(R96*G96*'Project Input'!$C$47)+(S96*G96*'Project Input'!$C$46)+(T96*G96*'Project Input'!$C$45),"") -> 636825 | W96: =IF(G96<>"",U96+P96,"") -> 1686825 | Z96: =R96*G96 -> 1050 | AA96: =S96*G96 -> 0 | AB96: =T96*G96 -> 0 | AC96: =SUM(Z96:AB96) -> 1050 | AD96: =IF(G96<>"",AC96/'Project Input'!$C$41,"") -> 14.583333
F97: Pipe AL 20 mm | G97: 3500 | H97: m | I97: =IF(G97<>"",O97/(1-('Project Input'!$C$20+'Project Input'!$C$21)),"") -> 101.31108 | J97: =IF(G97<>"",G97*I97,"") -> 354588.8 | K97: =IF(G97<>0,(U97/G97)/(1-('Project Input'!$C$20+'Project Input'!$C$21)),"") -> 253.00954 | L97: =IF(G97<>0,K97*G97,"") -> 885533.37 | M97: =IF(G97<>0,J97+L97,"") -> 1240122.2 | O97: 85 | P97: =IF(G97<>"",G97*O97,"") -> 297500 | R97: 0.35 | U97: =IF(G97<>"",(R97*G97*'Project Input'!$C$47)+(S97*G97*'Project Input'!$C$46)+(T97*G97*'Project Input'!$C$45),"") -> 742962.5 | W97: =IF(G97<>"",U97+P97,"") -> 1040462.5 | Z97: =R97*G97 -> 1225 | AA97: =S97*G97 -> 0 | AB97: =T97*G97 -> 0 | AC97: =SUM(Z97:AB97) -> 1225 | AD97: =IF(G97<>"",AC97/'Project Input'!$C$41,"") -> 17.013889
I98: =IF(G98<>"",O98/(1-('Project Input'!$C$20+'Project Input'!$C$21)),"") | J98: =IF(G98<>"",G98*I98,"") | K98: =IF(G98<>0,(U98/G98)/(1-('Project Input'!$C$20+'Project Input'!$C$21)),"") | L98: =IF(G98<>0,K98*G98,"") | M98: =IF(G98<>0,J98+L98,"") | P98: =IF(G98<>"",G98*O98,"") | U98: =IF(G98<>"",(R98*G98*'Project Input'!$C$47)+(S98*G98*'Project Input'!$C$46)+(T98*G98*'Project Input'!$C$45),"") | W98: =IF(G98<>"",U98+P98,"") | Z98: =R98*G98 -> 0 | AA98: =S98*G98 -> 0 | AB98: =T98*G98 -> 0 | AC98: =SUM(Z98:AB98) -> 0 | AD98: =IF(G98<>"",AC98/'Project Input'!$C$41,"")
F99: Office and loading bay | I99: =IF(G99<>"",O99/(1-('Project Input'!$C$20+'Project Input'!$C$21)),"") | J99: =IF(G99<>"",G99*I99,"") | K99: =IF(G99<>0,(U99/G99)/(1-('Project Input'!$C$20+'Project Input'!$C$21)),"") | L99: =IF(G99<>0,K99*G99,"") | M99: =IF(G99<>0,J99+L99,"") | P99: =IF(G99<>"",G99*O99,"") | U99: =IF(G99<>"",(R99*G99*'Project Input'!$C$47)+(S99*G99*'Project Input'!$C$46)+(T99*G99*'Project Input'!$C$45),"") | W99: =IF(G99<>"",U99+P99,"") | Z99: =R99*G99 -> 0 | AA99: =S99*G99 -> 0 | AB99: =T99*G99 -> 0 | AC99: =SUM(Z99:AB99) -> 0 | AD99: =IF(G99<>"",AC99/'Project Input'!$C$41,"")
F100: Basket Mesh 600x150 - Fiber | H100: m | I100: =IF(G100<>"",O100/(1-('Project Input'!$C$20+'Project Input'!$C$21)),"") | J100: =IF(G100<>"",G100*I100,"") | K100: =IF(G100<>0,(U100/G100)/(1-('Project Input'!$C$20+'Project Input'!$C$21)),"") | L100: =IF(G100<>0,K100*G100,"") | M100: =IF(G100<>0,J100+L100,"") | P100: =IF(G100<>"",G100*O100,"") | U100: =IF(G100<>"",(R100*G100*'Project Input'!$C$47)+(S100*G100*'Project Input'!$C$46)+(T100*G100*'Project Input'!$C$45),"") | W100: =IF(G100<>"",U100+P100,"") | Z100: =R100*G100 -> 0 | AA100: =S100*G100 -> 0 | AB100: =T100*G100 -> 0 | AC100: =SUM(Z100:AB100) -> 0 | AD100: =IF(G100<>"",AC100/'Project Input'!$C$41,"")
...

Sheet Project Input
B2: Client: | C2: CTS | E2: Estimate: | H2: Topics | J2: Deliv. | K2: Install | O2: Ratios: | P2: Cost (NOK)
B3: Responsible: | C3: QS Manager | E3: # cables BMS Gapit (Cat 6a FTP): | F3: =C5*50 -> 1250 | H3: Power Cables | J3: x | K3: x | O3: # BMS rack / MW | P3: 0.7
E4: # Power cables Gen: | F4: =27*C8 -> 27 | H4: Signal cables | J4: x | K4: x | O4: # DB / MW: | P4: 1.2
B5: MW: | C5: 25 | E5: # Access control Security Cat6 | F5: =15*C5 -> 375 | H5: Cable lugs | J5: x | K5: x | O5: 22 kV (loop between PODs) (NOK/MW) | P5: 400000
B6: Quantity of EPOD: | C6: 24 | E6: # Access control Security LiHCH 4x0,5 | F6: =3*C5 -> 75 | H6: Contaiment/cable ladders | J6: x | K6: x | O6: Access Control and Security Equipment cabling (Doors, card reader, push botton, cameras, cooling system (NOK/MW) | P6: 215000
B7: Transformer size [kVA]: | C7: 3150 | E7: # Access control Security PT 10 pair | F7: =3*C5 -> 75 | H7: Lights | J7: x | K7: x | O7: Auxiliar equipment (Aux chillers, pumps, elevators, small power cabling 630A Tap-Off…) (NOK/MW) | P7: 255000
B8: Quantity of Gen: | C8: 1 | E8: # Access control Security PT 4 pair | F8: =1*C5 -> 25 | H8: Fire detection | K8: x | O8: Average length BMS cabling: | P8: 50
B9: Power of Gen [kVA]: | C9: 3250 | E9: # Skids BMS instrumentation 4G1,5 | F9: =11*C5 -> 275 | H9: Early warning detection equipment | J9: x | K9: x | O9: Cabling CRAH, IFSI-EMC 4x6/6 (mt/MW) | P9: 250
B10: Main Switchboard sizing [A]: | C10: 4000 | E10: # Skids BMS instrumentation 7G1,5 | F10: =3*C5 -> 75 | H10: Clamps, ties, bolts etc.. | J10: x | K10: x | O10: Cabling Fan walls, IFSI-EMC 4x25/16 (mt/MW) | P10: 600
B11: Switchboard type: | C11: Form 4 Type 6 | E11: # Skids BMS instrumentation 12G1,5 | F11: =2*C5 -> 50 | H11: Tap off boxes | J11: x | K11: x | O11: Cabling to fire alarm system (NOK/m2) | P11: 215
B12: Quantity of Chiller: | C12: 38 | E12: # Skids BMS instr. Belden 79841NH | F12: =2*C5 -> 50 | H12: Install. Leak Detection | K12: x | O12: Cabling to fire alarm system (NOK/MW) | P12: 170000
B13: Quantity of Fanwall: | E13: # Skids BMS instrumentation Cat6 | F13: =3*C5 -> 75 | O13: Car Charger 11kW, 16A, 3 Phase+N; complete with cables (/un.) | P13: 15000
B14: Quantity of CRAH unit: | E14: # Fire damper KNX/BUS EIB-H 2x2x0,8 | F14: =5*C5 -> 125 | H14: CTS delivers: | O14: CCTV / camera cabeling indoor (NOK/m2) | P14: 50
B15: Quantity of DH: | E15: # PMS/Genset 12G1,5 | F15: =2*C8 -> 2 | H15: Busbars | K15: x | O15: CCTV / camera cabeling indoor (NOK/MW) | P15: 42500
B16: Rear door cooling: | E16: # PMS/Genset 5G1,5 | F16: =1*C8 -> 1 | H16: Switchboards | K16: x | O16: Control cabling to Generator (NOK/Gen) | P16: 42500
B17: Building area (m2): | C17: =5000+84+300+346 -> 5730 | E17: # PMS/Genset 3G2,5 | F17: =2*C8 -> 2 | H17: Fanwalls | O17: Documentation, red-marks, manuals (# hour/MW) | P17: 40
B18: Roof area (m2): | E18: # PMS/Genset Cat6 | F18: =1*C8 -> 1 | H18: IT racks | O18: Earthing inside building NOK/ m2: | P18: 535
E19: Number of DB - NB: | F19: =1*C6 -> 24 | H19: Chillers and cooling components | O19: Earthing inside building NOK/MW: | P19: 190000
B20: OH: | C20: =6.1% -> 0.061 | E20: Number of DB - SB: | F20: =0.5*C6 -> 12 | H20: Security and acces control components | O20: Earthing main ring underground
B21: Cost-plus (markup) | C21: 0.1 | E21: Number of DB - NB/SB: | F21: =1*C6 -> 24 | H21: Transport co | O21: Emergency lighting (NOK/MW) | P21: 140000
E22: Number of BMS rack (building): | F22: =0.5*C5 -> 12.5 | O22: Emergency lighting (centralized) NOK/m2: | P22: 365
B23: Velox Electro Nordics Labour hourly rate (Cost): | E23: # Rear door cooling | O23: Emergency lighting (centralized) NOK/MW: | P23: 127500
B24: Average: | C24: =460*1.05 -> 483 | E24: # Fanwall: | F24: =C5*6 -> 150 | O24: Emergency lighting (descentralized) NOK/m2 | P24: 340
B25: Engineer: | C25: 945 | O25: Emergency lighting (descentralized) NOK/MW | P25: 255000
B26: Supervisor: | C26: 805 | F26: /m2 | O26: General contractor administration [Project Director/Manager, Planners, HSE, Design, HR, Supervision, etc] (# hour / MW) | P26: 600
B27: Foreman: | C27: 605 | E27: lighting cabling | F27: 840 | O27: General contractor administration [Project Director/Manager, Planners, HSE, Design, HR, Supervision, etc] (NOK / MW) | P27: 600000
B28: Team leader: | C28: 605 | E28: emergency lighting | F28: 250 | O28: Heat Exchangers (control panel, flow meter, valce, PT 100 Dif pressure, Ethernet communication) (NOK/Heat Exchange) | P28: 148750
B29: Electrician/Fitter: | C29: 565 | E29: lighting cabling | F29: 450 | O29: Heat Exchangers (control panel, flow meter, valce, PT 100 Dif pressure, Ethernet communication) (NOK/MW) | P29: 51000
B30: Electrician/Fitter Assistant: | C30: 520 | O30: Heating trace (NOK/MW) | P30: 10500
B31: SW: | C31: 500 | E31: Currency NOK-€ | F31: 11.5 | O31: Hours / MW | P31: 5000
B32: NSW: | C32: 478 | O32: Installation complies with legislation (NOK/MW) | P32: 18000
E33: Variation market cooper price | F33: 1.07 | O33: Installation of fire alarm system (NOK/m2) | P33: 43
B34: External service: | C34: 730 | E34: Fitting (Bend, Union, T) average | F34: 1.3 | O34: Installation of fire alarm system (NOK/MW) | P34: 34000
E35: k installation | F35: 1.1 | O35: Instrumentation (Temperature, Pressure, Flow, Pressurization station, Levels...) (# instruments / MW) | P35: 20
B36: HR logistics Cost/Hour: | O36: Lenght containment / 1m multipole cable: | P36: 0.6
B37: Accomodation/Local travels: | O37: Lenght containment / 1m unipolar cable: | P37: 0.06
B38: Meals: | O38: Lighting Dali (Definelight) NOK/m2: | P38: 910
B39: Travels: | O39: Lighting Dali (Veko, Glamox) NOK/m2: | P39: 510
O40: Lighting indoor (NOK/MW) | P40: 425000
B41: Number hours per week | C41: 72 | O41: Lighting outoor (NOK/MW) | P41: 51000
B42: Rotation | C42: 2/2 | O42: Lightning protection Building, Gen sets and chillers (NOK/MW) | P42: 230000
O43: Mesh cable tray below false ceiling mt/MW: | P43: 230
B44: Manpower budget aux | O44: Outdoor lighting NOK/m2: | P44: 130
B45: =[72]Pricing!T7 -> Test/Commiss | C45: =C26+SUM(C37:C39) -> 805 | O45: Power cabling IFSI 4x120/70 Cu (Busbar 2000A - Busbar 630A) (mt/MW) | P45: 200
B46: =[72]Pricing!S7 -> Electrician | C46: =AVERAGE(C29,C34)+SUM(C37:C39) -> 647.5 | O46: Power cabling IFSI 4x120/70 Cu (POD - SB) (mt/MW) | P46: 110
B47: =[72]Pricing!R7 -> Average | C47: =AVERAGE(C34,C24)+SUM(C37:C39) -> 606.5 | O47: Power cabling IFSI 4x240/120 Cu (POD - NB) (mt/MW) | P47: 100
O48: Site infrastructure: Workshop, tools containers, waste management and site storage (NOK/MW) | P48: 85000
O49: Socket NOK/m2: | P49: 230
B50: Prices in NOK | O50: Fire alarm system (NOK/m2) | P50: 170
B51: Price per MW | C51: =Pricing!M1/'Project Input'!C5 -> 9381043.4 | O51: Fire alarm system (NOK/MW) | P51: 136000
B52: Price per m2 | C52: =Pricing!M1/'Project Input'!C17 -> 40929.509 | O52: Testing commissioning and AFA L1, L2, L3 (# hour / MW) | P52: 600
O53: Lift equipment (transport icluded) NOK/MW) | P53: 119000
O54: Unforeseen (%)
O55: UPS power cabling (NOK/MW) | P55: 1000000
O56: VESDA fire alarm in WS and MMR (NOK/m2) | P56: 85
O57: VESDA fire alarm in WS and MMR (NOK/MW) | P57: 55000
O58: Workshop support team (# hours/MW) | P58: 300
O59: Water treatment system
O60: Leak detection
O61: CRAHS unit communication cabling
O62: Tap-Off metering (NOK/tap-off 32A) | P62: 2300
O63: Rear door cooling valve cabling
O64: Rear door cooling valve communication
O65: Platform lift (1/MW) | P65: 1
O66: MW/Month | P66: 8

Sheet Cables
E2: ='Project Input'!F31 -> 11.5
A3: Code | B3: Type | C3: Material | D3: Price/mt [NOK] | E3: Price/mt [€] | F3: Last update | K3: Pulling cable (Cu) | L3: Cable Tie/mt (€) | X3: Prysmian | Y3: Prysmian (€) | Z3: Sonepar | AA3: Sonepar (€) | AB3: Diferences (€)
B4: XLPE 500V CU | C4: 3G2,5 mm2 | D4: =E4*$E$2 -> 12.716125 | E4: =1105.75/1000 -> 1.10575 | F4: 17/2 | K4: =D93 -> 0.07 | L4: =M93 -> 0.06 | P4: "Forecast" for Hamina FI | R4: size | S4: total (m) | T4: Qty. cables | U4: Qty Terminations | V4: Average mt
B5: XLPE 0,6/1kV CU | C5: 5G2,5 mm2 | D5: =E5*$E$2 -> 19.50561 | E5: =1696.14/1000 -> 1.69614 | F5: 17/2 | K5: =D108 -> 0.12 | L5: =M108 -> 0.09 | P5: XLPE 0,6/1kV CU | Q5: 4C | R5: 2,5 | S5: 100000 | T5: 1716 | U5: 3432 | V5: 58.275058 | X5: AFUX-HF C-PRo 500V 3G2,5 RM | Y5: 0.96018989 | Z5: HHJ LiteRex C 3x2,5 S | AA5: 1.3347 | AB5: =Y5-AA5 -> -0.37451011 | AD5: ="XLPE"&" "&"CU"&" "&"-"&" "&X5&" "&AC5 -> XLPE CU - AFUX-HF C-PRo 500V 3G2,5 RM
B6: XLPE 500V CU | C6: 5G4 mm2 | D6: =E6*$E$2 -> 29.361915 | E6: =2553.21/1000 -> 2.55321 | F6: 17/2 | K6: =D107 -> 0.13 | L6: =M107 -> 0.12 | P6: XLPE 0,6/1kV CU | Q6: 4C | R6: 4 | S6: 7000 | T6: 150 | U6: 300 | V6: 46.666667 | X6: AFUX-HF C-PRo 500V 5G4 RM | Y6: 2.8853882 | Z6: MMJ-HF C 5x6 S | AA6: 4.842 | AB6: =Y6-AA6 -> -1.9566118 | AD6: ="XLPE"&" "&"CU"&" "&"-"&" "&X6&" "&AC6 -> XLPE CU - AFUX-HF C-PRo 500V 5G4 RM
B7: XLPE 0,6/1kV CU | C7: 3x 6/6 mm2 | D7: =E7*$E$2 -> 41.00279 | E7: =E8 -> 3.56546 | K7: =D91 -> 0.12 | L7: =M91 -> 0.09 | P7: XLPE 0,6/1kV CU | Q7: 4C | R7: 6 | S7: 3000 | T7: 50 | U7: 100 | V7: 60 | X7: AFUX-HF C-PRo 1kV 5G6 RM | Y7: 3.7432644 | Z7: MMJ-HF C 5x6 S | AA7: 4.842 | AB7: =Y7-AA7 -> -1.0987356 | AD7: ="XLPE"&" "&"CU"&" "&"-"&" "&X7&" "&AC7 -> XLPE CU - AFUX-HF C-PRo 1kV 5G6 RM
B8: XLPE 0,6/1kV CU | C8: 5G6 mm2 | D8: =E8*$E$2 -> 41.00279 | E8: =3565.46/1000 -> 3.56546 | F8: 17/2 | K8: =D106 -> 0.13 | L8: =M106 -> 0.12 | P8: XLPE 0,6/1kV CU | Q8: 4C | R8: 10 | S8: 1500 | T8: 20 | U8: 40 | V8: 75 | X8: AFUX-HF C-PRo 1kV 5G10 RM | Y8: 5.8280351 | Z8: MMJ-HF C 5x10 S | AA8: 7.39 | AB8: =Y8-AA8 -> -1.5619649 | AD8: ="XLPE"&" "&"CU"&" "&"-"&" "&X8&" "&AC8 -> XLPE CU - AFUX-HF C-PRo 1kV 5G10 RM
B9: XLPE 0,6/1kV CU | C9: 3x 10/10 mm2 | D9: =E9*$E$2 -> 67.330315 | E9: =E10 -> 5.85481 | K9: =D90 -> 0.13 | L9: =M90 -> 0.12 | P9: XLPE 0,6/1kV CU G/Y | Q9: 1C | R9: 16 | S9: 3400 | T9: 14 | U9: 28 | V9: 242.85714 | X9: MK-HF C-Pro 16 KEVI | Y9: 1.7539708 | Z9: MK-HF C 16 GNYE H07Z1-R TYPE 2 | AA9: 2.6687 | AB9: =Y9-AA9 -> -0.91472925 | AC9: G/Y | AD9: ="XLPE"&" "&"CU"&" "&"-"&" "&X9&" "&AC9 -> XLPE CU - MK-HF C-Pro 16 KEVI G/Y
B10: XLPE 0,6/1kV CU | C10: 5G10 mm2 | D10: =E10*$E$2 -> 67.330315 | E10: =5854.81/1000 -> 5.85481 | F10: 17/2 | K10: =D105 -> 0.13 | L10: =M105 -> 0.15 | P10: XLPE 0,6/1kV CU | Q10: 4C | R10: 16 | S10: 13160 | T10: 188 | U10: 376 | V10: 70 | X10: MCMK-HF C-PRo 4x16/16 RM 1kV | Y10: 8.9459241 | Z10: XCMK-HF C 4x16/16 | AA10: 12.2682 | AB10: =Y10-AA10 -> -3.3222759 | AD10: ="XLPE"&" "&"CU"&" "&"-"&" "&X10&" "&AC10 -> XLPE CU - MCMK-HF C-PRo 4x16/16 RM 1kV
B11: XLPE 0,6/1kV CU | C11: 3x 16/10 mm2 | D11: =E11*$E$2 -> 102.85163 | E11: =E12 -> 8.94362 | K11: =D89 -> 0.13 | L11: =M89 -> 0.12 | P11: XLPE 0,6/1kV CU G/Y | Q11: 1C | R11: 25 | S11: 3300 | T11: 12 | U11: 24 | V11: 275 | X11: MK-HF C-Pro 25 KEVI | Y11: 2.7962848 | Z11: MK-HF C 25 GNYE H07Z1-R TYPE 2 | AA11: 4.0898 | AB11: =Y11-AA11 -> -1.2935152 | AC11: G/Y | AD11: ="XLPE"&" "&"CU"&" "&"-"&" "&X11&" "&AC11 -> XLPE CU - MK-HF C-Pro 25 KEVI G/Y
B12: XLPE 0,6/1kV CU | C12: 4x 16/16 mm2 | D12: =E12*$E$2 -> 102.85163 | E12: =8943.62/1000 -> 8.94362 | F12: 17/2 | K12: =D104 -> 0.13 | L12: =M104 -> 0.18 | P12: XLPE 0,6/1kV CU | Q12: 4C | R12: 25 | S12: 4075 | T12: 24 | U12: 48 | V12: 169.79167 | X12: MCMK-HF C-PRo 4x25/16 RM 1kV | Y12: 12.272245 | Z12: XCMK-HF C 4x25/16 | AA12: 18.6597 | AB12: =Y12-AA12 -> -6.387455 | AD12: ="XLPE"&" "&"CU"&" "&"-"&" "&X12&" "&AC12 -> XLPE CU - MCMK-HF C-PRo 4x25/16 RM 1kV
B13: XLPE 0,6/1kV CU | C13: 3x 25/16 mm2 | D13: =E13*$E$2 -> 163.44421 | E13: =E14 -> 14.21254 | K13: =D88 -> 0.13 | L13: =M88 -> 0.18 | P13: XLPE 0,6/1kV CU G/Y | Q13: 1C | R13: 35 | S13: 100 | T13: 2 | U13: 4 | V13: 50 | X13: MK-HF C-Pro 35 KEVI | Y13: 3.9188378 | Z13: MK-HF C 35 GNYE H07Z1-R TYPE 2 | AA13: 5.5358 | AB13: =Y13-AA13 -> -1.6169622 | AC13: G/Y | AD13: ="XLPE"&" "&"CU"&" "&"-"&" "&X13&" "&AC13 -> XLPE CU - MK-HF C-Pro 35 KEVI G/Y
B14: XLPE 0,6/1kV CU | C14: 4x 25/16 mm2 | D14: =E14*$E$2 -> 163.44421 | E14: =14212.54/1000 -> 14.21254 | F14: 17/2 | G14: =+E14/E12 -> 1.5891261 | K14: =D103 -> 0.22 | L14: =M103 -> 0.24 | P14: XLPE 0,6/1kV CU | Q14: 4C | R14: 35 | S14: 4090 | T14: 242 | U14: 484 | V14: 16.900826 | X14: MCMK-HF C-PRo 4x35/16 AN 1kV | Y14: 16.385098 | Z14: XCMK-HF C 4x35/16 | AA14: 24.1016 | AB14: =Y14-AA14 -> -7.7165019 | AD14: ="XLPE"&" "&"CU"&" "&"-"&" "&X14&" "&AC14 -> XLPE CU - MCMK-HF C-PRo 4x35/16 AN 1kV
B15: XLPE 0,6/1kV CU | C15: 3x 35/25 mm2 | D15: =E15*$E$2 -> 188.485 | E15: =E16 -> 16.39 | K15: =D87 -> 0.13 | L15: =M87 -> 0.24 | P15: XLPE 0,6/1kV CU | Q15: 1C | R15: 50 | S15: 11120 | T15: 64 | U15: 128 | V15: 173.75 | X15: XMK-HF Cca 1x50 RM 1kV | Y15: 6.1564197 | AA15: 0 | AD15: ="XLPE"&" "&"CU"&" "&"-"&" "&X15&" "&AC15 -> XLPE CU - XMK-HF Cca 1x50 RM 1kV
B16: XLPE 0,6/1kV CU | C16: 4x 35/16 mm2 | D16: =E16*$E$2 -> 188.485 | E16: 16.39 | F16: 29/11 | G16: =+E16/E14 -> 1.153207 | K16: =D102 -> 0.22 | L16: =M102 -> 0.3 | P16: XLPE 0,6/1kV CU | Q16: 4C | R16: 50 | S16: 7975 | T16: 98 | U16: 196 | V16: 81.377551 | X16: MCMK-HF C-PRo 4x50/25 AN 1kV | Y16: 22.016687 | Z16: XCMK-HF C 4x50/25 | AA16: 33.5428 | AB16: =Y16-AA16 -> -11.526113 | AD16: ="XLPE"&" "&"CU"&" "&"-"&" "&X16&" "&AC16 -> XLPE CU - MCMK-HF C-PRo 4x50/25 AN 1kV
B17: XLPE 0,6/1kV CU | C17: 3x 50/25 mm2 | D17: =E17*$E$2 -> 324.84372 | E17: =E18 -> 28.24728 | K17: =D86 -> 0.22 | L17: =M86 -> 0.3 | P17: XLPE 0,6/1kV CU | Q17: 1C | R17: 70 | S17: 6280 | T17: 40 | U17: 72 | V17: 171.11111 | X17: XMK-HF Cca 1x70 RM 1kV | Y17: 8.5159804 | AA17: 0 | AD17: ="XLPE"&" "&"CU"&" "&"-"&" "&X17&" "&AC17 -> XLPE CU - XMK-HF Cca 1x70 RM 1kV
B18: XLPE 0,6/1kV CU | C18: 4x 50/25 mm2 | D18: =E18*$E$2 -> 324.84372 | E18: =28247.28/1000 -> 28.24728 | F18: 17/2 | G18: =+E18/E16 -> 1.723446 | K18: =D101 -> 0.3 | L18: =M101 -> 0.36 | P18: XLPE 0,6/1kV CU | Q18: 4C | R18: 70 | S18: 2800 | T18: 40 | U18: 80 | V18: 70 | X18: MCMK-HF C-PRo 4x70/35 AN 1kV | Y18: 31.558685 | Z18: XCMK-HF C 4x70/35 | AA18: 46.2558 | AB18: =Y18-AA18 -> -14.697115 | AD18: ="XLPE"&" "&"CU"&" "&"-"&" "&X18&" "&AC18 -> XLPE CU - MCMK-HF C-PRo 4x70/35 AN 1kV
B19: XLPE 0,6/1kV CU | C19: 3x 70/35 mm2 | D19: =E19*$E$2 -> 462.56761 | E19: =E20 -> 40.22327 | K19: =D85 -> 0.29 | L19: =M85 -> 0.36 | P19: XLPE 0,6/1kV CU | Q19: 1C | R19: 95 | S19: 6760 | T19: 72 | U19: 144 | V19: 93.888889 | X19: XMK-HF Cca 1x95 RM 1kV | Y19: 11.101971 | AA19: 0 | AD19: ="XLPE"&" "&"CU"&" "&"-"&" "&X19&" "&AC19 -> XLPE CU - XMK-HF Cca 1x95 RM 1kV
B20: XLPE 0,6/1kV CU | C20: 4x 70/35 mm2 | D20: =E20*$E$2 -> 462.56761 | E20: =40223.27/1000 -> 40.22327 | F20: 17/2 | G20: =+E20/E18 -> 1.4239697 | K20: =D100 -> 0.32 | L20: =M100 -> 0.42 | P20: XLPE 0,6/1kV CU | Q20: 4C | R20: 95 | S20: 4550 | T20: 65 | U20: 130 | V20: 70 | X20: MCMK-HF C-PRo 4x95/50 AN 1kV | Y20: 43.542611 | Z20: XCMK-HF C 4x95/50 | AA20: 63.0734 | AB20: =Y20-AA20 -> -19.530789 | AD20: ="XLPE"&" "&"CU"&" "&"-"&" "&X20&" "&AC20 -> XLPE CU - MCMK-HF C-PRo 4x95/50 AN 1kV
B21: XLPE 0,6/1kV CU | C21: 3x 95/50 mm2 | D21: =E21*$E$2 -> 597.25273 | E21: =E22 -> 51.93502 | K21: =D84 -> 0.32 | L21: =M84 -> 0.42 | P21: XLPE 0,6/1kV CU | Q21: 1C | R21: 120 | S21: 1160 | T21: 34 | U21: 68 | V21: 34.117647 | X21: XMK-HF Cca 1x120 RM 1kV | Y21: 14.457398 | AA21: 0 | AB21: =Y21-AA21 -> 14.457398 | AD21: ="XLPE"&" "&"CU"&" "&"-"&" "&X21&" "&AC21 -> XLPE CU - XMK-HF Cca 1x120 RM 1kV
B22: XLPE 0,6/1kV CU | C22: 4x 95/50 mm2 | D22: =E22*$E$2 -> 597.25273 | E22: =51935.02/1000 -> 51.93502 | F22: 17/2 | G22: =+E22/E20 -> 1.2911685 | K22: =D99 -> 0.37 | L22: =M99 -> 0.48 | P22: XLPE 0,6/1kV CU | Q22: 4C | R22: 120 | S22: 360 | T22: 14 | U22: 28 | V22: 25.714286 | X22: MCMK-HF C-PRo 4x120/70 AN 1kV | Y22: 55.165802 | Z22: XCMK-HF C 4x120/70 | AA22: 79.9168 | AB22: =Y22-AA22 -> -24.750998 | AD22: ="XLPE"&" "&"CU"&" "&"-"&" "&X22&" "&AC22 -> XLPE CU - MCMK-HF C-PRo 4x120/70 AN 1kV
B23: XLPE 0,6/1kV CU | C23: 3x 120/70 mm2 | D23: =E23*$E$2 -> 634.455 | E23: =E24 -> 55.17 | K23: =D83 -> 0.35 | L23: =M83 -> 0.45 | P23: XLPE 0,6/1kV CU | Q23: 1C | R23: 185 | S23: 2320 | T23: 44 | U23: 88 | V23: 52.727273 | X23: XMK-HF C-PRo 1x185 AN 1kV | Y23: 18.552132 | AA23: 0 | AD23: ="XLPE"&" "&"CU"&" "&"-"&" "&X23&" "&AC23 -> XLPE CU - XMK-HF C-PRo 1x185 AN 1kV
B24: XLPE 0,6/1kV CU | C24: 4x 120/70 mm2 | D24: =E24*$E$2 -> 634.455 | E24: 55.17 | F24: 29/11 | G24: =+E24/E22 -> 1.062289 | K24: =D98 -> 0.38 | L24: =M98 -> 0.51 | P24: XLPE 0,6/1kV CU | Q24: 1C | R24: 240 | S24: 218060 | T24: 7920 | U24: 15840 | V24: 27.532828 | X24: XMK-HF C-PRo 1x240 AN 1kV | Y24: 23.882078 | AA24: 0 | AD24: ="XLPE"&" "&"CU"&" "&"-"&" "&X24&" "&AC24 -> XLPE CU - XMK-HF C-PRo 1x240 AN 1kV
B25: XLPE 0,6/1kV CU | C25: 3x 150/95 mm2 | D25: =E25*$E$2 -> 824.7915 | E25: =E24*1.3 -> 71.721 | K25: =D82 -> 0.38 | L25: =M82 -> 0.48 | P25: XLPE 0,6/1kV CU G/Y | Q25: 1C | R25: 240 | S25: 25990 | T25: 962 | U25: 1924 | V25: 27.016632 | X25: MKEM-HF C-PRo 240 KEVI | Y25: 24.075818 | Z25: MK-HF C 240 GNYE H07Z1-R TYPE 2 | AA25: 35.6581 | AB25: =Y25-AA25 -> -11.582282 | AC25: G/Y | AD25: ="XLPE"&" "&"CU"&" "&"-"&" "&X25&" "&AC25 -> XLPE CU - MKEM-HF C-PRo 240 KEVI G/Y
B26: XLPE 0,6/1kV CU | C26: 4x 150/95 mm2 | D26: =E26*$E$2 -> 888.237 | E26: =E24*1.4 -> 77.238 | K26: =D97 -> 0.39 | L26: =M97 -> 0.54 | P26: XLPE 0,6/1kV CU | Q26: 4C | R26: 240 | S26: 1430 | T26: 64 | U26: 128 | V26: 22.34375 | X26: MCMK-HF C-PRo 4x240/120 AN 1kV | Y26: 108.50066 | Z26: XCMK-HF C 4x240/120 | AA26: 157.909 | AB26: =Y26-AA26 -> -49.408341 | AD26: ="XLPE"&" "&"CU"&" "&"-"&" "&X26&" "&AC26 -> XLPE CU - MCMK-HF C-PRo 4x240/120 AN 1kV
B27: XLPE 0,6/1kV CU | C27: 3x 185/95 mm2 | D27: =E27*$E$2 -> 1072.229 | E27: =E25*1.3 -> 93.2373 | K27: =D81 -> 0.39 | L27: =M81 -> 0.54 | P27: XLPE 1kV CU | Q27: 1C | R27: 300 | S27: 6960 | T27: 128 | U27: 256 | V27: 54.375 | X27: XMK-HF C-PRo 1x300 AN 1kV | Y27: 32.316781 | AA27: 0 | AD27: ="XLPE"&" "&"CU"&" "&"-"&" "&X27&" "&AC27 -> XLPE CU - XMK-HF C-PRo 1x300 AN 1kV
B28: XLPE 0,6/1kV CU | C28: 4x 185/95 mm2 | D28: =E28*$E$2 -> 1154.7081 | E28: =E25*1.4 -> 100.4094 | K28: =D96 -> 0.4 | L28: =M96 -> 0.6 | P28: XLPE 1kV CU | Q28: 1C | R28: 400 | S28: 9800 | T28: 560 | U28: 1120 | V28: 17.5 | X28: XMK-HF C-PRo 1x400 AN 1kV | Y28: 42.160701 | Z28: MK-HF C 400 GNYE H07Z1-R TYPE 2 | AA28: 59.202 | AB28: =Y28-AA28 -> -17.041299 | AD28: ="XLPE"&" "&"CU"&" "&"-"&" "&X28&" "&AC28 -> XLPE CU - XMK-HF C-PRo 1x400 AN 1kV
B29: XLPE 0,6/1kV CU | C29: 3x 240/120 mm2 | D29: =E29*$E$2 -> 1247.75 | E29: =E30 -> 108.5 | K29: =D80 -> 0.4 | L29: =M80 -> 0.6 | P29: XLPE 0,6/1kV CU Flexible Class 5
B30: XLPE 0,6/1kV CU | C30: 4x 240/120 mm2 | D30: =E30*$E$2 -> 1247.75 | E30: 108.5 | F30: 29/11 | K30: =D95 -> 0.43 | L30: =M95 -> 0.66
C32: 1x 10 mm2 | D32: =E32*$E$2 -> 12.42 | E32: =1080/1000 -> 1.08 | F32: 17/2 | K32: =D77 -> 0.05 | L32: =M77 -> 0.12
B33: XLPE CU G/Y | C33: 1x 16 mm2 | D33: =E33*$E$2 -> 19.09 | E33: =1660/1000 -> 1.66 | F33: 17/2 | K33: =D76 -> 0.05 | L33: =M76 -> 0.15
B34: XLPE CU G/Y | C34: 1x 25 mm2 | D34: =E34*$E$2 -> 29.44 | E34: =2560/1000 -> 2.56 | F34: 17/2 | G34: =+E34/E33-1 -> 0.54216867 | K34: =D75 -> 0.07 | L34: =M75 -> 0.18
B35: XLPE CU G/Y | C35: 1x 35 mm2 | D35: =E35*$E$2 -> 40.94 | E35: =3560/1000 -> 3.56 | F35: 17/2 | G35: =+E35/E34-1 -> 0.390625 | K35: =D74 -> 0.09 | L35: =M74 -> 0.21
B36: XLPE 0,6/1kV CU | C36: 1x 50 mm2 | D36: =E36*$E$2 -> 70.84 | E36: 6.16 | F36: 29/11 | G36: =+E36/E35-1 -> 0.73033708 | K36: =D73 -> 0.12 | L36: =M73 -> 0.24
B37: XLPE 0,6/1kV CU | C37: 1x 70 mm2 | D37: =E37*$E$2 -> 97.98 | E37: 8.52 | F37: 17/2 | G37: =+E37/E36-1 -> 0.38311688 | K37: =D72 -> 0.12 | L37: =M72 -> 0.3
B38: XLPE 0,6/1kV CU | C38: 1x 95 mm2 | D38: =E38*$E$2 -> 127.65 | E38: 11.1 | F38: 29/11 | G38: =+E38/E37-1 -> 0.3028169 | K38: =D71 -> 0.12 | L38: =M71 -> 0.45
B39: XLPE 0,6/1kV CU | C39: 1x 120 mm2 | D39: =E39*$E$2 -> 144.44 | E39: =12560/1000 -> 12.56 | F39: 17/2 | G39: =+E39/E38-1 -> 0.13153153 | K39: =D70 -> 0.13 | L39: =M70 -> 0.6
B40: XLPE 0,6/1kV CU | C40: 1x 150 mm2 | D40: =E40*$E$2 -> 177.64234 | E40: =15447.16/1000 -> 15.44716 | F40: 17/2 | K40: =D69 -> 0.13 | L40: =M69 -> 0.75
B41: XLPE 0,6/1kV CU | C41: 1x 185 mm2 | D41: =E41*$E$2 -> 215.28253 | E41: =18720.22/1000 -> 18.72022 | F41: 17/2 | G41: =+E41/E39-1 -> 0.49046338 | K41: =D68 -> 0.13 | L41: =M68 -> 0.9
B42: XLPE 0,6/1kV CU | C42: 1x 240 mm2 | D42: =E42*$E$2 -> 289.8 | E42: =25200/1000 -> 25.2 | F42: 17/2 | G42: =+E42/E41-1 -> 0.34613803 | K42: =D67 -> 0.22 | L42: =M67 -> 9
B43: XLPE CU G/Y | C43: 1x 240 mm2 | D43: =E43*$E$2 -> 289.8 | E43: =25200/1000 -> 25.2 | F43: 17/2 | G43: =+E43/E41-1 -> 0.34613803 | K43: =D67 -> 0.22 | L43: =M67 -> 9
B44: TXXI 1kV CU | C44: 1x300 mm2 | D44: =E44*$E$2 -> 431.825 | E44: =37550/1000 -> 37.55 | F44: 17/2 | G44: =+E44/E42-1 -> 0.49007937 | K44: =D66 -> 0.26 | L44: =M66 -> 10
B45: TXXI 1kV CU | C45: 1x400 mm2 | D45: =E45*$E$2 -> 484.84 | E45: 42.16 | F45: 29/11 | G45: =+E45/E44-1 -> 0.12276964 | K45: =D65 -> 0.3 | L45: =M65 -> 10
B47: TXXI 1kV AL | C47: 1x300 mm2 | D47: 79.34 | E47: =D47/$E$2 -> 6.8991304
B48: TXXI 1kV AL | C48: 1x400 mm2 | D48: 97.9 | E48: =D48/$E$2 -> 8.5130435
B50: BFXI CU | C50: Cu 4mm2 4C XLPE LSZH | D50: 43.5 | E50: =D50/$E$2 -> 3.7826087 | F50: NHXH FE180/E30, LSZH, FRNC-compound HI1 Insulated, FRNC-compound HMI1 Sheathing, Non-Armoured, Class 1/2
B51: BFXI CU | C51: Cu 6mm2 4C XLPE LSZH | D51: 58.8 | E51: =D51/$E$2 -> 5.1130435 | F51: NHXH FE180/E30, LSZH, FRNC-compound HI1 Insulated, FRNC-compound HMI1 Sheathing, Non-Armoured, Class 1/2
B52: FLAMEBLOCKER N2XH-J CU | C52: 4x10RE XLPE LSZH | D52: 66.5 | E52: =D52/$E$2 -> 5.7826087 | F52: NHXH FE180/E30, LSZH, FRNC-compound HI1 Insulated, FRNC-compound HMI1 Sheathing, Non-Armoured, Class 1/2
B53: FLAMEBLOCKER N2XH-J CU | C53: 4x16RE XLPE LSZH | D53: 100.4 | E53: =D53/$E$2 -> 8.7304348 | F53: NHXH FE180/E30, LSZH, FRNC-compound HI1 Insulated, FRNC-compound HMI1 Sheathing, Non-Armoured, Class 1/2
B54: FLAMEBLOCKER N2XH-J CU | C54: 4x25RM XLPE LSZH | D54: 154.8 | E54: =D54/$E$2 -> 13.46087 | F54: NHXH FE180/E30, LSZH, FRNC-compound HI1 Insulated, FRNC-compound HMI1 Sheathing, Non-Armoured, Class 1/2
B55: N2XH-J 0,6/1KV B2 CU | C55: 4x35 RM XLPE LSZH | D55: 238.6 | E55: =D55/$E$2 -> 20.747826 | F55: N2XH, FRNC-LSZH, XLPE insulated, Non-Armoured, Class 2
B56: N2XH-J 0,6/1KV B2 CU | C56: 4x50 RM XLPE LSZH | D56: 359 | E56: =D56/$E$2 -> 31.217391 | F56: N2XH, FRNC-LSZH, XLPE insulated, Non-Armoured, Class 2
B57: N2XH-J 0,6/1KV B2 CU | C57: 4x70 SM XLPE LSZH | D57: 459.5 | E57: =D57/$E$2 -> 39.956522 | F57: N2XH, FRNC-LSZH, XLPE insulated, Non-Armoured, Class 2
B58: N2XH-J 0,6/1KV B2 CU | C58: 4x95 SM XLPE LSZH | D58: 625.4 | E58: =D58/$E$2 -> 54.382609 | F58: N2XH, FRNC-LSZH, XLPE insulated, Non-Armoured, Class 2
B59: N2XH-J 0,6/1KV B2 CU | C59: 4x120 SM XLPE LSZH | D59: 778.8 | E59: =D59/$E$2 -> 67.721739 | F59: N2XH, FRNC-LSZH, XLPE insulated, Non-Armoured, Class 2
B60: N2XH-J 0,6/1KV B2 CU | C60: 4x150 SM XLPE LSZH | D60: 993 | E60: =D60/$E$2 -> 86.347826 | F60: N2XH, FRNC-LSZH, XLPE insulated, Non-Armoured, Class 2
B61: RZ1-K 1kV black | C61: 1x240RF XLPE LSZH | D61: 320.6 | E61: =D61/$E$2 -> 27.878261 | F61: N2XH, FRNC-LSZH, XLPE insulated, Non-Armoured, Class 2
B62: RZ1-K 1kV czarny | C62: 1x300RF XLPE LSZH | D62: 398.9 | E62: =D62/$E$2 -> 34.686957 | F62: N2XH, FRNC-LSZH, XLPE insulated, Non-Armoured, Class 2
A64: Code | C64: Pulling cable | D64: MO (hour) | M64: Cable Tie/mt (€)
B65: CU | C65: 1x400 | D65: 0.3 | M65: =15*(2/3) -> 10
B66: CU | C66: 1x300 | D66: 0.26 | M66: =15*(2/3) -> 10
B67: CU | C67: 1x240 | D67: 0.22 | M67: =13.5*(2/3) -> 9
B68: CU | C68: 1x185 | D68: 0.13 | M68: =3*0.3 -> 0.9
B69: CU | C69: 1x150 | D69: 0.13 | M69: =3*0.25 -> 0.75
B70: CU | C70: 1x120 | D70: 0.13 | M70: =3*0.2 -> 0.6
B71: CU | C71: 1x95 | D71: 0.12 | M71: =3*0.15 -> 0.45
B72: CU | C72: 1x70 | D72: 0.12 | M72: =3*0.1 -> 0.3
B73: CU | C73: 1x50 | D73: 0.12 | M73: =3*0.08 -> 0.24
B74: CU | C74: 1x35 | D74: 0.09 | M74: =3*0.07 -> 0.21
B75: CU | C75: 1x25 | D75: 0.07 | M75: =3*0.06 -> 0.18
B76: CU | C76: 1x16 | D76: 0.05 | M76: =3*0.05 -> 0.15
B77: CU | C77: 1x10 | D77: 0.05 | M77: =3*0.04 -> 0.12
B78: CU | C78: 1x6 | D78: 0.04 | M78: =3*0.03 -> 0.09
B80: CU | C80: 3x240/120 | D80: 0.4 | M80: =3*0.2 -> 0.6
B81: CU | C81: 3x185/95 | D81: 0.39 | M81: =3*0.18 -> 0.54
B82: CU | C82: 3x150/95 | D82: 0.38 | M82: =3*0.16 -> 0.48
B83: CU | C83: 3x120/70 | D83: 0.35 | M83: =3*0.15 -> 0.45
B84: CU | C84: 3x95/50 | D84: 0.32 | M84: =3*0.14 -> 0.42
B85: CU | C85: 3x70/35 | D85: 0.29 | M85: =3*0.12 -> 0.36
B86: CU | C86: 3x50/25 | D86: 0.22 | M86: =3*0.1 -> 0.3
B87: CU | C87: 3x35/25 | D87: 0.13 | M87: =3*0.08 -> 0.24
B88: CU | C88: 3X25/16 | D88: 0.13 | M88: =3*0.06 -> 0.18
B89: CU | C89: 3G16 | D89: 0.13 | M89: =3*0.04 -> 0.12
B90: CU | C90: 3G10 | D90: 0.13 | M90: =3*0.04 -> 0.12
B91: CU | C91: 3X6 | D91: 0.12 | M91: =3*0.03 -> 0.09
B92: CU | C92: 3G4 | D92: 0.12 | M92: =3*0.03 -> 0.09
B93: CU | C93: 3G2.5 | D93: 0.07 | M93: =3*0.02 -> 0.06
B95: CU | C95: 4x240/120 | D95: 0.43 | M95: =3*0.22 -> 0.66
B96: CU | C96: 4x185/95 | D96: 0.4 | M96: =3*0.2 -> 0.6
B97: CU | C97: 4x150/95 | D97: 0.39 | M97: =3*0.18 -> 0.54
B98: CU | C98: 4x120/70 | D98: 0.38 | M98: =3*0.17 -> 0.51
B99: CU | C99: 4x95/50 | D99: 0.37 | M99: =3*0.16 -> 0.48
B100: CU | C100: 4x70/35 | D100: 0.32 | M100: =3*0.14 -> 0.42
B101: CU | C101: 4X50/25 | D101: 0.3 | M101: =3*0.12 -> 0.36
B102: CU | C102: 4X35/16 | D102: 0.22 | M102: =3*0.1 -> 0.3
B103: CU | C103: 4x25/16 | D103: 0.22 | M103: =3*0.08 -> 0.24
B104: CU | C104: 5G16 | D104: 0.13 | M104: =3*0.06 -> 0.18
B105: CU | C105: 5G10 | D105: 0.13 | M105: =3*0.05 -> 0.15
B106: CU | C106: 5G6 | D106: 0.13 | M106: =3*0.04 -> 0.12
B107: CU | C107: 5G4 | D107: 0.13 | M107: =3*0.04 -> 0.12
...

Sheet Cable trays + Fittings
A1: Code | B1: Type | C1: Material | D1: width | E1: height | G1: Qty. | H1: Unit. Price | I1: Material Price € | J1: Material Price NOK | L1: Time | M1: 0.5 | N1: h* | O1: Qty | P1: Qty/Un
A2: Index: | B2: Cable trays | D2: Fittings
A4: Cable trays:
A5: =CONCATENATE("Cable ",B5," ",C5," ",D5," x ",E5) -> Cable Basket HDG 450 x 60 | B5: Basket | C5: HDG | D5: 450 | E5: 60 | I5: =SUM(I6:I14) -> 37.036421 | J5: =I5*NOK2EUR -> 425.91884 | L5: =IF(D5>300,D5/1000,0.25) -> 0.45 | M5: =$M$1 -> 0.5 | N5: =L5+L5*M5 -> 0.675 | O5: =SUMIF('[55]Cable Trays - maching table'!C:C,A5,'[55]Cable Trays - maching table'!D:D) -> #VALUE!
F6: =CONCATENATE("Cable ",B5," ",C5," ",D5," x ",E5) -> Cable Basket HDG 450 x 60 | G6: 1 | H6: =IF(F6="",0,VLOOKUP(F6,'Cable trays (UnitPrice)'!B:F,5,0)) -> 16.972017 | I6: =H6*G6 -> 16.972017 | P6: =G6*O5 -> #VALUE!
F7: =CONCATENATE(B5," - Union ",C5) -> Basket - Union HDG | G7: 0.7 | H7: =IF(F7="",0,VLOOKUP(F7,'Cable trays (UnitPrice)'!B:F,5,0)) -> 0.68362045 | I7: =H7*G7 -> 0.47853432 | P7: =G7*O5 -> #VALUE!
F8: T-skrue M10x35mm Els MP-983E | G8: 4 | H8: =IF(F8="",0,VLOOKUP(F8,'Cable trays (UnitPrice)'!B:F,5,0)) -> 1.6165217 | I8: =H8*G8 -> 6.466087 | P8: =G8*O5 -> #VALUE!
F9: Hexagonal screw stainless steel, M8 x 30 +Washer M8 | G9: 8 | H9: =IF(F9="",0,VLOOKUP(F9,'Cable trays (UnitPrice)'!B:F,5,0)) -> 0.16434783 | I9: =H9*G9 -> 1.3147826 | P9: =G9*O5 -> #VALUE!
F10: =IF(C5="HDG","Anchor rail 41x41 HDG","Anchor rail 41x41") -> Anchor rail 41x41 HDG | G10: =D5/1000 -> 0.45 | H10: =IF(F10="",0,VLOOKUP(F10,'Cable trays (UnitPrice)'!B:F,5,0)) -> 5.9608696 | I10: =H10*G10 -> 2.6823913 | P10: =G10*O5 -> #VALUE!
F11: ENDEBESKYTTER 41X41MM | G11: 1 | H11: =IF(F11="",0,VLOOKUP(F11,'Cable trays (UnitPrice)'!B:F,5,0)) -> 0.78521739 | I11: =H11*G11 -> 0.78521739 | P11: =G11*O5 -> #VALUE!
F12: =IF(C5="HDG","Ceiling mount for anchor rail Varmf MP-230Z HDG","Ceiling mount for anchor rail Sendz MP-230S") -> Ceiling mount for anchor rail Varmf MP-230Z HDG | G12: 2 | H12: =IF(F12="",0,VLOOKUP(F12,'Cable trays (UnitPrice)'!B:F,5,0)) -> 4.1686957 | I12: =H12*G12 -> 8.3373913 | P12: =G12*O5 -> #VALUE!
H13: =IF(F13="",0,VLOOKUP(F13,'Cable trays (UnitPrice)'!B:F,5,0)) -> 0 | I13: =H13*G13 -> 0 | P13: =G13*O5 -> #VALUE!
H14: =IF(F14="",0,VLOOKUP(F14,'Cable trays (UnitPrice)'!B:F,5,0)) -> 0 | I14: =H14*G14 -> 0 | P14: =G14*O5 -> #VALUE!
A15: =CONCATENATE("Cable ",B15," ",C15," ",D15," x ",E15) -> Cable Basket HDG 450 x 50 | B15: Basket | C15: HDG | D15: 450 | E15: 50 | I15: =SUM(I16:I24) -> 37.020926 | J15: =I15*NOK2EUR -> 425.74064 | L15: =IF(D15>300,D15/1000,0.25) -> 0.45 | M15: =$M$1 -> 0.5 | N15: =L15+L15*M15 -> 0.675 | O15: =SUMIF('[55]Cable Trays - maching table'!C:C,A15,'[55]Cable Trays - maching table'!D:D) -> #VALUE!
F16: =CONCATENATE("Cable ",B15," ",C15," ",D15," x ",E15) -> Cable Basket HDG 450 x 50 | G16: 1 | H16: =IF(F16="",0,VLOOKUP(F16,'Cable trays (UnitPrice)'!B:F,5,0)) -> 16.956522 | I16: =H16*G16 -> 16.956522 | P16: =G16*O15 -> #VALUE!
F17: =CONCATENATE(B15," - Union ",C15) -> Basket - Union HDG | G17: 0.7 | H17: =IF(F17="",0,VLOOKUP(F17,'Cable trays (UnitPrice)'!B:F,5,0)) -> 0.68362045 | I17: =H17*G17 -> 0.47853432 | P17: =G17*O15 -> #VALUE!
F18: T-skrue M10x35mm Els MP-983E | G18: 4 | H18: =IF(F18="",0,VLOOKUP(F18,'Cable trays (UnitPrice)'!B:F,5,0)) -> 1.6165217 | I18: =H18*G18 -> 6.466087 | P18: =G18*O15 -> #VALUE!
F19: Hexagonal screw stainless steel, M8 x 30 +Washer M8 | G19: 8 | H19: =IF(F19="",0,VLOOKUP(F19,'Cable trays (UnitPrice)'!B:F,5,0)) -> 0.16434783 | I19: =H19*G19 -> 1.3147826 | P19: =G19*O15 -> #VALUE!
F20: =IF(C15="HDG","Anchor rail 41x41 HDG","Anchor rail 41x41") -> Anchor rail 41x41 HDG | G20: =D15/1000 -> 0.45 | H20: =IF(F20="",0,VLOOKUP(F20,'Cable trays (UnitPrice)'!B:F,5,0)) -> 5.9608696 | I20: =H20*G20 -> 2.6823913 | P20: =G20*O15 -> #VALUE!
F21: ENDEBESKYTTER 41X41MM | G21: 1 | H21: =IF(F21="",0,VLOOKUP(F21,'Cable trays (UnitPrice)'!B:F,5,0)) -> 0.78521739 | I21: =H21*G21 -> 0.78521739 | P21: =G21*O15 -> #VALUE!
F22: =IF(C15="HDG","Ceiling mount for anchor rail Varmf MP-230Z HDG","Ceiling mount for anchor rail Sendz MP-230S") -> Ceiling mount for anchor rail Varmf MP-230Z HDG | G22: 2 | H22: =IF(F22="",0,VLOOKUP(F22,'Cable trays (UnitPrice)'!B:F,5,0)) -> 4.1686957 | I22: =H22*G22 -> 8.3373913 | P22: =G22*O15 -> #VALUE!
H23: =IF(F23="",0,VLOOKUP(F23,'Cable trays (UnitPrice)'!B:F,5,0)) -> 0 | I23: =H23*G23 -> 0 | P23: =G23*O15 -> #VALUE!
H24: =IF(F24="",0,VLOOKUP(F24,'Cable trays (UnitPrice)'!B:F,5,0)) -> 0 | I24: =H24*G24 -> 0 | P24: =G24*O15 -> #VALUE!
A25: =CONCATENATE("Cable ",B25," ",C25," ",D25," x ",E25) -> Cable Basket HDG 300 x 100 | B25: Basket | C25: HDG | D25: 300 | E25: 100 | I25: =SUM(I26:I34) -> 30.474621 | J25: =I25*NOK2EUR -> 350.45814 | L25: =IF(D25>300,D25/1000,0.25) -> 0.25 | M25: =$M$1 -> 0.5 | N25: =L25+L25*M25 -> 0.375 | O25: =SUMIF('[55]Cable Trays - maching table'!C:C,A25,'[55]Cable Trays - maching table'!D:D) -> #VALUE!
F26: =CONCATENATE("Cable ",B25," ",C25," ",D25," x ",E25) -> Cable Basket HDG 300 x 100 | G26: 1 | H26: =IF(F26="",0,VLOOKUP(F26,'Cable trays (UnitPrice)'!B:F,5,0)) -> 11.304348 | I26: =H26*G26 -> 11.304348 | P26: =G26*O25 -> #VALUE!
F27: =CONCATENATE(B25," - Union ",C25) -> Basket - Union HDG | G27: 0.7 | H27: =IF(F27="",0,VLOOKUP(F27,'Cable trays (UnitPrice)'!B:F,5,0)) -> 0.68362045 | I27: =H27*G27 -> 0.47853432 | P27: =G27*O25 -> #VALUE!
F28: T-skrue M10x35mm Els MP-983E | G28: 4 | H28: =IF(F28="",0,VLOOKUP(F28,'Cable trays (UnitPrice)'!B:F,5,0)) -> 1.6165217 | I28: =H28*G28 -> 6.466087 | P28: =G28*O25 -> #VALUE!
F29: Hexagonal screw stainless steel, M8 x 30 +Washer M8 | G29: 8 | H29: =IF(F29="",0,VLOOKUP(F29,'Cable trays (UnitPrice)'!B:F,5,0)) -> 0.16434783 | I29: =H29*G29 -> 1.3147826 | P29: =G29*O25 -> #VALUE!
F30: =IF(C25="HDG","Anchor rail 41x41 HDG","Anchor rail 41x41") -> Anchor rail 41x41 HDG | G30: =D25/1000 -> 0.3 | H30: =IF(F30="",0,VLOOKUP(F30,'Cable trays (UnitPrice)'!B:F,5,0)) -> 5.9608696 | I30: =H30*G30 -> 1.7882609 | P30: =G30*O25 -> #VALUE!
F31: ENDEBESKYTTER 41X41MM | G31: 1 | H31: =IF(F31="",0,VLOOKUP(F31,'Cable trays (UnitPrice)'!B:F,5,0)) -> 0.78521739 | I31: =H31*G31 -> 0.78521739 | P31: =G31*O25 -> #VALUE!
F32: =IF(C25="HDG","Ceiling mount for anchor rail Varmf MP-230Z HDG","Ceiling mount for anchor rail Sendz MP-230S") -> Ceiling mount for anchor rail Varmf MP-230Z HDG | G32: 2 | H32: =IF(F32="",0,VLOOKUP(F32,'Cable trays (UnitPrice)'!B:F,5,0)) -> 4.1686957 | I32: =H32*G32 -> 8.3373913 | P32: =G32*O25 -> #VALUE!
H33: =IF(F33="",0,VLOOKUP(F33,'Cable trays (UnitPrice)'!B:F,5,0)) -> 0 | I33: =H33*G33 -> 0 | P33: =G33*O25 -> #VALUE!
H34: =IF(F34="",0,VLOOKUP(F34,'Cable trays (UnitPrice)'!B:F,5,0)) -> 0 | I34: =H34*G34 -> 0 | P34: =G34*O25 -> #VALUE!
A35: =CONCATENATE("Cable ",B35," ",C35," ",D35," x ",E35) -> Cable Basket HDG 300 x 60 | B35: Basket | C35: HDG | D35: 300 | E35: 60 | I35: =SUM(I36:I44) -> 29.661569 | J35: =I35*NOK2EUR -> 341.10804 | L35: =IF(D35>300,D35/1000,0.25) -> 0.25 | M35: =$M$1 -> 0.5 | N35: =L35+L35*M35 -> 0.375 | O35: =SUMIF('[55]Cable Trays - maching table'!C:C,A35,'[55]Cable Trays - maching table'!D:D) -> #VALUE!
F36: =CONCATENATE("Cable ",B35," ",C35," ",D35," x ",E35) -> Cable Basket HDG 300 x 60 | G36: 1 | H36: =IF(F36="",0,VLOOKUP(F36,'Cable trays (UnitPrice)'!B:F,5,0)) -> 10.491295 | I36: =H36*G36 -> 10.491295 | P36: =G36*O35 -> #VALUE!
F37: =CONCATENATE(B35," - Union ",C35) -> Basket - Union HDG | G37: 0.7 | H37: =IF(F37="",0,VLOOKUP(F37,'Cable trays (UnitPrice)'!B:F,5,0)) -> 0.68362045 | I37: =H37*G37 -> 0.47853432 | P37: =G37*O35 -> #VALUE!
F38: T-skrue M10x35mm Els MP-983E | G38: 4 | H38: =IF(F38="",0,VLOOKUP(F38,'Cable trays (UnitPrice)'!B:F,5,0)) -> 1.6165217 | I38: =H38*G38 -> 6.466087 | P38: =G38*O35 -> #VALUE!
F39: Hexagonal screw stainless steel, M8 x 30 +Washer M8 | G39: 8 | H39: =IF(F39="",0,VLOOKUP(F39,'Cable trays (UnitPrice)'!B:F,5,0)) -> 0.16434783 | I39: =H39*G39 -> 1.3147826 | P39: =G39*O35 -> #VALUE!
F40: =IF(C35="HDG","Anchor rail 41x41 HDG","Anchor rail 41x41") -> Anchor rail 41x41 HDG | G40: =D35/1000 -> 0.3 | H40: =IF(F40="",0,VLOOKUP(F40,'Cable trays (UnitPrice)'!B:F,5,0)) -> 5.9608696 | I40: =H40*G40 -> 1.7882609 | P40: =G40*O35 -> #VALUE!
F41: ENDEBESKYTTER 41X41MM | G41: 1 | H41: =IF(F41="",0,VLOOKUP(F41,'Cable trays (UnitPrice)'!B:F,5,0)) -> 0.78521739 | I41: =H41*G41 -> 0.78521739 | P41: =G41*O35 -> #VALUE!
F42: =IF(C35="HDG","Ceiling mount for anchor rail Varmf MP-230Z HDG","Ceiling mount for anchor rail Sendz MP-230S") -> Ceiling mount for anchor rail Varmf MP-230Z HDG | G42: 2 | H42: =IF(F42="",0,VLOOKUP(F42,'Cable trays (UnitPrice)'!B:F,5,0)) -> 4.1686957 | I42: =H42*G42 -> 8.3373913 | P42: =G42*O35 -> #VALUE!
H43: =IF(F43="",0,VLOOKUP(F43,'Cable trays (UnitPrice)'!B:F,5,0)) -> 0 | I43: =H43*G43 -> 0 | P43: =G43*O35 -> #VALUE!
H44: =IF(F44="",0,VLOOKUP(F44,'Cable trays (UnitPrice)'!B:F,5,0)) -> 0 | I44: =H44*G44 -> 0 | P44: =G44*O35 -> #VALUE!
A45: =CONCATENATE("Cable ",B45," ",C45," ",D45," x ",E45) -> Cable Basket HDG 300 x 50 | B45: Basket | C45: HDG | D45: 300 | E45: 50 | I45: =SUM(I46:I54) -> 29.661569 | J45: =I45*NOK2EUR -> 341.10804 | L45: =IF(D45>300,D45/1000,0.25) -> 0.25 | M45: =$M$1 -> 0.5 | N45: =L45+L45*M45 -> 0.375 | O45: =SUMIF('[55]Cable Trays - maching table'!C:C,A45,'[55]Cable Trays - maching table'!D:D) -> #VALUE!
F46: =CONCATENATE("Cable ",B45," ",C45," ",D45," x ",E45) -> Cable Basket HDG 300 x 50 | G46: 1 | H46: =IF(F46="",0,VLOOKUP(F46,'Cable trays (UnitPrice)'!B:F,5,0)) -> 10.491295 | I46: =H46*G46 -> 10.491295 | P46: =G46*O45 -> #VALUE!
F47: =CONCATENATE(B45," - Union ",C45) -> Basket - Union HDG | G47: 0.7 | H47: =IF(F47="",0,VLOOKUP(F47,'Cable trays (UnitPrice)'!B:F,5,0)) -> 0.68362045 | I47: =H47*G47 -> 0.47853432 | P47: =G47*O45 -> #VALUE!
F48: T-skrue M10x35mm Els MP-983E | G48: 4 | H48: =IF(F48="",0,VLOOKUP(F48,'Cable trays (UnitPrice)'!B:F,5,0)) -> 1.6165217 | I48: =H48*G48 -> 6.466087 | P48: =G48*O45 -> #VALUE!
F49: Hexagonal screw stainless steel, M8 x 30 +Washer M8 | G49: 8 | H49: =IF(F49="",0,VLOOKUP(F49,'Cable trays (UnitPrice)'!B:F,5,0)) -> 0.16434783 | I49: =H49*G49 -> 1.3147826 | P49: =G49*O45 -> #VALUE!
F50: =IF(C45="HDG","Anchor rail 41x41 HDG","Anchor rail 41x41") -> Anchor rail 41x41 HDG | G50: =D45/1000 -> 0.3 | H50: =IF(F50="",0,VLOOKUP(F50,'Cable trays (UnitPrice)'!B:F,5,0)) -> 5.9608696 | I50: =H50*G50 -> 1.7882609 | P50: =G50*O45 -> #VALUE!
F51: ENDEBESKYTTER 41X41MM | G51: 1 | H51: =IF(F51="",0,VLOOKUP(F51,'Cable trays (UnitPrice)'!B:F,5,0)) -> 0.78521739 | I51: =H51*G51 -> 0.78521739 | P51: =G51*O45 -> #VALUE!
F52: =IF(C45="HDG","Ceiling mount for anchor rail Varmf MP-230Z HDG","Ceiling mount for anchor rail Sendz MP-230S") -> Ceiling mount for anchor rail Varmf MP-230Z HDG | G52: 2 | H52: =IF(F52="",0,VLOOKUP(F52,'Cable trays (UnitPrice)'!B:F,5,0)) -> 4.1686957 | I52: =H52*G52 -> 8.3373913 | P52: =G52*O45 -> #VALUE!
H53: =IF(F53="",0,VLOOKUP(F53,'Cable trays (UnitPrice)'!B:F,5,0)) -> 0 | I53: =H53*G53 -> 0 | P53: =G53*O45 -> #VALUE!
H54: =IF(F54="",0,VLOOKUP(F54,'Cable trays (UnitPrice)'!B:F,5,0)) -> 0 | I54: =H54*G54 -> 0 | P54: =G54*O45 -> #VALUE!
A55: =CONCATENATE("Cable ",B55," ",C55," ",D55," x ",E55) -> Cable Basket HDG 200 x 60 | B55: Basket | C55: HDG | D55: 200 | E55: 60 | I55: =SUM(I56:I64) -> 27.292626 | J55: =I55*NOK2EUR -> 313.8652 | L55: =IF(D55>300,D55/1000,0.25) -> 0.25 | M55: =$M$1 -> 0.5 | N55: =L55+L55*M55 -> 0.375 | O55: =SUMIF('[55]Cable Trays - maching table'!C:C,A55,'[55]Cable Trays - maching table'!D:D) -> #VALUE!
F56: =CONCATENATE("Cable ",B55," ",C55," ",D55," x ",E55) -> Cable Basket HDG 200 x 60 | G56: 1 | H56: =IF(F56="",0,VLOOKUP(F56,'Cable trays (UnitPrice)'!B:F,5,0)) -> 8.7184395 | I56: =H56*G56 -> 8.7184395 | P56: =G56*O55 -> #VALUE!
F57: =CONCATENATE(B55," - Union ",C55) -> Basket - Union HDG | G57: 0.7 | H57: =IF(F57="",0,VLOOKUP(F57,'Cable trays (UnitPrice)'!B:F,5,0)) -> 0.68362045 | I57: =H57*G57 -> 0.47853432 | P57: =G57*O55 -> #VALUE!
F58: T-skrue M10x35mm Els MP-983E | G58: 4 | H58: =IF(F58="",0,VLOOKUP(F58,'Cable trays (UnitPrice)'!B:F,5,0)) -> 1.6165217 | I58: =H58*G58 -> 6.466087 | P58: =G58*O55 -> #VALUE!
F59: Hexagonal screw stainless steel, M8 x 30 +Washer M8 | G59: 8 | H59: =IF(F59="",0,VLOOKUP(F59,'Cable trays (UnitPrice)'!B:F,5,0)) -> 0.16434783 | I59: =H59*G59 -> 1.3147826 | P59: =G59*O55 -> #VALUE!
F60: =IF(C55="HDG","Anchor rail 41x41 HDG","Anchor rail 41x41") -> Anchor rail 41x41 HDG | G60: =D55/1000 -> 0.2 | H60: =IF(F60="",0,VLOOKUP(F60,'Cable trays (UnitPrice)'!B:F,5,0)) -> 5.9608696 | I60: =H60*G60 -> 1.1921739 | P60: =G60*O55 -> #VALUE!
F61: ENDEBESKYTTER 41X41MM | G61: 1 | H61: =IF(F61="",0,VLOOKUP(F61,'Cable trays (UnitPrice)'!B:F,5,0)) -> 0.78521739 | I61: =H61*G61 -> 0.78521739 | P61: =G61*O55 -> #VALUE!
F62: =IF(C55="HDG","Ceiling mount for anchor rail Varmf MP-230Z HDG","Ceiling mount for anchor rail Sendz MP-230S") -> Ceiling mount for anchor rail Varmf MP-230Z HDG | G62: 2 | H62: =IF(F62="",0,VLOOKUP(F62,'Cable trays (UnitPrice)'!B:F,5,0)) -> 4.1686957 | I62: =H62*G62 -> 8.3373913 | P62: =G62*O55 -> #VALUE!
H63: =IF(F63="",0,VLOOKUP(F63,'Cable trays (UnitPrice)'!B:F,5,0)) -> 0 | I63: =H63*G63 -> 0 | P63: =G63*O55 -> #VALUE!
H64: =IF(F64="",0,VLOOKUP(F64,'Cable trays (UnitPrice)'!B:F,5,0)) -> 0 | I64: =H64*G64 -> 0 | P64: =G64*O55 -> #VALUE!
A65: =CONCATENATE("Cable ",B65," ",C65," ",D65," x ",E65) -> Cable Basket HDG 200 x 50 | B65: Basket | C65: HDG | D65: 200 | E65: 50 | I65: =SUM(I66:I74) -> 27.292626 | J65: =I65*NOK2EUR -> 313.8652 | L65: =IF(D65>300,D65/1000,0.25) -> 0.25 | M65: =$M$1 -> 0.5 | N65: =L65+L65*M65 -> 0.375 | O65: =SUMIF('[55]Cable Trays - maching table'!C:C,A65,'[55]Cable Trays - maching table'!D:D) -> #VALUE!
F66: =CONCATENATE("Cable ",B65," ",C65," ",D65," x ",E65) -> Cable Basket HDG 200 x 50 | G66: 1 | H66: =IF(F66="",0,VLOOKUP(F66,'Cable trays (UnitPrice)'!B:F,5,0)) -> 8.7184395 | I66: =H66*G66 -> 8.7184395 | P66: =G66*O65 -> #VALUE!
F67: =CONCATENATE(B65," - Union ",C65) -> Basket - Union HDG | G67: 0.7 | H67: =IF(F67="",0,VLOOKUP(F67,'Cable trays (UnitPrice)'!B:F,5,0)) -> 0.68362045 | I67: =H67*G67 -> 0.47853432 | P67: =G67*O65 -> #VALUE!
F68: T-skrue M10x35mm Els MP-983E | G68: 4 | H68: =IF(F68="",0,VLOOKUP(F68,'Cable trays (UnitPrice)'!B:F,5,0)) -> 1.6165217 | I68: =H68*G68 -> 6.466087 | P68: =G68*O65 -> #VALUE!
F69: Hexagonal screw stainless steel, M8 x 30 +Washer M8 | G69: 8 | H69: =IF(F69="",0,VLOOKUP(F69,'Cable trays (UnitPrice)'!B:F,5,0)) -> 0.16434783 | I69: =H69*G69 -> 1.3147826 | P69: =G69*O65 -> #VALUE!
F70: =IF(C65="HDG","Anchor rail 41x41 HDG","Anchor rail 41x41") -> Anchor rail 41x41 HDG | G70: =D65/1000 -> 0.2 | H70: =IF(F70="",0,VLOOKUP(F70,'Cable trays (UnitPrice)'!B:F,5,0)) -> 5.9608696 | I70: =H70*G70 -> 1.1921739 | P70: =G70*O65 -> #VALUE!
F71: ENDEBESKYTTER 41X41MM | G71: 1 | H71: =IF(F71="",0,VLOOKUP(F71,'Cable trays (UnitPrice)'!B:F,5,0)) -> 0.78521739 | I71: =H71*G71 -> 0.78521739 | P71: =G71*O65 -> #VALUE!
F72: =IF(C65="HDG","Ceiling mount for anchor rail Varmf MP-230Z HDG","Ceiling mount for anchor rail Sendz MP-230S") -> Ceiling mount for anchor rail Varmf MP-230Z HDG | G72: 2 | H72: =IF(F72="",0,VLOOKUP(F72,'Cable trays (UnitPrice)'!B:F,5,0)) -> 4.1686957 | I72: =H72*G72 -> 8.3373913 | P72: =G72*O65 -> #VALUE!
H73: =IF(F73="",0,VLOOKUP(F73,'Cable trays (UnitPrice)'!B:F,5,0)) -> 0 | I73: =H73*G73 -> 0 | P73: =G73*O65 -> #VALUE!
H74: =IF(F74="",0,VLOOKUP(F74,'Cable trays (UnitPrice)'!B:F,5,0)) -> 0 | I74: =H74*G74 -> 0 | P74: =G74*O65 -> #VALUE!
A75: =CONCATENATE("Cable ",B75," ",C75," ",D75," x ",E75) -> Cable Basket HDG 150 x 60 | B75: Basket | C75: HDG | D75: 150 | E75: 60 | I75: =SUM(I76:I84) -> 26.994583 | J75: =I75*NOK2EUR -> 310.4377 | L75: =IF(D75>300,D75/1000,0.25) -> 0.25 | M75: =$M$1 -> 0.5 | N75: =L75+L75*M75 -> 0.375 | O75: =SUMIF('[55]Cable Trays - maching table'!C:C,A75,'[55]Cable Trays - maching table'!D:D) -> #VALUE!
F76: =CONCATENATE("Cable ",B75," ",C75," ",D75," x ",E75) -> Cable Basket HDG 150 x 60 | G76: 1 | H76: =IF(F76="",0,VLOOKUP(F76,'Cable trays (UnitPrice)'!B:F,5,0)) -> 8.7184395 | I76: =H76*G76 -> 8.7184395 | P76: =G76*O75 -> #VALUE!
F77: =CONCATENATE(B75," - Union ",C75) -> Basket - Union HDG | G77: 0.7 | H77: =IF(F77="",0,VLOOKUP(F77,'Cable trays (UnitPrice)'!B:F,5,0)) -> 0.68362045 | I77: =H77*G77 -> 0.47853432 | P77: =G77*O75 -> #VALUE!
F78: T-skrue M10x35mm Els MP-983E | G78: 4 | H78: =IF(F78="",0,VLOOKUP(F78,'Cable trays (UnitPrice)'!B:F,5,0)) -> 1.6165217 | I78: =H78*G78 -> 6.466087 | P78: =G78*O75 -> #VALUE!
F79: Hexagonal screw stainless steel, M8 x 30 +Washer M8 | G79: 8 | H79: =IF(F79="",0,VLOOKUP(F79,'Cable trays (UnitPrice)'!B:F,5,0)) -> 0.16434783 | I79: =H79*G79 -> 1.3147826 | P79: =G79*O75 -> #VALUE!
F80: =IF(C75="HDG","Anchor rail 41x41 HDG","Anchor rail 41x41") -> Anchor rail 41x41 HDG | G80: =D75/1000 -> 0.15 | H80: =IF(F80="",0,VLOOKUP(F80,'Cable trays (UnitPrice)'!B:F,5,0)) -> 5.9608696 | I80: =H80*G80 -> 0.89413043 | P80: =G80*O75 -> #VALUE!
F81: ENDEBESKYTTER 41X41MM | G81: 1 | H81: =IF(F81="",0,VLOOKUP(F81,'Cable trays (UnitPrice)'!B:F,5,0)) -> 0.78521739 | I81: =H81*G81 -> 0.78521739 | P81: =G81*O75 -> #VALUE!
F82: =IF(C75="HDG","Ceiling mount for anchor rail Varmf MP-230Z HDG","Ceiling mount for anchor rail Sendz MP-230S") -> Ceiling mount for anchor rail Varmf MP-230Z HDG | G82: 2 | H82: =IF(F82="",0,VLOOKUP(F82,'Cable trays (UnitPrice)'!B:F,5,0)) -> 4.1686957 | I82: =H82*G82 -> 8.3373913 | P82: =G82*O75 -> #VALUE!
H83: =IF(F83="",0,VLOOKUP(F83,'Cable trays (UnitPrice)'!B:F,5,0)) -> 0 | I83: =H83*G83 -> 0 | P83: =G83*O75 -> #VALUE!
H84: =IF(F84="",0,VLOOKUP(F84,'Cable trays (UnitPrice)'!B:F,5,0)) -> 0 | I84: =H84*G84 -> 0 | P84: =G84*O75 -> #VALUE!
A85: =CONCATENATE("Cable ",B85," ",C85," ",D85," x ",E85) -> Cable Basket HDG 150 x 50 | B85: Basket | C85: HDG | D85: 150 | E85: 50 | I85: =SUM(I86:I94) -> 26.994583 | J85: =I85*NOK2EUR -> 310.4377 | L85: =IF(D85>300,D85/1000,0.25) -> 0.25 | M85: =$M$1 -> 0.5 | N85: =L85+L85*M85 -> 0.375 | O85: =SUMIF('[55]Cable Trays - maching table'!C:C,A85,'[55]Cable Trays - maching table'!D:D) -> #VALUE!
F86: =CONCATENATE("Cable ",B85," ",C85," ",D85," x ",E85) -> Cable Basket HDG 150 x 50 | G86: 1 | H86: =IF(F86="",0,VLOOKUP(F86,'Cable trays (UnitPrice)'!B:F,5,0)) -> 8.7184395 | I86: =H86*G86 -> 8.7184395 | P86: =G86*O85 -> #VALUE!
F87: =CONCATENATE(B85," - Union ",C85) -> Basket - Union HDG | G87: 0.7 | H87: =IF(F87="",0,VLOOKUP(F87,'Cable trays (UnitPrice)'!B:F,5,0)) -> 0.68362045 | I87: =H87*G87 -> 0.47853432 | P87: =G87*O85 -> #VALUE!
F88: T-skrue M10x35mm Els MP-983E | G88: 4 | H88: =IF(F88="",0,VLOOKUP(F88,'Cable trays (UnitPrice)'!B:F,5,0)) -> 1.6165217 | I88: =H88*G88 -> 6.466087 | P88: =G88*O85 -> #VALUE!
F89: Hexagonal screw stainless steel, M8 x 30 +Washer M8 | G89: 8 | H89: =IF(F89="",0,VLOOKUP(F89,'Cable trays (UnitPrice)'!B:F,5,0)) -> 0.16434783 | I89: =H89*G89 -> 1.3147826 | P89: =G89*O85 -> #VALUE!
F90: =IF(C85="HDG","Anchor rail 41x41 HDG","Anchor rail 41x41") -> Anchor rail 41x41 HDG | G90: =D85/1000 -> 0.15 | H90: =IF(F90="",0,VLOOKUP(F90,'Cable trays (UnitPrice)'!B:F,5,0)) -> 5.9608696 | I90: =H90*G90 -> 0.89413043 | P90: =G90*O85 -> #VALUE!
F91: ENDEBESKYTTER 41X41MM | G91: 1 | H91: =IF(F91="",0,VLOOKUP(F91,'Cable trays (UnitPrice)'!B:F,5,0)) -> 0.78521739 | I91: =H91*G91 -> 0.78521739 | P91: =G91*O85 -> #VALUE!
F92: =IF(C85="HDG","Ceiling mount for anchor rail Varmf MP-230Z HDG","Ceiling mount for anchor rail Sendz MP-230S") -> Ceiling mount for anchor rail Varmf MP-230Z HDG | G92: 2 | H92: =IF(F92="",0,VLOOKUP(F92,'Cable trays (UnitPrice)'!B:F,5,0)) -> 4.1686957 | I92: =H92*G92 -> 8.3373913 | P92: =G92*O85 -> #VALUE!
H93: =IF(F93="",0,VLOOKUP(F93,'Cable trays (UnitPrice)'!B:F,5,0)) -> 0 | I93: =H93*G93 -> 0 | P93: =G93*O85 -> #VALUE!
H94: =IF(F94="",0,VLOOKUP(F94,'Cable trays (UnitPrice)'!B:F,5,0)) -> 0 | I94: =H94*G94 -> 0 | P94: =G94*O85 -> #VALUE!
A95: =CONCATENATE("Cable ",B95," ",C95," ",D95," x ",E95) -> Cable Basket PRE Galv. 600 x 150 | B95: Basket | C95: PRE Galv. | D95: 600 | E95: 150 | I95: =SUM(I96:I104) -> 40.471507 | J95: =I95*NOK2EUR -> 465.42233 | L95: =IF(D95>300,D95/1000,0.25) -> 0.6 | M95: =$M$1 -> 0.5 | N95: =L95+L95*M95 -> 0.9 | O95: =SUMIF('[55]Cable Trays - maching table'!C:C,A95,'[55]Cable Trays - maching table'!D:D) -> #VALUE!
F96: =CONCATENATE("Cable ",B95," ",C95," ",D95," x ",E95) -> Cable Basket PRE Galv. 600 x 150 | G96: 1 | H96: =IF(F96="",0,VLOOKUP(F96,'Cable trays (UnitPrice)'!B:F,5,0)) -> 22.608696 | I96: =H96*G96 -> 22.608696 | P96: =G96*O95 -> #VALUE!
F97: =CONCATENATE(B95," - Union ",C95) -> Basket - Union PRE Galv. | G97: 0.7 | H97: =IF(F97="",0,VLOOKUP(F97,'Cable trays (UnitPrice)'!B:F,5,0)) -> 0.50587914 | I97: =H97*G97 -> 0.3541154 | P97: =G97*O95 -> #VALUE!
F98: T-skrue M10x35mm Els MP-983E | G98: 4 | H98: =IF(F98="",0,VLOOKUP(F98,'Cable trays (UnitPrice)'!B:F,5,0)) -> 1.6165217 | I98: =H98*G98 -> 6.466087 | P98: =G98*O95 -> #VALUE!
F99: Hexagonal screw stainless steel, M8 x 30 +Washer M8 | G99: 8 | H99: =IF(F99="",0,VLOOKUP(F99,'Cable trays (UnitPrice)'!B:F,5,0)) -> 0.16434783 | I99: =H99*G99 -> 1.3147826 | P99: =G99*O95 -> #VALUE!
F100: =IF(C95="HDG","Anchor rail 41x41 HDG","Anchor rail 41x41") -> Anchor rail 41x41 | G100: =D95/1000 -> 0.6 | H100: =IF(F100="",0,VLOOKUP(F100,'Cable trays (UnitPrice)'!B:F,5,0)) -> 4.0869565 | I100: =H100*G100 -> 2.4521739 | P100: =G100*O95 -> #VALUE!
F101: ENDEBESKYTTER 41X41MM | G101: 1 | H101: =IF(F101="",0,VLOOKUP(F101,'Cable trays (UnitPrice)'!B:F,5,0)) -> 0.78521739 | I101: =H101*G101 -> 0.78521739 | P101: =G101*O95 -> #VALUE!
...

Sheet Cable trays (UnitPrice)
A1: Pos. | B1: Description | C1: QT | D1: Price NOK | E1: Price EURO | F1: Total Price € | G1: ref. | H1: Supplier | I1: unit | J1: % | K1: Total | L1: Update price date | M1: Total Qty Used | N1: Total € Used - cost | O1: Total € Used - sales
B2: General items | D2: ='[55]Project Input'!E32 -> 11.5 | F2: Cable Trays | G2: Fittings | L2: =SUBTOTAL(3,L4:L1036)/SUBTOTAL(3,I4:I1036) -> 1.0018975 | N2: =SUBTOTAL(9,N4:N931) -> #VALUE! | O2: =#REF! -> #REF! | P2: =N2-N3 -> #VALUE!
N3: 3131529.1 | O3: 3707685.7 | P3: before updated BA price 08.jan
L5: "ctrl + ;" add today date | M5: =SUMIF('Cable trays + Fittings'!F:F,'Cable trays (UnitPrice)'!B5,'Cable trays + Fittings'!P:P) -> 0
M6: =SUMIF('Cable trays + Fittings'!F:F,'Cable trays (UnitPrice)'!B6,'Cable trays + Fittings'!P:P) -> 0
A7: 1. | B7: General items: | M7: =SUMIF('Cable trays + Fittings'!F:F,'Cable trays (UnitPrice)'!B7,'Cable trays + Fittings'!P:P) -> 0 | N7: =M7*F7 -> 0
A8: 1.1 | B8: Miscellaneous | C8: 1 | D8: 1 | E8: =D8/NOK2EUR -> 0.086956522 | F8: =C8*E8 -> 0.086956522 | K8: not found | M8: =SUMIF('Cable trays + Fittings'!F:F,'Cable trays (UnitPrice)'!B8,'Cable trays + Fittings'!P:P) -> 0 | N8: =M8*F8 -> 0 | R8: 1 | S8: =D8-R8 -> 0
A9: 1.2 | B9: Support | C9: 1 | D9: 390 | E9: =D9/NOK2EUR -> 33.913043 | F9: =C9*E9 -> 33.913043 | K9: not found | M9: =SUMIF('Cable trays + Fittings'!F:F,'Cable trays (UnitPrice)'!B9,'Cable trays + Fittings'!P:P) -> 0 | N9: =M9*F9 -> 0 | R9: 390 | S9: =D9-R9 -> 0
A10: 1.3 | B10: T-skrue M10x35mm Els MP-983E | C10: 1 | D10: =K10 -> 18.59 | E10: =D10/NOK2EUR -> 1.6165217 | F10: =C10*E10 -> 1.6165217 | I10: un | K10: 18.59 | L10: 45665 | M10: =SUMIF('Cable trays + Fittings'!F:F,'Cable trays (UnitPrice)'!B10,'Cable trays + Fittings'!P:P) -> #VALUE! | N10: =M10*F10 -> #VALUE! | R10: 22.76 | S10: =D10-R10 -> -4.17
A11: 1.4 | B11: Hexagonal screw stainless steel, M8 x 30 +Washer M8 | C11: 1 | D11: =0.21+1.68 -> 1.89 | E11: =D11/NOK2EUR -> 0.16434783 | F11: =C11*E11 -> 0.16434783 | I11: un | K11: not found | L11: 45665 | M11: =SUMIF('Cable trays + Fittings'!F:F,'Cable trays (UnitPrice)'!B11,'Cable trays + Fittings'!P:P) -> #VALUE! | N11: =M11*F11 -> #VALUE! | R11: 31.2 | S11: =D11-R11 -> -29.31
A12: 1.5 | B12: Anchor rail 41x21 | C12: 1 | D12: 58.3 | E12: =D12/NOK2EUR -> 5.0695652 | F12: =C12*E12 -> 5.0695652 | K12: not found | M12: =SUMIF('Cable trays + Fittings'!F:F,'Cable trays (UnitPrice)'!B12,'Cable trays + Fittings'!P:P) -> 0 | N12: =M12*F12 -> 0 | R12: 58.3 | S12: =D12-R12 -> 0
A13: 1.6 | B13: Anchor rail 41x41 | C13: 1 | D13: =K13 -> 47 | E13: =D13/NOK2EUR -> 4.0869565 | F13: =C13*E13 -> 4.0869565 | I13: un | K13: 47 | L13: 45665 | M13: =SUMIF('Cable trays + Fittings'!F:F,'Cable trays (UnitPrice)'!B13,'Cable trays + Fittings'!P:P) -> #VALUE! | N13: =M13*F13 -> #VALUE! | R13: =89.2*1.1 -> 98.12 | S13: =D13-R13 -> -51.12
A14: 1.7 | B14: Anchor rail 41x41 HDG | C14: 1 | D14: =K14 -> 68.55 | E14: =D14/NOK2EUR -> 5.9608696 | F14: =C14*E14 -> 5.9608696 | I14: un | K14: 68.55 | L14: 45665 | M14: =SUMIF('Cable trays + Fittings'!F:F,'Cable trays (UnitPrice)'!B14,'Cable trays + Fittings'!P:P) -> #VALUE! | N14: =M14*F14 -> #VALUE! | R14: =132*1.1 -> 145.2 | S14: =D14-R14 -> -76.65
A15: 1.8 | B15: Ankerskinne Anchor rail 41x41 Sendz MP-233S | C15: 1 | D15: =76.1/3 -> 25.366667 | E15: =D15/NOK2EUR -> 2.2057971 | F15: =C15*E15 -> 2.2057971 | G15: 1353837 | I15: un | K15: not found | L15: 45624 | M15: =SUMIF('Cable trays + Fittings'!F:F,'Cable trays (UnitPrice)'!B15,'Cable trays + Fittings'!P:P) -> 0 | N15: =M15*F15 -> 0 | R15: =76.1/3 -> 25.366667 | S15: =D15-R15 -> 0
A16: 1.9 | B16: ENDEBESKYTTER 41X41MM | C16: 1 | D16: =K16 -> 9.03 | E16: =D16/NOK2EUR -> 0.78521739 | F16: =C16*E16 -> 0.78521739 | G16: 1353719 | I16: un | K16: 9.03 | L16: 45665 | M16: =SUMIF('Cable trays + Fittings'!F:F,'Cable trays (UnitPrice)'!B16,'Cable trays + Fittings'!P:P) -> #VALUE! | N16: =M16*F16 -> #VALUE! | R16: 34.23 | S16: =D16-R16 -> -25.2
A17: 1.10 | B17: BEND 20MM 90GRAD STÅL 3016122 | C17: 1 | D17: 290 | E17: =D17/NOK2EUR -> 25.217391 | F17: =C17*E17 -> 25.217391 | K17: not found | M17: =SUMIF('Cable trays + Fittings'!F:F,'Cable trays (UnitPrice)'!B17,'Cable trays + Fittings'!P:P) -> 0 | N17: =M17*F17 -> 0 | R17: 290 | S17: =D17-R17 -> 0
A18: 1.11 | B18: Ceiling mount for anchor rail Sendz MP-230S | C18: 1 | D18: =K18 -> 37.32 | E18: =D18/NOK2EUR -> 3.2452174 | F18: =C18*E18 -> 3.2452174 | I18: un | K18: 37.32 | L18: 45665 | M18: =SUMIF('Cable trays + Fittings'!F:F,'Cable trays (UnitPrice)'!B18,'Cable trays + Fittings'!P:P) -> #VALUE! | N18: =M18*F18 -> #VALUE! | R18: 36.25 | S18: =D18-R18 -> 1.07
A19: 1.12 | B19: Ceiling mount for anchor rail Varmf MP-230Z HDG | C19: 1 | D19: =K19 -> 47.94 | E19: =D19/NOK2EUR -> 4.1686957 | F19: =C19*E19 -> 4.1686957 | I19: un | K19: 47.94 | L19: 45665 | M19: =SUMIF('Cable trays + Fittings'!F:F,'Cable trays (UnitPrice)'!B19,'Cable trays + Fittings'!P:P) -> #VALUE! | N19: =M19*F19 -> #VALUE! | R19: 53.04 | S19: =D19-R19 -> -5.1
A20: 1.13 | B20: ELIS FEST BETONGSKRUE 7,5X45C4 | C20: 1 | D20: 5.3 | E20: =D20/NOK2EUR -> 0.46086957 | F20: =C20*E20 -> 0.46086957 | K20: not found | M20: =SUMIF('Cable trays + Fittings'!F:F,'Cable trays (UnitPrice)'!B20,'Cable trays + Fittings'!P:P) -> 0 | N20: =M20*F20 -> 0 | R20: 5.3 | S20: =D20-R20 -> 0
A21: 1.14 | B21: GSV 34 G | C21: 1 | D21: 97.7 | E21: =D21/NOK2EUR -> 8.4956522 | F21: =C21*E21 -> 8.4956522 | K21: not found | M21: =SUMIF('Cable trays + Fittings'!F:F,'Cable trays (UnitPrice)'!B21,'Cable trays + Fittings'!P:P) -> 0 | N21: =M21*F21 -> 0 | R21: 97.7 | S21: =D21-R21 -> 0
A22: 1.15 | B22: GURT 20MM STÅLRØR TYNNVEGGET | C22: 1 | D22: =43.13/3 -> 14.376667 | E22: =D22/NOK2EUR -> 1.2501449 | F22: =C22*E22 -> 1.2501449 | K22: not found | M22: =SUMIF('Cable trays + Fittings'!F:F,'Cable trays (UnitPrice)'!B22,'Cable trays + Fittings'!P:P) -> 0 | N22: =M22*F22 -> 0 | R22: =43.13/3 -> 14.376667 | S22: =D22-R22 -> 0
A23: 1.16 | B23: GURT 25MM STÅLRØR TYNNVEGGET | C23: 1 | D23: =66.35/3 -> 22.116667 | E23: =D23/NOK2EUR -> 1.9231884 | F23: =C23*E23 -> 1.9231884 | K23: not found | M23: =SUMIF('Cable trays + Fittings'!F:F,'Cable trays (UnitPrice)'!B23,'Cable trays + Fittings'!P:P) -> 0 | N23: =M23*F23 -> 0 | R23: =66.35/3 -> 22.116667 | S23: =D23-R23 -> 0
A24: 1.17 | B24: KJØTEMUFFE 20MM STÅL 3015172 | C24: 1 | D24: 60.33 | E24: =D24/NOK2EUR -> 5.246087 | F24: =C24*E24 -> 5.246087 | K24: not found | M24: =SUMIF('Cable trays + Fittings'!F:F,'Cable trays (UnitPrice)'!B24,'Cable trays + Fittings'!P:P) -> 0 | N24: =M24*F24 -> 0 | R24: 60.33 | S24: =D24-R24 -> 0
A25: 1.18 | B25: TGE-T16 SKRUE 4.2 X 16 GRABBER | C25: 1 | D25: 0.71 | E25: =D25/NOK2EUR -> 0.06173913 | F25: =C25*E25 -> 0.06173913 | K25: not found | M25: =SUMIF('Cable trays + Fittings'!F:F,'Cable trays (UnitPrice)'!B25,'Cable trays + Fittings'!P:P) -> 0 | N25: =M25*F25 -> 0 | R25: 0.71 | S25: =D25-R25 -> 0
A26: 1.19 | B26: TKS-ER 20 SADEL RUSTFRI | C26: 1 | D26: 2.5 | E26: =D26/NOK2EUR -> 0.2173913 | F26: =C26*E26 -> 0.2173913 | K26: not found | M26: =SUMIF('Cable trays + Fittings'!F:F,'Cable trays (UnitPrice)'!B26,'Cable trays + Fittings'!P:P) -> 0 | N26: =M26*F26 -> 0 | R26: 2.5 | S26: =D26-R26 -> 0
A27: 1.20 | B27: TP 2 PLASTPLUGG 35MM RØD | C27: 1 | D27: 0.67 | E27: =D27/NOK2EUR -> 0.05826087 | F27: =C27*E27 -> 0.05826087 | K27: not found | M27: =SUMIF('Cable trays + Fittings'!F:F,'Cable trays (UnitPrice)'!B27,'Cable trays + Fittings'!P:P) -> 0 | N27: =M27*F27 -> 0 | R27: 0.67 | S27: =D27-R27 -> 0
A28: 1.21 | B28: Veggkonsoll KL 300mm Sendz MP-754S | C28: 1 | D28: 55.64 | E28: =D28/NOK2EUR -> 4.8382609 | F28: =C28*E28 -> 4.8382609 | K28: not found | M28: =SUMIF('Cable trays + Fittings'!F:F,'Cable trays (UnitPrice)'!B28,'Cable trays + Fittings'!P:P) -> 0 | N28: =M28*F28 -> 0 | R28: 55.64 | S28: =D28-R28 -> 0
A29: 1.22 | B29: Veggkonsoll KL 400mm Sendz MP-754S | C29: 1 | D29: 64.35 | E29: =D29/NOK2EUR -> 5.5956522 | F29: =C29*E29 -> 5.5956522 | K29: not found | M29: =SUMIF('Cable trays + Fittings'!F:F,'Cable trays (UnitPrice)'!B29,'Cable trays + Fittings'!P:P) -> 0 | N29: =M29*F29 -> 0 | R29: 64.35 | S29: =D29-R29 -> 0
A30: 1.23 | B30: Veggkonsoll KL 600mm Sendz MP-762S | C30: 1 | D30: 97.7 | E30: =D30/NOK2EUR -> 8.4956522 | F30: =C30*E30 -> 8.4956522 | K30: not found | M30: =SUMIF('Cable trays + Fittings'!F:F,'Cable trays (UnitPrice)'!B30,'Cable trays + Fittings'!P:P) -> 0 | N30: =M30*F30 -> 0 | R30: 97.7 | S30: =D30-R30 -> 0
S31: =D31-R31 -> 0
S32: =D32-R32 -> 0
A33: 2. | B33: Cable Trays: | S33: =D33-R33 -> 0
A34: 2.1 | B34: Cable Basket HDG 600 x 250 | C34: 1 | D34: 440.5 | E34: =D34/NOK2EUR -> 38.304348 | F34: =C34*E34 -> 38.304348 | I34: m | K34: not found | L34: 45624 | M34: =SUMIF('Cable trays + Fittings'!F:F,'Cable trays (UnitPrice)'!B34,'Cable trays + Fittings'!P:P) -> 0 | N34: =M34*F34 -> 0 | R34: 440.5 | S34: =D34-R34 -> 0
A35: 2.2 | B35: Cable Basket HDG 450 x 60 | C35: 1 | D35: =K35 -> 195.1782 | E35: =D35/NOK2EUR -> 16.972017 | F35: =C35*E35 -> 16.972017 | I35: m | K35: 195.1782 | L35: 45665 | M35: =SUMIF('Cable trays + Fittings'!F:F,'Cable trays (UnitPrice)'!B35,'Cable trays + Fittings'!P:P) -> #VALUE! | N35: =M35*F35 -> #VALUE! | R35: 360 | S35: =D35-R35 -> -164.8218
A36: 2.3 | B36: Cable Basket HDG 450 x 50 | C36: 1 | D36: 195 | E36: =D36/NOK2EUR -> 16.956522 | F36: =C36*E36 -> 16.956522 | I36: m | K36: not found | L36: 45624 | M36: =SUMIF('Cable trays + Fittings'!F:F,'Cable trays (UnitPrice)'!B36,'Cable trays + Fittings'!P:P) -> #VALUE! | N36: =M36*F36 -> #VALUE! | R36: 350 | S36: =D36-R36 -> -155
A37: 2.4 | B37: Cable Basket HDG 400 x 150 | C37: 1 | D37: 251.8 | E37: =D37/NOK2EUR -> 21.895652 | F37: =C37*E37 -> 21.895652 | I37: m | K37: not found | L37: 45624 | M37: =SUMIF('Cable trays + Fittings'!F:F,'Cable trays (UnitPrice)'!B37,'Cable trays + Fittings'!P:P) -> 0 | N37: =M37*F37 -> 0 | R37: 251.8 | S37: =D37-R37 -> 0
A38: 2.5 | B38: Cable Basket HDG 300 x 100 | C38: 1 | D38: 130 | E38: =D38/NOK2EUR -> 11.304348 | F38: =C38*E38 -> 11.304348 | I38: m | K38: not found | L38: 45624 | M38: =SUMIF('Cable trays + Fittings'!F:F,'Cable trays (UnitPrice)'!B38,'Cable trays + Fittings'!P:P) -> #VALUE! | N38: =M38*F38 -> #VALUE! | R38: 139.15 | S38: =D38-R38 -> -9.15
A39: 2.6 | B39: Cable Basket HDG 300 x 60 | C39: 1 | D39: =K39 -> 120.6499 | E39: =D39/NOK2EUR -> 10.491295 | F39: =C39*E39 -> 10.491295 | I39: m | K39: 120.6499 | L39: 45665 | M39: =SUMIF('Cable trays + Fittings'!F:F,'Cable trays (UnitPrice)'!B39,'Cable trays + Fittings'!P:P) -> #VALUE! | N39: =M39*F39 -> #VALUE! | R39: 135 | S39: =D39-R39 -> -14.350105
A40: 2.7 | B40: Cable Basket HDG 300 x 50 | C40: 1 | D40: =K40 -> 120.6499 | E40: =D40/NOK2EUR -> 10.491295 | F40: =C40*E40 -> 10.491295 | I40: m | K40: 120.6499 | L40: 45665 | M40: =SUMIF('Cable trays + Fittings'!F:F,'Cable trays (UnitPrice)'!B40,'Cable trays + Fittings'!P:P) -> #VALUE! | N40: =M40*F40 -> #VALUE! | R40: 130 | S40: =D40-R40 -> -9.3501048
A41: 2.8 | B41: Cable Basket HDG 200 x 60 | C41: 1 | D41: =K41 -> 100.26205 | E41: =D41/NOK2EUR -> 8.7184395 | F41: =C41*E41 -> 8.7184395 | I41: m | K41: 100.26205 | L41: 45665 | M41: =SUMIF('Cable trays + Fittings'!F:F,'Cable trays (UnitPrice)'!B41,'Cable trays + Fittings'!P:P) -> #VALUE! | N41: =M41*F41 -> #VALUE! | R41: 115 | S41: =D41-R41 -> -14.737945
A42: 2.9 | B42: Cable Basket HDG 200 x 50 | C42: 1 | D42: =K42 -> 100.26205 | E42: =D42/NOK2EUR -> 8.7184395 | F42: =C42*E42 -> 8.7184395 | G42: 1448509 | H42: MEKA | I42: m | K42: 100.26205 | L42: 45665 | M42: =SUMIF('Cable trays + Fittings'!F:F,'Cable trays (UnitPrice)'!B42,'Cable trays + Fittings'!P:P) -> #VALUE! | N42: =M42*F42 -> #VALUE! | R42: =(5.31+4)*11.87 -> 110.5097 | S42: =D42-R42 -> -10.247645
A43: 2.10 | B43: Cable Basket HDG 150 x 60 | C43: 1 | D43: =K43 -> 100.26205 | E43: =D43/NOK2EUR -> 8.7184395 | F43: =C43*E43 -> 8.7184395 | I43: m | K43: 100.26205 | L43: 45665 | M43: =SUMIF('Cable trays + Fittings'!F:F,'Cable trays (UnitPrice)'!B43,'Cable trays + Fittings'!P:P) -> #VALUE! | N43: =M43*F43 -> #VALUE! | R43: 105 | S43: =D43-R43 -> -4.7379455
A44: 2.11 | B44: Cable Basket HDG 150 x 50 | C44: 1 | D44: =K44 -> 100.26205 | E44: =D44/NOK2EUR -> 8.7184395 | F44: =C44*E44 -> 8.7184395 | I44: m | K44: 100.26205 | L44: 45665 | M44: =SUMIF('Cable trays + Fittings'!F:F,'Cable trays (UnitPrice)'!B44,'Cable trays + Fittings'!P:P) -> #VALUE! | N44: =M44*F44 -> #VALUE! | R44: 100 | S44: =D44-R44 -> 0.26205451
A45: 2.12 | B45: Cable Basket HDG 100 x 50 | C45: 1 | D45: =(4.08+4)*11.87 -> 95.9096 | E45: =D45/NOK2EUR -> 8.3399652 | F45: =C45*E45 -> 8.3399652 | G45: 1448508 | H45: MEKA | I45: m | K45: not found | L45: 45624 | M45: =SUMIF('Cable trays + Fittings'!F:F,'Cable trays (UnitPrice)'!B45,'Cable trays + Fittings'!P:P) -> 0 | N45: =M45*F45 -> 0 | R45: =(4.08+4)*11.87 -> 95.9096 | S45: =D45-R45 -> 0
A46: 2.13 | B46: Cable Basket PRE Galv. 600 x 150 | C46: 1 | D46: 260 | E46: =D46/NOK2EUR -> 22.608696 | F46: =C46*E46 -> 22.608696 | G46: 1448424 | H46: MEKA | I46: m | K46: not found | L46: 45624 | M46: =SUMIF('Cable trays + Fittings'!F:F,'Cable trays (UnitPrice)'!B46,'Cable trays + Fittings'!P:P) -> #VALUE! | N46: =M46*F46 -> #VALUE! | R46: =(18.52+4)*11.57 -> 260.5564 | S46: =D46-R46 -> -0.5564
A47: 2.14 | B47: Cable Basket PRE Galv. 600 x 100 | C47: 1 | D47: 250 | E47: =D47/NOK2EUR -> 21.73913 | F47: =C47*E47 -> 21.73913 | I47: m | K47: not found | L47: 45624 | M47: =SUMIF('Cable trays + Fittings'!F:F,'Cable trays (UnitPrice)'!B47,'Cable trays + Fittings'!P:P) -> #VALUE! | N47: =M47*F47 -> #VALUE! | R47: 250 | S47: =D47-R47 -> 0
A48: 2.15 | B48: Cable Basket PRE Galv. 500 x 100 | C48: 1 | D48: =(14+4)*11.57 -> 208.26 | E48: =D48/NOK2EUR -> 18.109565 | F48: =C48*E48 -> 18.109565 | G48: 448419 | H48: MEKA | I48: m | K48: not found | L48: 45624 | M48: =SUMIF('Cable trays + Fittings'!F:F,'Cable trays (UnitPrice)'!B48,'Cable trays + Fittings'!P:P) -> 0 | N48: =M48*F48 -> 0 | R48: =(14+4)*11.57 -> 208.26 | S48: =D48-R48 -> 0
A49: 2.16 | B49: Cable Basket PRE Galv. 300 x 150 | C49: 1 | D49: =(13.91+4)*11.57 -> 207.2187 | E49: =D49/NOK2EUR -> 18.019017 | F49: =C49*E49 -> 18.019017 | I49: m | K49: not found | L49: 45624 | M49: =SUMIF('Cable trays + Fittings'!F:F,'Cable trays (UnitPrice)'!B49,'Cable trays + Fittings'!P:P) -> 0 | N49: =M49*F49 -> 0 | R49: =(13.91+4)*11.57 -> 207.2187 | S49: =D49-R49 -> 0
A50: 2.17 | B50: Cable Basket PRE Galv. 300 x 100 | C50: 1 | D50: =K50 -> 90.67086 | E50: =D50/NOK2EUR -> 7.8844226 | F50: =C50*E50 -> 7.8844226 | G50: 1448417 | H50: MEKA | I50: m | K50: 90.67086 | L50: 45665 | M50: =SUMIF('Cable trays + Fittings'!F:F,'Cable trays (UnitPrice)'!B50,'Cable trays + Fittings'!P:P) -> #VALUE! | N50: =M50*F50 -> #VALUE! | R50: =(10.37+4)*11.57 -> 166.2609 | S50: =D50-R50 -> -75.59004
A51: 2.18 | B51: Cable Basket PRE Galv. 300 x 38 | C51: 1 | D51: 90 | E51: =D51/NOK2EUR -> 7.826087 | F51: =C51*E51 -> 7.826087 | I51: m | K51: not found | L51: 45624 | M51: =SUMIF('Cable trays + Fittings'!F:F,'Cable trays (UnitPrice)'!B51,'Cable trays + Fittings'!P:P) -> #VALUE! | N51: =M51*F51 -> #VALUE! | R51: 150 | S51: =D51-R51 -> -60
A52: 2.19 | B52: Cable Basket PRE Galv. 200 x 100 | C52: 1 | D52: =(5.87+4)*11.87 -> 117.1569 | E52: =D52/NOK2EUR -> 10.187557 | F52: =C52*E52 -> 10.187557 | G52: 1448416 | H52: MEKA | I52: m | K52: not found | L52: 45624 | M52: =SUMIF('Cable trays + Fittings'!F:F,'Cable trays (UnitPrice)'!B52,'Cable trays + Fittings'!P:P) -> 0 | N52: =M52*F52 -> 0 | R52: =(5.87+4)*11.87 -> 117.1569 | S52: =D52-R52 -> 0
A53: 2.20 | B53: Cable Basket PRE Galv. 200 x 50 | C53: 1 | D53: =(4.95+4)*11.87 -> 106.2365 | E53: =D53/NOK2EUR -> 9.2379565 | F53: =C53*E53 -> 9.2379565 | G53: 1448409 | H53: MEKA | I53: m | K53: not found | L53: 45624 | M53: =SUMIF('Cable trays + Fittings'!F:F,'Cable trays (UnitPrice)'!B53,'Cable trays + Fittings'!P:P) -> 0 | N53: =M53*F53 -> 0 | R53: =(4.95+4)*11.87 -> 106.2365 | S53: =D53-R53 -> 0
A54: 2.21 | B54: Cable Basket PRE Galv. 150 x 100 | C54: 1 | D54: =K54 -> 57.966457 | E54: =D54/NOK2EUR -> 5.0405615 | F54: =C54*E54 -> 5.0405615 | I54: m | K54: 57.966457 | L54: 45665 | M54: =SUMIF('Cable trays + Fittings'!F:F,'Cable trays (UnitPrice)'!B54,'Cable trays + Fittings'!P:P) -> #VALUE! | N54: =M54*F54 -> #VALUE! | R54: 105 | S54: =D54-R54 -> -47.033543
A55: 2.22 | B55: Cable Basket PRE Galv. 150 x 80 | C55: 1 | D55: 55 | E55: =D55/NOK2EUR -> 4.7826087 | F55: =C55*E55 -> 4.7826087 | I55: m | K55: not found | L55: 45624 | M55: =SUMIF('Cable trays + Fittings'!F:F,'Cable trays (UnitPrice)'!B55,'Cable trays + Fittings'!P:P) -> #VALUE! | N55: =M55*F55 -> #VALUE! | R55: 105 | S55: =D55-R55 -> -50
A56: 2.23 | B56: Cable Basket PRE Galv. 150 x 54 | C56: 1 | D56: 55 | E56: =D56/NOK2EUR -> 4.7826087 | F56: =C56*E56 -> 4.7826087 | I56: m | K56: not found | L56: 45624 | M56: =SUMIF('Cable trays + Fittings'!F:F,'Cable trays (UnitPrice)'!B56,'Cable trays + Fittings'!P:P) -> #VALUE! | N56: =M56*F56 -> #VALUE! | R56: 105 | S56: =D56-R56 -> -50
A57: 2.24 | B57: Cable Basket PRE Galv. 100 x 150 | C57: 1 | D57: 55 | E57: =D57/NOK2EUR -> 4.7826087 | F57: =C57*E57 -> 4.7826087 | I57: m | K57: not found | L57: 45624 | M57: =SUMIF('Cable trays + Fittings'!F:F,'Cable trays (UnitPrice)'!B57,'Cable trays + Fittings'!P:P) -> #VALUE! | N57: =M57*F57 -> #VALUE! | R57: 100 | S57: =D57-R57 -> -45
A58: 2.25 | B58: Cable Basket PRE Galv. 100 x 50 | C58: 1 | D58: 55 | E58: =D58/NOK2EUR -> 4.7826087 | F58: =C58*E58 -> 4.7826087 | I58: m | K58: not found | L58: 45624 | M58: =SUMIF('Cable trays + Fittings'!F:F,'Cable trays (UnitPrice)'!B58,'Cable trays + Fittings'!P:P) -> #VALUE! | N58: =M58*F58 -> #VALUE! | R58: 100 | S58: =D58-R58 -> -45
A59: 2.26 | B59: Cable Basket PRE Galv. 100 x 25 | C59: 1 | D59: 55 | E59: =D59/NOK2EUR -> 4.7826087 | F59: =C59*E59 -> 4.7826087 | I59: m | K59: not found | L59: 45624 | M59: =SUMIF('Cable trays + Fittings'!F:F,'Cable trays (UnitPrice)'!B59,'Cable trays + Fittings'!P:P) -> #VALUE! | N59: =M59*F59 -> #VALUE! | R59: 100 | S59: =D59-R59 -> -45
A60: 2.27 | B60: Cable Basket PRE Galv. 70 x 50 | C60: 1 | D60: =(3.56+4)*11.87 -> 89.7372 | E60: =D60/NOK2EUR -> 7.8032348 | F60: =C60*E60 -> 7.8032348 | G60: 1448407 | H60: MEKA | I60: m | K60: not found | L60: 45624 | M60: =SUMIF('Cable trays + Fittings'!F:F,'Cable trays (UnitPrice)'!B60,'Cable trays + Fittings'!P:P) -> 0 | N60: =M60*F60 -> 0 | R60: =(3.56+4)*11.87 -> 89.7372 | S60: =D60-R60 -> 0
A61: 2.28 | B61: Cable Ladder HDG 1200 x 125 | C61: 1 | D61: =K61 -> 638.25996 | E61: =D61/NOK2EUR -> 55.500866 | F61: =C61*E61 -> 55.500866 | I61: m | K61: 638.25996 | L61: 45665 | M61: =SUMIF('Cable trays + Fittings'!F:F,'Cable trays (UnitPrice)'!B61,'Cable trays + Fittings'!P:P) -> #VALUE! | N61: =M61*F61 -> #VALUE! | R61: 1200 | S61: =D61-R61 -> -561.74004
A62: 2.29 | B62: Cable Ladder HDG 1200 x 100 | C62: 1 | D62: =K62 -> 638.25996 | E62: =D62/NOK2EUR -> 55.500866 | F62: =C62*E62 -> 55.500866 | I62: m | K62: 638.25996 | L62: 45665 | M62: =SUMIF('Cable trays + Fittings'!F:F,'Cable trays (UnitPrice)'!B62,'Cable trays + Fittings'!P:P) -> #VALUE! | N62: =M62*F62 -> #VALUE! | R62: 950 | S62: =D62-R62 -> -311.74004
A63: 2.29 | B63: Cable Ladder HDG 950 x 125 | C63: 1 | D63: =K63 -> 638.25996 | E63: =D63/NOK2EUR -> 55.500866 | F63: =C63*E63 -> 55.500866 | I63: m | K63: 638.25996 | L63: 45665 | M63: =SUMIF('Cable trays + Fittings'!F:F,'Cable trays (UnitPrice)'!B63,'Cable trays + Fittings'!P:P) -> #VALUE! | N63: =M63*F63 -> #VALUE! | R63: 950 | S63: =D63-R63 -> -311.74004
A64: 2.30 | B64: Cable Ladder HDG 900 x 125 | C64: 1 | D64: 630 | E64: =D64/NOK2EUR -> 54.782609 | F64: =C64*E64 -> 54.782609 | I64: m | K64: not found | L64: 45624 | M64: =SUMIF('Cable trays + Fittings'!F:F,'Cable trays (UnitPrice)'!B64,'Cable trays + Fittings'!P:P) -> #VALUE! | N64: =M64*F64 -> #VALUE! | R64: 900 | S64: =D64-R64 -> -270
A65: 2.31 | B65: Cable Ladder HDG 900 x 100 | C65: 1 | D65: 850 | E65: =D65/NOK2EUR -> 73.913043 | F65: =C65*E65 -> 73.913043 | I65: m | K65: not found | L65: 45624 | M65: =SUMIF('Cable trays + Fittings'!F:F,'Cable trays (UnitPrice)'!B65,'Cable trays + Fittings'!P:P) -> 0 | N65: =M65*F65 -> 0 | R65: 850 | S65: =D65-R65 -> 0
A66: 2.32 | B66: Cable Ladder HDG 800 x 125 | C66: 1 | D66: =K66 -> 601.12683 | E66: =D66/NOK2EUR -> 52.271899 | F66: =C66*E66 -> 52.271899 | I66: m | K66: 601.12683 | L66: 45665 | M66: =SUMIF('Cable trays + Fittings'!F:F,'Cable trays (UnitPrice)'!B66,'Cable trays + Fittings'!P:P) -> #VALUE! | N66: =M66*F66 -> #VALUE! | R66: 775 | S66: =D66-R66 -> -173.87317
A67: 2.32 | B67: Cable Ladder HDG 750 x 125 | C67: 1 | D67: =K67 -> 601.12683 | E67: =D67/NOK2EUR -> 52.271899 | F67: =C67*E67 -> 52.271899 | I67: m | K67: 601.12683 | L67: 45665 | M67: =SUMIF('Cable trays + Fittings'!F:F,'Cable trays (UnitPrice)'!B67,'Cable trays + Fittings'!P:P) -> #VALUE! | N67: =M67*F67 -> #VALUE! | R67: 775 | S67: =D67-R67 -> -173.87317
A68: 2.33 | B68: Cable Ladder HDG 650 x 125 | C68: 1 | D68: =K68 -> 582.57338 | E68: =D68/NOK2EUR -> 50.658554 | F68: =C68*E68 -> 50.658554 | I68: m | K68: 582.57338 | L68: 45665 | M68: =SUMIF('Cable trays + Fittings'!F:F,'Cable trays (UnitPrice)'!B68,'Cable trays + Fittings'!P:P) -> #VALUE! | N68: =M68*F68 -> #VALUE! | R68: 750 | S68: =D68-R68 -> -167.42662
A69: 2.34 | B69: Cable Ladder HDG 650 x 100 | C69: 1 | D69: 580 | E69: =D69/NOK2EUR -> 50.434783 | F69: =C69*E69 -> 50.434783 | I69: m | K69: not found | L69: 45624 | M69: =SUMIF('Cable trays + Fittings'!F:F,'Cable trays (UnitPrice)'!B69,'Cable trays + Fittings'!P:P) -> #VALUE! | N69: =M69*F69 -> #VALUE! | R69: 740 | S69: =D69-R69 -> -160
A70: 2.35 | B70: Cable Ladder HDG 610 x 38 | C70: 1 | D70: =K70 -> 564.01992 | E70: =D70/NOK2EUR -> 49.04521 | F70: =C70*E70 -> 49.04521 | I70: m | K70: 564.01992 | L70: 45665 | M70: =SUMIF('Cable trays + Fittings'!F:F,'Cable trays (UnitPrice)'!B70,'Cable trays + Fittings'!P:P) -> #VALUE! | N70: =M70*F70 -> #VALUE! | R70: 700 | S70: =D70-R70 -> -135.98008
A71: 2.36 | B71: Cable Ladder HDG 600 x 150 | C71: 1 | D71: =K71 -> 564.01992 | E71: =D71/NOK2EUR -> 49.04521 | F71: =C71*E71 -> 49.04521 | I71: m | K71: 564.01992 | L71: 45665 | M71: =SUMIF('Cable trays + Fittings'!F:F,'Cable trays (UnitPrice)'!B71,'Cable trays + Fittings'!P:P) -> #VALUE! | N71: =M71*F71 -> #VALUE! | R71: 680 | S71: =D71-R71 -> -115.98008
A72: 2.37 | B72: Cable Ladder HDG 600 x 125 | C72: 1 | D72: =K72 -> 564.01992 | E72: =D72/NOK2EUR -> 49.04521 | F72: =C72*E72 -> 49.04521 | I72: m | K72: 564.01992 | L72: 45665 | M72: =SUMIF('Cable trays + Fittings'!F:F,'Cable trays (UnitPrice)'!B72,'Cable trays + Fittings'!P:P) -> #VALUE! | N72: =M72*F72 -> #VALUE! | R72: 671.7 | S72: =D72-R72 -> -107.68008
A73: 2.38 | B73: Cable Ladder HDG 600 x 100 | C73: 1 | D73: 564 | E73: =D73/NOK2EUR -> 49.043478 | F73: =C73*E73 -> 49.043478 | G73: W4-SL3-600-GY-1.5W-1.5T | H73: UNITRUNK | I73: m | K73: not found | L73: 45624 | M73: =SUMIF('Cable trays + Fittings'!F:F,'Cable trays (UnitPrice)'!B73,'Cable trays + Fittings'!P:P) -> #VALUE! | N73: =M73*F73 -> #VALUE! | R73: 650 | S73: =D73-R73 -> -86
A74: 2.39 | B74: Cable Ladder HDG 500 x 125 | C74: 1 | D74: 550 | E74: =D74/NOK2EUR -> 47.826087 | F74: =C74*E74 -> 47.826087 | I74: m | K74: not found | L74: 45624 | M74: =SUMIF('Cable trays + Fittings'!F:F,'Cable trays (UnitPrice)'!B74,'Cable trays + Fittings'!P:P) -> #VALUE! | N74: =M74*F74 -> #VALUE! | R74: 550 | S74: =D74-R74 -> 0
A75: 2.40 | B75: Cable Ladder HDG 500 x 100 | C75: 1 | D75: 500 | E75: =D75/NOK2EUR -> 43.478261 | F75: =C75*E75 -> 43.478261 | I75: m | K75: not found | L75: 45624 | M75: =SUMIF('Cable trays + Fittings'!F:F,'Cable trays (UnitPrice)'!B75,'Cable trays + Fittings'!P:P) -> #VALUE! | N75: =M75*F75 -> #VALUE! | R75: 500 | S75: =D75-R75 -> 0
A76: 2.41 | B76: Cable Ladder HDG 450 x 125 | C76: 1 | D76: =K76 -> 547.92977 | E76: =D76/NOK2EUR -> 47.646067 | F76: =C76*E76 -> 47.646067 | I76: m | K76: 547.92977 | L76: 45665 | M76: =SUMIF('Cable trays + Fittings'!F:F,'Cable trays (UnitPrice)'!B76,'Cable trays + Fittings'!P:P) -> #VALUE! | N76: =M76*F76 -> #VALUE! | R76: 498 | S76: =D76-R76 -> 49.929769
A77: 2.42 | B77: Cable Ladder HDG 450 x 100 | C77: 1 | D77: =K77 -> 233.1761 | E77: =D77/NOK2EUR -> 20.276183 | F77: =C77*E77 -> 20.276183 | I77: m | K77: 233.1761 | L77: 45665 | M77: =SUMIF('Cable trays + Fittings'!F:F,'Cable trays (UnitPrice)'!B77,'Cable trays + Fittings'!P:P) -> #VALUE! | N77: =M77*F77 -> #VALUE! | R77: 495 | S77: =D77-R77 -> -261.8239
A78: 2.43 | B78: Cable Ladder HDG 450 x 38 | C78: 1 | D78: =K78 -> 172.06499 | E78: =D78/NOK2EUR -> 14.962173 | F78: =C78*E78 -> 14.962173 | I78: m | K78: 172.06499 | L78: 45665 | M78: =SUMIF('Cable trays + Fittings'!F:F,'Cable trays (UnitPrice)'!B78,'Cable trays + Fittings'!P:P) -> #VALUE! | N78: =M78*F78 -> #VALUE! | R78: 490 | S78: =D78-R78 -> -317.93501
A79: 2.44 | B79: Cable Ladder HDG 400 x 125 | C79: 1 | D79: 550 | E79: =D79/NOK2EUR -> 47.826087 | F79: =C79*E79 -> 47.826087 | I79: m | K79: not found | L79: 45624 | M79: =SUMIF('Cable trays + Fittings'!F:F,'Cable trays (UnitPrice)'!B79,'Cable trays + Fittings'!P:P) -> #VALUE! | N79: =M79*F79 -> #VALUE! | R79: 489.4 | S79: =D79-R79 -> 60.6
A80: 2.45 | B80: Cable Ladder HDG 350 x 125 | C80: 1 | D80: =K80 -> 530.13627 | E80: =D80/NOK2EUR -> 46.098806 | F80: =C80*E80 -> 46.098806 | I80: m | K80: 530.13627 | L80: 45665 | M80: =SUMIF('Cable trays + Fittings'!F:F,'Cable trays (UnitPrice)'!B80,'Cable trays + Fittings'!P:P) -> #VALUE! | N80: =M80*F80 -> #VALUE! | R80: 480 | S80: =D80-R80 -> 50.136268
A81: 2.46 | B81: Cable Ladder HDG 300 x 150 | C81: 1 | D81: 520 | E81: =D81/NOK2EUR -> 45.217391 | F81: =C81*E81 -> 45.217391 | I81: m | K81: not found | L81: 45624 | M81: =SUMIF('Cable trays + Fittings'!F:F,'Cable trays (UnitPrice)'!B81,'Cable trays + Fittings'!P:P) -> #VALUE! | N81: =M81*F81 -> #VALUE! | R81: 470 | S81: =D81-R81 -> 50
A82: 2.47 | B82: Cable Ladder HDG 300 x 125 | C82: 1 | D82: =K82 -> 512.36897 | E82: =D82/NOK2EUR -> 44.553824 | F82: =C82*E82 -> 44.553824 | I82: m | K82: 512.36897 | L82: 45665 | M82: =SUMIF('Cable trays + Fittings'!F:F,'Cable trays (UnitPrice)'!B82,'Cable trays + Fittings'!P:P) -> #VALUE! | N82: =M82*F82 -> #VALUE! | R82: 465 | S82: =D82-R82 -> 47.368973
A83: 2.48 | B83: Cable Ladder HDG 300 x 100 | C83: 1 | D83: =K83 -> 214.51782 | E83: =D83/NOK2EUR -> 18.653723 | F83: =C83*E83 -> 18.653723 | I83: m | K83: 214.51782 | L83: 45665 | M83: =SUMIF('Cable trays + Fittings'!F:F,'Cable trays (UnitPrice)'!B83,'Cable trays + Fittings'!P:P) -> #VALUE! | N83: =M83*F83 -> #VALUE! | R83: 460 | S83: =D83-R83 -> -245.48218
A84: 2.49 | B84: Cable Ladder HDG 225 x 125 | C84: 1 | D84: 500 | E84: =D84/NOK2EUR -> 43.478261 | F84: =C84*E84 -> 43.478261 | I84: m | K84: not found | L84: 45624 | M84: =SUMIF('Cable trays + Fittings'!F:F,'Cable trays (UnitPrice)'!B84,'Cable trays + Fittings'!P:P) -> #VALUE! | N84: =M84*F84 -> #VALUE! | R84: 450 | S84: =D84-R84 -> 50
A85: 2.50 | B85: Cable Ladder HDG 200 x 125 | C85: 1 | D85: =K85 -> 487.36897 | E85: =D85/NOK2EUR -> 42.379911 | F85: =C85*E85 -> 42.379911 | I85: m | K85: 487.36897 | L85: 45665 | M85: =SUMIF('Cable trays + Fittings'!F:F,'Cable trays (UnitPrice)'!B85,'Cable trays + Fittings'!P:P) -> #VALUE! | N85: =M85*F85 -> #VALUE! | R85: 430 | S85: =D85-R85 -> 57.368973
A86: 2.51 | B86: Cable Ladder HDG 200 x 50 | C86: 1 | D86: =K86 -> 146.54088 | E86: =D86/NOK2EUR -> 12.742685 | F86: =C86*E86 -> 12.742685 | I86: m | K86: 146.54088 | L86: 45665 | M86: =SUMIF('Cable trays + Fittings'!F:F,'Cable trays (UnitPrice)'!B86,'Cable trays + Fittings'!P:P) -> #VALUE! | N86: =M86*F86 -> #VALUE! | R86: 400 | S86: =D86-R86 -> -253.45912
A87: 2.52 | B87: Cable Ladder HDG 150 x 125 | C87: 1 | D87: =K87 -> 487.36897 | E87: =D87/NOK2EUR -> 42.379911 | F87: =C87*E87 -> 42.379911 | I87: m | K87: 487.36897 | L87: 45665 | M87: =SUMIF('Cable trays + Fittings'!F:F,'Cable trays (UnitPrice)'!B87,'Cable trays + Fittings'!P:P) -> #VALUE! | N87: =M87*F87 -> #VALUE! | R87: 350 | S87: =D87-R87 -> 137.36897
A88: 2.53 | B88: Cable Ladder HDG 150 x 100 | C88: 1 | D88: =K88 -> 209.17191 | E88: =D88/NOK2EUR -> 18.188862 | F88: =C88*E88 -> 18.188862 | I88: m | K88: 209.17191 | L88: 45665 | M88: =SUMIF('Cable trays + Fittings'!F:F,'Cable trays (UnitPrice)'!B88,'Cable trays + Fittings'!P:P) -> #VALUE! | N88: =M88*F88 -> #VALUE! | R88: 340 | S88: =D88-R88 -> -130.82809
A89: 2.54 | B89: Cable Ladder HDG 150 x 38 | C89: 1 | D89: 200 | E89: =D89/NOK2EUR -> 17.391304 | F89: =C89*E89 -> 17.391304 | I89: m | K89: not found | L89: 45624 | M89: =SUMIF('Cable trays + Fittings'!F:F,'Cable trays (UnitPrice)'!B89,'Cable trays + Fittings'!P:P) -> #VALUE! | N89: =M89*F89 -> #VALUE! | R89: 300 | S89: =D89-R89 -> -100
A90: 2.55 | B90: Cable Ladder PRE Galv. 900 x 100 | C90: 1 | D90: 750 | E90: =D90/NOK2EUR -> 65.217391 | F90: =C90*E90 -> 65.217391 | G90: SW4-SL3-900-QQ | I90: m | K90: not found | L90: 45624 | M90: =SUMIF('Cable trays + Fittings'!F:F,'Cable trays (UnitPrice)'!B90,'Cable trays + Fittings'!P:P) -> #VALUE! | N90: =M90*F90 -> #VALUE! | R90: 750 | S90: =D90-R90 -> 0
A91: 2.56 | B91: Cable Ladder PRE Galv. 750 x 125 | C91: 1 | D91: =K91 -> 601.12683 | E91: =D91/NOK2EUR -> 52.271899 | F91: =C91*E91 -> 52.271899 | I91: m | K91: 601.12683 | L91: 45665 | M91: =SUMIF('Cable trays + Fittings'!F:F,'Cable trays (UnitPrice)'!B91,'Cable trays + Fittings'!P:P) -> #VALUE! | N91: =M91*F91 -> #VALUE! | R91: 700 | S91: =D91-R91 -> -98.873166
A92: 2.57 | B92: Cable Ladder PRE Galv. 600 x 125 | C92: 1 | D92: 600 | E92: =D92/NOK2EUR -> 52.173913 | F92: =C92*E92 -> 52.173913 | G92: SW4-SL3-600-QQ | I92: m | K92: not found | L92: 45624 | M92: =SUMIF('Cable trays + Fittings'!F:F,'Cable trays (UnitPrice)'!B92,'Cable trays + Fittings'!P:P) -> #VALUE! | N92: =M92*F92 -> #VALUE! | R92: 618.2 | S92: =D92-R92 -> -18.2
A93: 2.57 | B93: Cable Ladder PRE Galv. 600 x 100 | C93: 1 | D93: 618.2 | E93: =D93/NOK2EUR -> 53.756522 | F93: =C93*E93 -> 53.756522 | G93: SW4-SL3-600-QQ | I93: m | K93: not found | L93: 45624 | M93: =SUMIF('Cable trays + Fittings'!F:F,'Cable trays (UnitPrice)'!B93,'Cable trays + Fittings'!P:P) -> 0 | N93: =M93*F93 -> 0 | R93: 618.2 | S93: =D93-R93 -> 0
A94: 2.58 | B94: Cable Ladder PRE Galv. 600 x 38 | C94: 1 | D94: =K94 -> 113.41719 | E94: =D94/NOK2EUR -> 9.8623644 | F94: =C94*E94 -> 9.8623644 | I94: m | K94: 113.41719 | L94: 45665 | M94: =SUMIF('Cable trays + Fittings'!F:F,'Cable trays (UnitPrice)'!B94,'Cable trays + Fittings'!P:P) -> #VALUE! | N94: =M94*F94 -> #VALUE! | R94: 618.2 | S94: =D94-R94 -> -504.78281
A95: 2.58 | B95: Cable Ladder PRE Galv. 610 x 38 | C95: 1 | D95: =K95 -> 113.41719 | E95: =D95/NOK2EUR -> 9.8623644 | F95: =C95*E95 -> 9.8623644 | I95: m | K95: 113.41719 | L95: 45665 | M95: =SUMIF('Cable trays + Fittings'!F:F,'Cable trays (UnitPrice)'!B95,'Cable trays + Fittings'!P:P) -> #VALUE! | N95: =M95*F95 -> #VALUE! | R95: 618.2 | S95: =D95-R95 -> -504.78281
A96: 2.59 | B96: Cable Ladder PRE Galv. 450 x 100 | C96: 1 | D96: 475.6 | E96: =D96/NOK2EUR -> 41.356522 | F96: =C96*E96 -> 41.356522 | G96: SW4-SL3-450-QQ | I96: m | K96: not found | L96: 45624 | M96: =SUMIF('Cable trays + Fittings'!F:F,'Cable trays (UnitPrice)'!B96,'Cable trays + Fittings'!P:P) -> 0 | N96: =M96*F96 -> 0 | R96: 475.6 | S96: =D96-R96 -> 0
A97: 2.60 | B97: Cable Ladder PRE Galv. 300 x 100 | C97: 1 | D97: 475.6 | E97: =D97/NOK2EUR -> 41.356522 | F97: =C97*E97 -> 41.356522 | G97: SW4-SL3-300-QQ | I97: m | K97: not found | L97: 45624 | M97: =SUMIF('Cable trays + Fittings'!F:F,'Cable trays (UnitPrice)'!B97,'Cable trays + Fittings'!P:P) -> 0 | N97: =M97*F97 -> 0 | R97: 475.6 | S97: =D97-R97 -> 0
A98: 2.60 | B98: Cable Ladder PRE Galv. 300 x 125 | C98: 1 | D98: =K98 -> 512.36897 | E98: =D98/NOK2EUR -> 44.553824 | F98: =C98*E98 -> 44.553824 | G98: SW4-SL3-300-QQ | I98: m | K98: 512.36897 | L98: 45665 | M98: =SUMIF('Cable trays + Fittings'!F:F,'Cable trays (UnitPrice)'!B98,'Cable trays + Fittings'!P:P) -> #VALUE! | N98: =M98*F98 -> #VALUE! | R98: 475.6 | S98: =D98-R98 -> 36.768973
A99: 2.61 | B99: Cable Ladder PRE Galv. 200 x 100 | C99: 1 | D99: 450 | E99: =D99/NOK2EUR -> 39.130435 | F99: =C99*E99 -> 39.130435 | I99: m | K99: not found | L99: 45624 | M99: =SUMIF('Cable trays + Fittings'!F:F,'Cable trays (UnitPrice)'!B99,'Cable trays + Fittings'!P:P) -> 0 | N99: =M99*F99 -> 0 | R99: 450 | S99: =D99-R99 -> 0
A100: 2.62 | B100: Cable Ladder PRE Galv. 150 x 150 | C100: 1 | D100: 500 | E100: =D100/NOK2EUR -> 43.478261 | F100: =C100*E100 -> 43.478261 | I100: m | K100: not found | L100: 45624 | M100: =SUMIF('Cable trays + Fittings'!F:F,'Cable trays (UnitPrice)'!B100,'Cable trays + Fittings'!P:P) -> #VALUE! | N100: =M100*F100 -> #VALUE! | R100: 425 | S100: =D100-R100 -> 75
A101: 2.62 | B101: Cable Ladder PRE Galv. 150 x 125 | C101: 1 | D101: =K101 -> 487.36897 | E101: =D101/NOK2EUR -> 42.379911 | F101: =C101*E101 -> 42.379911 | I101: m | K101: 487.36897 | L101: 45665 | M101: =SUMIF('Cable trays + Fittings'!F:F,'Cable trays (UnitPrice)'!B101,'Cable trays + Fittings'!P:P) -> #VALUE! | N101: =M101*F101 -> #VALUE! | R101: 425 | S101: =D101-R101 -> 62.368973
...

Sheet Lighting
D1: Currency
D2: ='[55]Project Input'!E32 -> 11.5
A4: INTERNAL CODE | B4: TYPE | C4: PRICE NOK | D4: PRICE EUR | E4: UPDATE PRICE DATE | F4: MANUFACTURER | G4: MODEL | H4: ARTICLE NO. | I4: DESCRIPTION | J4: FLUX (Lm) | K4: LAMP | L4: LAMP COLOUR (K) | M4: ACTIVE POWER (W) | N4: IP RATING | O4: DIMENSIONS (mm) | P4: WEIGHT (Kg) | Q4: LINK (AS NA EXAMPLE) | R4: PICTURE | S4: TYPICAL MOUNTING HEIGHT (mt) | T4: MANPOWER (HR) | U4: LIGHT FIXTURE TAG | V4: QTY THIS OFFER | AD4: Skien Qty.
D5: 190 | E5: 27/11/2024 | F5: Lightinova | I5: Linear LED pendant lamp 1200 mm Black | J5: 1600 Lm | K5: LED | L5: 3000K | M5: 20w | N5: IP20 | O5: 50 x 70 x 1200 mm | P5: 2,38 Kg | Q5: https://www.lightinova.com/en/led-pendant-lamp-line-1200-mm-black.html | T5: 1 | U5: 99.A | V5: 12
B6: NORMAL LIGHT | C6: 2507 | D6: =C6/$D$2 -> 218 | E6: 27/11/2024 | F6: GARRABRIDGE | G6: CITY ECOLED | H6: L1550 2 | I6: DIFFUSER MANUFACTURED IN INJECTION MADE OF ACRYLIC (PMMA IK03) | J6: 6200 Lm (840) | K6: LED | M6: 63w | N6: IP66 | S6: 3,2 mt | T6: 1 | U6: A | W6: g-LGF-Lighting Fixture A - Type A (CITY ECOLED L1550 2 6200/840 MMA) | AD6: 99
C7: 5091 | D7: =C7/$D$2 -> 442.69565 | E7: 27/11/2024 | F7: THORLUX | G7: A-LINE | H7: AP020LAN | I7: NARROW DISTRIBUTION, ALUMINUM BODY WITH ACRYLIC REFRACTOR. Extremely efficient, multi-purpose, corrosion-resistant luminaires | J7: 4345 Lm | K7: LED | L7: 4000K | M7: 20w | N7: IP66 | O7: 1500 mm | P7: 6,4 Kg | Q7: https://www.thorlux.com/products/a-line-pro | T7: 1 | U7: A1 | W7: thorlux A-Line AP020LAN 4345 lm | AD7: 20
C8: 5216 | D8: =C8/$D$2 -> 453.56522 | E8: 27/11/2024 | F8: THORLUX | G8: A-LINE | H8: AP020LAB | I8: IP66 RATED, 1500MM 6.4KG, BROAD DISTRIBUTION, ALUMINUM BODY WITH ACRYLIC REFRACTOR | J8: 4440 Lm | K8: LED | M8: 20w | T8: 1 | U8: A2 | W8: thorlux A-Line AP020LAB 4440 lm | AD8: 668
D9: =C9/$D$2 -> 0 | E9: 27/11/2024 | F9: THORLUX | G9: A-LINE | H9: AP016MAB | I9: BROAD DISTRIBUTION, ALUMINUM BODY WITH ACRYLIC REFRACTOR | J9: 3030 Lm | K9: LED | M9: 16w | N9: IP66 | O9: 1200 mm | P9: 4,8 Kg | T9: 1 | U9: A3
D10: =C10/$D$2 -> 0 | E10: 27/11/2024 | F10: SCHUCH | G10: 144 12L60 AUS | H10: 14402004 | I10: SERIES 144 AUS, FOR APPLICATION IN UNPROTECTED OUTDOOR AREAS. EXTREMELY ROBUST DUSTPROOF/WATERPROOF. FITTING WITH CENTRAL LOCKING SYSTEM | J10: 6590 Lm | K10: LED | M10: 44w | S10: 3,2 mt | T10: 1 | U10: B
D11: =C11/$D$2 -> 0 | E11: 27/11/2024 | F11: THORLUX | G11: REALTA | H11: RL19111 | I11: WALL MOUNTED LUMINAIRE. DIE CAST ALUMINUM BODY. GLASS OR PC REFRACTOR. LESS THAN 2% UPWARD LIGHT | J11: 4850 Lm | K11: LED | L11: 4000K | M11: 34w | N11: IP66 | T11: 1 | U11: B1
D12: =C12/$D$2 -> 0 | E12: 27/11/2024 | F12: GARRABRIDGE | G12: ALASKA | H12: DLR25WUGR BF | I12: LED DOWNLIGHT LUMINAIRE IP65 | J12: 2375 Lm | K12: LED | M12: 25w | S12: 3 mt | T12: 1 | U12: C
D13: 40 | E13: 27/11/2024 | F13: GARRABRIDGE | G13: RAPSODY M600x600 | H13: RAPSODY | I13: LED RECESSED LUMINAIRE COMPATIBLE IP56 | J13: 3400 Lm | K13: LED | L13: 3400K (840) | M13: 34w | O13: 600x600 mm | Q13: https://www.todayoutlet.store/?path=page/ggitem&ggpid=3479834 | S13: 3 mt | T13: 1 | U13: D | V13: 241
C14: 2300 | D14: =C14/$D$2 -> 200 | E14: 27/11/2024 | F14: EATON | G14: IP65+ | H14: IP65PLPCGS+ L CG-S PC | I14: SAFETY LUMINAIRE WITH HIGH INGRESS PROTECTION CLASS (IP65) AND LED TECHNOLOGY SUITABLE FOR BOTH INDOOR AND OUTDOOR USE | J14: 770 Lm | K14: LED | M14: 9,3w | S14: 3,2 mt | T14: 1 | U14: E1 | W14: g-LGF-Emergency Lighting Fixture E1 - E1 (IP65PLPCGS+ L CG-S PC) | AD14: 171
D15: =C15/$D$2 -> 0 | E15: 27/11/2024 | F15: EATON | G15: GUIDELED SL | H15: 13021.1 CG-S CEAG NOTLICHTSYS TEME GMBH - 40071354481 | I15: LED EMERGENCY LUMINAIRE FOR USE WITH CENTRAL BATTERY SYSTEM (SYMMETRIC OPTICS FOR ANTI PANIC OR OPEN SPACE) | J15: 250 Lm | K15: LED | M15: 2,0w | S15: 3 mt | T15: 1 | U15: E2
B16: EMERGENCY LIGHT | C16: 1800 | D16: =C16/$D$2 -> 156.52174 | E16: 27/11/2024 | F16: EATON | G16: OUTDOOR WALL CG-S LT | H16: OUTDOOR WALL CG-S | I16: LED WALL MOUNTED EMERGENCY LUMINAIRE FOR USE WITH CENTRAL BATTERY SYSTEM (IP65) | J16: 225 Lm | K16: LED | M16: 7,7w | S16: 3 mt | T16: 1 | U16: E3 | W16: g-LGF-Emergency Lighting Fixture E3 - Outdoor E3 | AD16: 44
C17: 1875 | D17: =C17/$D$2 -> 163.04348 | E17: 27/11/2024 | F17: EATON | G17: ATLANTIC LED CG-S | H17: 40071354870 | I17: LED EMERGENCY EXIT SIGN FOR USE WITH CENTRAL BATTERY SYSTEM, VIEWING DISTANCE 30M | J17: N/A | K17: LED | M17: 7,0w | S17: 3 mt | T17: 1 | U17: E4B | W17: Eaton LED S CG-S Atlantic 40071354870 | AD17: 79
C18: 1875 | D18: =C18/$D$2 -> 163.04348 | E18: 27/11/2024 | F18: EATON | G18: ATLANTIC LED CG-S | H18: 40071354871 | I18: LED EMERGENCY EXIT SIGN FOR USE WITH CENTRAL BATTERY SYSTEM, VIEWING DISTANCE 30M | J18: N/A | K18: LED | M18: 7,0w | S18: 3 mt | T18: 1 | U18: E4C | W18: Eaton LED S CG-S Atlantic 40071354871 | AD18: 12
D19: =C19/$D$2 -> 0 | E19: 27/11/2024 | F19: EATON | G19: ATLANTIC LED CG-S | H19: 40071354870 | I19: LED EMERGENCY EXIT SIGN AT EXTERNAL YARDS, SELF CONTAINED, MAINTAINED INTEGRAL 3-HOUR BACK WITH VIEWING DISTANCE OF 30M (SINGLE SIDED) | J19: N/A | K19: LED | M19: 7,0w | S19: 3 mt | T19: 1 | U19: E4B
D20: =C20/$D$2 -> 0 | E20: 27/11/2024 | F20: EATON | G20: ATLANTIC LED CG-S | H20: 40071354871 | I20: LED EMERGENCY EXIT SIGN AT EXTERNAL YARDS, SELF CONTAINED, MAINTAINED INTEGRAL 3-HOUR BACK WITH VIEWING DISTANCE OF 30M (DOUBLE SIDED) | J20: N/A | K20: LED | M20: 7,0w | S20: 3 mt | T20: 1 | U20: E4C
D21: =C21/$D$2 -> 0 | E21: 27/11/2024 | F21: EATON | G21: GUIDELED SL | H21: 11021/11022/11 023/11024 | I21: LED EMERGENCY DOUBLE-SIDED EXIT SIGN FOR USE WITH CENTRAL BATTERY SYSTEM, VIEWING DISTANCE 30M | J21: N/A | K21: LED | M21: 7,0w | S21: 3 mt | T21: 1 | U21: E5
D22: =C22/$D$2 -> 0 | E22: 27/11/2024 | F22: EATON | G22: GUIDELED SL | H22: LED 46011 CG- S WITH PICTOGRAM | I22: LED EMERGENCY SINGLE-SIDED EXIT SIGN FOR USE WITH CENTRAL BATTERY, VIEWING DISTANCE 60M | J22: N/A | K22: LED | M22: 7,0w | S22: 3 mt | T22: 1 | U22: E6
D23: =C23/$D$2 -> 0 | E23: 27/11/2024 | F23: EATON | G23: IP65PLA3HCGL | H23: LED CEILING MOUNTED LUMINAIRE WITH WIDE BEAM AND SELF CONTAINED BATTERY | I23: SAFETY LUMINAIRE WITH HIGH INGRESS PROTECTION CLASS (IP65) AND LED TECHNOLOGY SUITABLE FOR BOTH INDOOR AND OUTDOOR USE | J23: 510 Lm | K23: LED | M23: 6,5w | S23: 6,5 mt | T23: 1 | U23: E7
D24: =C24/$D$2 -> 0 | E24: 27/11/2024 | F24: EATON | G24: IP65+ | H24: IP65PLP3HCGL | I24: SAFETY LUMINAIRE WITH HIGH DEGREE PROTECTION CLASS (IP65) AND LED TECHNOLOGY SUITABLE FOR BOTH INDOOR/OUTDOOR USE, INTEGRAL WITH 3- HOUR BATTERY | J24: 560 Lm | K24: LED | M24: 6,5w | T24: 1 | U24: E8
D25: =C25/$D$2 -> 0 | E25: 27/11/2024 | F25: EATON | G25: CG LINE+ H | H25: 40071354879 | I25: SAFETY LUMINAIRE WITH HIGH DEGREE PROTECTION CLASS (IP65) AND LED TECHNOLOGY SUITABLE FOR OUTDOOR USE, INTEGRAL WITH 3-HOUR BATTERY | J25: 225 Lm | K25: LED | M25: 3,2w | T25: 1 | U25: E9
B26: EMERGENCY LIGHT | C26: 2113 | D26: =C26/$D$2 -> 183.73913 | E26: 27/11/2024 | F26: EATON | G26: ATLANTIC LED CGLINE+ H | H26: 40071354877 | I26: SAFETY LUMINAIRE ATLANTIC LED R CGLINE+ H, WITH ASYMMETRIC OPTICS, WITH BATTERY HEATER FOR LOW AMBIENT TEMPERATURE DOWN TO -20°C, 1-HOUR BATTERY | J26: 225 Lm | K26: LED | M26: 9,3w | S26: 3 mt | T26: 1 | U26: E10 | W26: g-LGF-Emergency Lighting Fixture E10 - ARROW DOWN FROM HERE - RIGHT SIDE E4 - ANNO_UP | AD26: 366
C27: 2113 | D27: =C27/$D$2 -> 183.73913 | E27: 27/11/2024 | F27: EATON | G27: ATLANTIC LED CGLINE+ H | H27: 40071354878 | I27: SAFETY LUMINAIRE ATLANTIC LED O CGLINE+ H, WITH SYMMETRIC OPTICS, WITH BATTERY HEATER FOR LOW AMBIENT TEMPERATURE DOWN TO -20°C, 1-HOUR BATTERY | J27: 220 Lm | K27: LED | M27: 9,3w | S27: 3 mt | T27: 1 | U27: E11 | W27: Eaton LED CGLine+ H Atlantic 40071354878 | AD27: 197
C28: 5000 | D28: =C28/$D$2 -> 434.78261 | E28: 27/11/2024 | F28: GARRABRIDGE | G28: CRUISER 2 LB LED | H28: GBHB 238.4 | I28: IMPACT RESISTANT LED LUMINAIRE WITH PRISMATIC DIFFUSER. 090432.5L06. 013 CRUISER 2 HE. SZARY | J28: 22600 Lm (840) | K28: LED | M28: 174w | N28: IP66 | S28: 6,5 mt | T28: 1 | U28: F | W28: g-LGF-Lighting Fixture F - Type F (GARRABRIDGE - 7428 RAPSODY M600X600 3400 840 MP) | AD28: =350+71 -> 421
C29: 3000 | D29: =C29/$D$2 -> 260.86957 | E29: 27/11/2024 | F29: THORLUX | G29: THOROPROOF | H29: ETP19776 | I29: HIGH IMPACT CORROSION RESISTANT, INJECTION MOULDED POLYCARBONATE BODY IP65 | J29: 6625 Lm | K29: LED | M29: 46w | N29: IP65 | S29: 3,2 mt | T29: 1 | U29: G | W29: g-LGF-Shiraz-CA LIGHT-UP - G (THORLUX THOROPROOD ETP19776 IP65) | AD29: =11+232 -> 243
D30: =C30/$D$2 -> 0 | E30: 27/11/2024 | F30: TRILUX | G30: NAVIONA | H30: 10236960 | I30: LAY-IN RECESSED DIRECT/INDIRECT LED CEILING LUMINAIRE, TPB MICRO PRISMATIC. M73 36-840 ETDD | J30: 3575 Lm | K30: LED | M30: 32w | S30: 3 mt | T30: 1 | U30: H
D31: =C31/$D$2 -> 0 | E31: 27/11/2024 | F31: LUG | G31: POWERLUG MINI LED ED | H31: GBM 7150.4 | I31: EXTERNAL LED SURFACE MOUNTED FLOOD LIGHT. POWERLUG MINI LED ED. AS SZEROKI SZARY. 120212.5 L191.41 | J31: 7150 Lm (740) | K31: LED | M31: 54w | N31: IP65 | T31: 1 | U31: X1
D32: =C32/$D$2 -> 0 | E32: 27/11/2024 | F32: LUG | G32: POWERLUG MINI LED ED | H32: 120212.5L171.41 | I32: EXTERNAL LED SURFACE MOUNTED FLOOD LIGHT. AS WIDE GRAY ED. 120212.5 L171.41 | J32: 3600 Lm | K32: LED | L32: 4000K | M32: 25w | N32: IP66 | T32: 1 | U32: X2
D33: =C33/$D$2 -> 0 | E33: 27/11/2024 | F33: LUG | G33: URBINO LED ED 6450LM/740 O5 | H33: GBU 654.4 | I33: EXTERNAL LED COLUMN MOUNTED STREET LIGHT. 130222.5L042.041 | J33: 6450 Lm | K33: LED | M33: 53w | T33: 1 | U33: Y1
D34: =C34/$D$2 -> 0 | E34: 27/11/2024 | F34: LUG | G34: URBINO LED ED 10200LM/730 O38 | H34: GBU 780.4 | I34: EXTERNAL LED COLUMN MOUNTED STREET LIGHT. 130222.5L771.181 | J34: 10200 Lm | K34: LED | M34: 68w | T34: 1 | U34: Y2
D35: =C35/$D$2 -> 0 | E35: 27/11/2024 | F35: LUG | G35: URBINO LED ED 7250LM/740 O38 | H35: GBU 425.4 | I35: EXTERNAL LED COLUMN MOUNTED STREET LIGHT. 130222.5L811.181 | J35: 7250 Lm | K35: LED | M35: 51w | T35: 1 | U35: Y3
D36: =C36/$D$2 -> 0 | E36: 27/11/2024 | F36: LUG | G36: URBINO LED ED 3200LM/740 O38 | H36: GBU 320.4 | I36: EXTERNAL LED COLUMN MOUNTED STREET LIGHT. 130222.5L791.181 | J36: 3200 Lm | K36: LED | M36: 23w | T36: 1 | U36: Y4
D37: =C37/$D$2 -> 0 | E37: 27/11/2024 | F37: THORN | G37: KATONA KAT RD 2000-840 HF | I37: EXTERNAL SURFACE MOUNTED IP65 | J37: 1950 Lm | K37: LED | M37: 16,3w | T37: 1 | U37: Z1
D38: =C38/$D$2 -> 0 | E38: 27/11/2024 | F38: THORN | G38: KATONA KAT RD 2000-840 HF E3D | I38: EXTERNAL SURFACE MOUNTED IP65 | J38: 1950 Lm | K38: LED | M38: 16,3w | T38: 1 | U38: Z1E
X48: Intervalo de Lúmens (lm) | Y48: Tipo de Luminária | Z48: Preço Aproximado (€)
X49: 0 - 500 | Y49: Lâmpadas decorativas | Z49: 45427
X50: 500 - 1.000 | Y50: Iluminação residencial | Z50: 45595
X51: 1.000 - 3.000 | Y51: Luminárias de teto (LED) | Z51: 30 - 100
C52: W \ IP | D52: 20 | E52: 44 | F52: 65 | X52: 3.000 - 5.000 | Y52: Luminárias industriais | Z52: 50 - 150
C53: 200 | D53: 450 | E53: 690 | F53: 800 | X53: 5.000+ | Y53: Projetores ou exteriores | Z53: 100 - 500+
C54: 150 | D54: 370 | E54: 560 | F54: 650
C55: 100 | D55: 250 | E55: 390 | F55: 450
C56: 75 | D56: 250 | E56: 390 | F56: 450
C57: 50 | D57: 230 | E57: 350 | F57: 400
C58: 25 | D58: 200 | E58: 300 | F58: 350 | X58: Intervalo de Lúmens (lm) | Y58: Tipo de Luminária | Z58: Local | AA58: Autonomia (Emergência) | AB58: Preço Aproximado (€)
C59: 15 | D59: 170 | E59: 260 | F59: 300 | X59: 0 - 500 | Y59: Decorativa (ex.: arandelas) | Z59: Interior | AA59: Não aplicável | AB59: 5 - 20
C60: 10 | D60: 115 | E60: 170 | F60: 200 | Y60: Emergência | Z60: Interior | AA60: 1H+ | AB60: 20 - 50
F61: /€ | X61: 500 - 1.000 | Y61: Residencial (ex.: plafons simples) | Z61: Interior | AA61: Não aplicável | AB61: 15 - 30
Y62: Emergência (iluminação geral) | Z62: Interior | AA62: 1H+ | AB62: 30 - 60
Y63: Exterior decorativa | Z63: Exterior | AA63: Não aplicável | AB63: 20 - 50
X64: 1.000 - 3.000 | Y64: Plafons de alto fluxo | Z64: Interior | AA64: Não aplicável | AB64: 30 - 70
Y65: Emergência (áreas amplas) | Z65: Interior | AA65: 1H+ | AB65: 50 - 100
Y66: Iluminação de jardins | Z66: Exterior | AA66: Não aplicável | AB66: 50 - 120
X67: 3.000 - 5.000 | Y67: Luminárias industriais leves | Z67: Interior | AA67: Não aplicável | AB67: 60 - 150
Y68: Projeção de fachadas | Z68: Exterior | AA68: Não aplicável | AB68: 70 - 200
X69: 5.000 - 10.000 | Y69: Luminárias industriais pesadas | Z69: Interior | AA69: Não aplicável | AB69: 150 - 300
Y70: Projetores para áreas amplas | Z70: Exterior | AA70: Não aplicável | AB70: 100 - 400
X71: 10.000+ | Y71: Iluminação de armazéns/logística | Z71: Interior | AA71: Não aplicável | AB71: 300+
Y72: Grandes projetores exteriores | Z72: Exterior | AA72: Não aplicável | AB72: 400+
X75: Preço Médio de Iluminação por Metro Quadrado
X77: Tipo de Espaço | Y77: Nível de Iluminação (lux) | Z77: Preço Médio (€ por m²)
X78: Residencial (salas/quartos) | Y78: 100 - 300 lux | Z78: 5 - 10
X79: Cozinhas e casas de banho | Y79: 300 - 500 lux | Z79: 10 - 15
X80: Escritórios | Y80: 300 - 500 lux | Z80: 10 - 20
X81: Lojas comerciais | Y81: 500 - 800 lux | Z81: 15 - 30
X82: Áreas industriais leves | Y82: 300 - 500 lux | Z82: 10 - 25
X83: Armazéns (circulação) | Y83: 150 - 300 lux | Z83: 5 - 15
X84: Armazéns (trabalho) | Y84: 300 - 500 lux | Z84: 10 - 20
X85: Estacionamentos | Y85: 75 - 150 lux | Z85: 5 - 10
X86: Áreas externas (jardins) | Y86: 50 - 150 lux | Z86: 5 - 15
X87: Áreas externas (fachadas) | Y87: 200 - 400 lux | Z87: 15 - 30

Sheet Lighting Control
A4: INTERNAL CODE | B4: TYPE | C4: UNIT PRICE EUR | D4: MANUFACTURER | E4: MODEL | F4: ARTICLE NO. | G4: DESCRIPTION | H4: FLUX (Lm) | I4: LAMP | J4: LAMP COLOUR (K) | K4: ACTIVE POWER (W) | L4: IP RATING | M4: DIMENSIONS (mm) | N4: WEIGHT (Kg) | O4: LINK (AS NA EXAMPLE) | P4: PICTURE | Q4: TYPICAL MOUNTING HEIGHT (mt) | R4: MANPOWER (HR) | Z4: Skien Qty.
C5: 2000 | G5: BACnet Lighting Controller (3 per data hall)
C6: 55 | G6: BACnet LED Drivers (1 per fixture)
C7: 120 | G7: BACnet Occupancy & Daylight Sensors (1 per 10 fixtures)
C8: 1500 | G8: BACnet MS/TP Gateways (To Convert Data Between BACnet/IP and BACnet MS/TP) (1 per data hall)
C9: 55000 | G9: BACnet Control Software (For Centralized Lighting Management)
C10: 2500 | G10: Network Switches (For BACnet/IP Connectivity) (1 per data hall)
C11: 30000 | G11: BACnet MS/TP (RS-485) Cabling: 20,000 meters (~€1.50/m)
C12: 6000 | G12: Ethernet Cabling (For BACnet/IP Backbone): 5,000 meters (~€1.20/m)
C13: 35000 | G13: Installation Hardware (Junction Boxes, Mounts, etc.)
A19: Installation Guidelines (BACnet System)
A21: 1. System Architecture
A23: BACnet/IP for Central Control
A24: Connects to a central server running BACnet software.
A25: BACnet MS/TP for Local Control
A26: Each data hall has one BACnet MS/TP network with RS-485 wiring connecting the fixtures to BACnet lighting controllers.
A28: 2. Cabling & Networking
A30: BACnet/IP Backbone:
A31: Use industrial-grade Ethernet switches in each data hall.
A32: Ensure proper VLANs for security & performance.
A33: BACnet MS/TP (RS-485) Wiring:
A34: Daisy-chain occupancy sensors and drivers to controllers.
... A97: More Info: Philips Dynalite

Sheet 4.0_Assumptions
C3: Assumptions, Clarifications & Exclusions
C6: CLARIFICATIONS & ASSUMPTIONS
C7: 1. | D7: Our Tender is based on the information provided by the client.
C8: 2. | D8: We have assumed offices space will be provided by GC free of charge.
C9: 3. | D9: Our proposal is based on unhindered access to the approved design. We assume that there is free and unimpeded access for the work to be carried out and for any deliveries and the like.
C10: 4. | D10: The price for the cable termination is for both sides of the cable.
C11: 5. | D11: The scope of commissioning includes collecting documentation of the equipment, verifying the installation, assembly, labelling and conclusion of works, and start-up test (energize together with the vendor responsible for each asset on site. Supervision, QA and Responsibility, Documentation, checklists, manuals, red-pens, included in Commissioning pricing of this tender.
C12: 6. | D12: As detailed information for the end consumers has not been provided, an average length for the cable output has been taken into consideration for the supply and install the installation.
C13: 7. | D13: All lighting fixtures have DALI communication and are controlled by BACnet system. Electrical Fixtures Point of Connection, connection boxes and switches are included in the Lighting package.
C14: 8. | D14: Accommodation, meals and travels for white collars (Staff) are included in GC3 Staff.
C15: 9. | D15: Subcontract man power could be considered if needed.
C20: EXCLUSIONS
C21: 1. | D21: All equipment and work not mentioned in the proposal
C22: 2. | D22: We have assumed the Client will carry out all general contractor duties and provide any temporary services and the like required.
C23: 3. | D23: We assume that the general contractor will take care of all tasks, all the necessary temporary and similar services.
C24: 4. | D24: Commissioning Level 4 (except for Load banks testing) and Level 5.
C25: 5. | D25: PMS, BMS, Fire Alarm and Heat Trace System
C26: 6. | D26: Electrical Panel Board to Electrical Vehicles
C27: 7. | D27: Supply and maintenance of Temporary Power Supply and Water during the construction
C28: 8. | D28: Accommodation, meals and local travels for blue collars workers
C29: 9. | D29: Excluded MV test cable "ensaio descargas parciais"
C30: 10 | D30: Roxtec system

Sheet GCs Gen Cond
C2: General Conditions
B3: Project: | E3: Date of Issue:
B4: Scope: | D4: Revision: | F4: 1
B5: Company:
B6: DATA CENTRE WORKS
B7: Ref. | C7: Category Description | D7: Qty | E7: Unit | F7: Rate | G7: Total (EUR)
B9: 1 | C9: Site Accommodation & Facilities | G9: =SUM(G10:G16) -> 1229220
B10: 1.01 | C10: Tools and Materials Storage | D10: 58 | E10: wks | F10: 18000 | G10: =D10*F10 -> 1044000
B11: 1.02 | C11: Parking | G11: =D11*F11 -> 0
B12: 1.03 | C12: IT Equipment, Photocopiers, Peripherals and Comms | D12: 58 | E12: wks | F12: 1500 | G12: =D12*F12 -> 87000
B13: 1.04 | C13: Stationary and Consumables | D13: 58 | E13: wks | F13: 800 | G13: =D13*F13 -> 46400
B14: 1.05 | C14: Telecom landlines / Mobile Phones / Radios / Email / Wi-Fi | D14: 58 | E14: wks | F14: 290 | G14: =D14*F14 -> 16820
B15: 1.06 | C15: Other Software Licenses As Required (e.g. VEO, Textura, SAP, P6, Prolog etc.) | D15: 14 | E15: month | F15: 2500 | G15: =D15*F15 -> 35000
G16: =D16*F16 -> 0
B17: 2 | C17: Temporary Works & Services | G17: =SUM(G18:G21) -> 203000
B18: 2.01 | C18: Task Power and Lighting for Site Works | D18: 58 | E18: wks | F18: 3500 | G18: =D18*F18 -> 203000
B19: 2.02 | C19: Temporary roads, hard standings and footpaths on the site | G19: =D19*F19 -> 0
B20: 2.03 | C20: Traffic Regulations and Traffic Management | G20: =D20*F20 -> 0
G21: =D21*F21 -> 0
B22: 3 | C22: Site Plant and Equipment | G22: =SUM(G23:G32) -> 0
B23: 3.01 | C23: Earth Moving Plant | G23: =D23*F23 -> 0
B24: 3.02 | C24: Concrete Plant | G24: =D24*F24 -> 0
B25: 3.03 | C25: Piling Plant | G25: =D25*F25 -> 0
B26: 3.04 | C26: Fixed Cranes | G26: =D26*F26 -> 0
B27: 3.05 | C27: Mobile Cranes | G27: =D27*F27 -> 0
B28: 3.06 | C28: Hoists | G28: =D28*F28 -> 0
B29: 3.07 | C29: Access Plant; Telehandlers, MEWPs, Cherry Pickers | G29: =D29*F29 -> 0
B30: 3.08 | C30: Plant and material movement: Forklifts | G30: =D30*F30 -> 0
B31: 3.09 | C31: Other Plant | G31: =D31*F31 -> 0
G32: =D32*F32 -> 0
B33: 4 | C33: Scaffolding, Access, Loading, Fencing and Signage | G33: =SUM(G34:G41) -> 348000
B34: 4.01 | C34: Safety Barriers and Rails | D34: 58 | E34: wks | F34: 500 | G34: =D34*F34 -> 29000
B35: 4.02 | C35: Temporary Hoardings, Fences and Gates | G35: =D35*F35 -> 0
B36: 4.03 | C36: Fixed Access Scaffolding | D36: 58 | E36: wks | F36: 3000 | G36: =D36*F36 -> 174000
B37: 4.04 | C37: Mobile Access Scaffolding | D37: 58 | E37: wks | F37: 1500 | G37: =D37*F37 -> 87000
B38: 4.05 | C38: Support Scaffolding and Propping | D38: 58 | E38: wks | F38: 1000 | G38: =D38*F38 -> 58000
B39: 4.06 | C39: Landing decks and Crash decks | G39: =D39*F39 -> 0
B40: 4.07 | C40: Wayfinding and Safety Signage | G40: =D40*F40 -> 0
G41: =D41*F41 -> 0
B42: 5 | C42: Local Authority Permits and Fees | G42: =SUM(G43:G45) -> 43000
B43: 5.01 | C43: Temporary permits | D43: 14 | E43: month | F43: 2000 | G43: =D43*F43 -> 28000
B44: 5.02 | C44: Permanent permits | D44: 1 | E44: LS | F44: 15000 | G44: =D44*F44 -> 15000
G45: =D45*F45 -> 0
B46: 6 | C46: Licenses, Fees and Charges | G46: =SUM(G47:G51) -> 0
B47: 6.01 | C47: Road Closure Licenses | G47: =D47*F47 -> 0
B48: 6.02 | C48: Other Licenses (Please Specify) | G48: =D48*F48 -> 0
B49: 6.03 | C49: Utilities Consumption Charges (Power/Water/Drainage/Communications) | G49: =D49*F49 -> 0
B50: 6.04 | C50: Disposal Charges (Foul Water) | G50: =D50*F50 -> 0
G51: =D51*F51 -> 0
B52: 7 | C52: Statutory and Regulatory Compliance | G52: =SUM(G53:G59) -> 0
B53: 7.01 | C53: Building Control Compliance and Approvals | G53: =D53*F53 -> 0
B54: 7.02 | C54: Reports and Energy Performance Certificate | G54: =D54*F54 -> 0
B55: 7.03 | C55: Compliance with Planning Conditions | G55: =D55*F55 -> 0
B56: 7.04 | C56: Environmental Impact Assessment and Reporting | G56: =D56*F56 -> 0
B57: 7.05 | C57: Noise Impact Assessment and Reporting | G57: =D57*F57 -> 0
B58: 7.06 | C58: Fire Compliance Risk Assessments and Reporting | G58: =D58*F58 -> 0
G59: =D59*F59 -> 0
B60: 7 | C60: Waste Management | G60: =SUM(G61:G66) -> 87000
B61: 7.01 | C61: Waste Water Disposal | D61: 58 | E61: wks | F61: 300 | G61: =D61*F61 -> 17400
B62: 7.02 | C62: Land Fill Waste Disposal | D62: 58 | E62: wks | F62: 300 | G62: =D62*F62 -> 17400
B63: 7.03 | C63: Recycling Waste Disposal | D63: 58 | E63: wks | F63: 300 | G63: =D63*F63 -> 17400
B64: 7.04 | C64: Hazardous Waste Disposal | D64: 58 | E64: wks | F64: 300 | G64: =D64*F64 -> 17400
B65: 7.05 | C65: Site Waste Removal from Working Areas | D65: 58 | E65: wks | F65: 300 | G65: =D65*F65 -> 17400
G66: =D66*F66 -> 0
B67: 8 | C67: Protection and Cleaning of the Works | G67: =SUM(G68:G73) -> 493000
B68: 8.01 | C68: Protection of the Works | D68: 58 | E68: wks | F68: 2500 | G68: =D68*F68 -> 145000
B69: 8.02 | C69: Cleaning and drying out of the works | D69: 58 | E69: wks | F69: 3000 | G69: =D69*F69 -> 174000
B70: 8.03 | C70: Builder's clean | D70: 58 | E70: wks | F70: 3000 | G70: =D70*F70 -> 174000
B71: 8.04 | C71: Clincal clean | G71: =D71*F71 -> 0
B72: 8.05 | C72: Cleaning and maintenance of public and private highways used in the course of the works | G72: =D72*F72 -> 0
G73: =D73*F73 -> 0
B74: 9 | C74: Quality Control and Health & Safety | G74: =SUM(G75:G80) -> 789500
B75: 9.01 | C75: Safety and Accident Prevention including EU CLP Regulations | D75: 290 | E75: unit | F75: 700 | G75: =D75*F75 -> 203000
B76: 9.02 | C76: Personnel Protective Equipment | D76: 290 | E76: unit | F76: 1250 | G76: =D76*F76 -> 362500
B77: 9.03 | C77: Method Statements, Risk Assessments and Site Safety Records | D77: 58 | E77: wks | F77: 1500 | G77: =D77*F77 -> 87000
B78: 9.04 | C78: Quality Control Management, Monitoring and Reporting (Site/Factory Visits) | D78: 58 | E78: wks | F78: 1500 | G78: =D78*F78 -> 87000
B79: 9.05 | C79: Defects / Snagging Coordination and Close Out | D79: 1 | E79: LS | F79: 50000 | G79: =D79*F79 -> 50000
G80: =D80*F80 -> 0
B81: 10 | C81: Security Control and Access Management | G81: =SUM(G82:G86) -> 243000
B82: 10.01 | C82: Security Staff | D82: 58 | E82: wks | F82: 1500 | G82: =D82*F82 -> 87000
B83: 10.02 | C83: Security Installations and Equipment including Lighting, Turnstiles, Access Control etc | D83: 1 | E83: LS | F83: 25000 | G83: =D83*F83 -> 25000
B84: 10.03 | C84: Compliance with Employer's Site Security Rules and Protocols | D84: 1 | E84: LS | F84: 15000 | G84: =D84*F84 -> 15000
B85: 10.04 | C85: Supervision and Co-ordination of RAMS and Permits Related to Working in Employer Controlled Areas | D85: 58 | E85: wks | F85: 2000 | G85: =D85*F85 -> 116000
G86: =D86*F86 -> 0
B87: 11 | C87: Insurances / Guarantees / Bond / Warranties | G87: =SUM(G88:G96) -> 2686400
B88: 11.01 | C88: Works Insurance - By Contractor | D88: 60 | E88: wks | F88: 16000 | G88: =D88*F88 -> 960000
B89: 11.03 | C89: Professional Indemnity Insurance | D89: 60 | E89: wks | F89: 3500 | G89: =D89*F89 -> 210000
B90: 11.04 | C90: Public Liability Insurance | D90: 1 | E90: ls | F90: 20000 | G90: =D90*F90 -> 20000
B91: 11.05 | C91: Employer’s (Main Contractor’s) Liability Insurance | D91: 58 | E91: wks | F91: 25800 | G91: =D91*F91 -> 1496400
B92: 11.06 | C92: Parent Company Guarantee | D92: 1 | E92: ls | G92: =D92*F92 -> 0
B93: 11.07 | C93: Performance Bond | D93: 1 | E93: ls | G93: =D93*F93 -> 0
B94: 11.08 | C94: Collateral Warranties | D94: 1 | E94: ls | G94: =D94*F94 -> 0
B95: 11.09 | C95: Bank Guarantees | D95: 1 | E95: ls | G95: =D95*F95 -> 0
G96: =D96*F96 -> 0
B97: 12 | C97: H&S Planning and Handover Documentation | G97: =SUM(G98:G103) -> 323000
B98: 12.01 | C98: Health & Safety Plan and Management | D98: 1 | E98: LS | F98: 12000 | G98: =D98*F98 -> 12000
B99: 12.02 | C99: O&M Manual Production | D99: 1 | E99: LS | F99: 40000 | G99: =D99*F99 -> 40000
B100: 12.03 | C100: As-Built Drawing Production | D100: 1 | E100: LS | F100: 256000 | G100: =D100*F100 -> 256000
B101: 12.04 | C101: Standard Operating Procedures and Emergency Operating Procedures | D101: 1 | E101: LS | F101: 15000 | G101: =D101*F101 -> 15000
B104: 13 | C104: Training | G104: =SUM(G105:G106) -> 290000
...

Sheet GRs Staff
B1: General Requirements - Staff
A2: Project: | B2: Sines Phase 2 | F2: Date of Issue:
A3: Scope: | F3: Revision: | H3: 1
A4: Company:
A5: Contractor Staff - Resource Loader and Costs | D5: Insert Month:
D6: Week No.: | E6: 1 | F6: 2 | G6: 3 | H6: 4 | I6: 5 | J6: 6 | K6: 7 | L6: 8 | M6: 9 | N6: 10 | O6: 11 | P6: 12 | Q6: 13 | R6: 14 | S6: 15 | T6: 16 | U6: 17 | V6: 18 | W6: 19 | X6: 20 | Y6: 21 | Z6: 22 | AA6: 23 | AB6: 24 | AC6: 25 | AD6: 26 | AE6: 27 | AF6: 28 | AG6: 29 | AH6: 30 | AI6: 31 | AJ6: 32 | AK6: 33 | AL6: 34 | AM6: 35 | AN6: 36 | AO6: 37 | AP6: 38 | AQ6: 39 | AR6: 40 | AS6: 41 | AT6: 42 | AU6: 43 | AV6: 44 | AW6: 45 | AX6: 46 | AY6: 47 | AZ6: 48 | BA6: 49 | BB6: 50 | BC6: 51 | BD6: 52 | BE6: 53 | BF6: 54 | BG6: 55 | BH6: 56 | BI6: 57 | BJ6: 58 | BK6: 59 | BL6: 60 | BM6: 61 | BN6: 62 | BO6: 63 | BP6: 64 | BQ6: 65 | BS6: Total Hours | BT6: Total EUR (€)
D7: W/C Date: | E7: 46049 | F7: =E7+7 -> 46056 | G7: =F7+7 -> 46063 | H7: =G7+7 -> 46070 | I7: =H7+7 -> 46077 | J7: =I7+7 -> 46084 | K7: =J7+7 -> 46091 | L7: =K7+7 -> 46098 | M7: =L7+7 -> 46105 | ... BQ7: =BP7+7 -> 46497
A8: DC WORKS
B9: Function | C9: Name | D9: All-in Rate | BS9: =SUM(E9:BR9) -> 0
B10: Head Office Staff
A11: 1 | B11: Head Office Management
BS12: =SUM(E12:BR12) -> 0 | BT12: =BS12*D12 -> 0
BS13: =SUM(E13:BR13) -> 0 | BT13: =BS13*D13 -> 0
BS14: =SUM(E14:BR14) -> 0 | BT14: =BS14*D14 -> 0
B15: =B10 -> Head Office Staff | C15: Sub-Total | E15: =SUM(E11:E14) -> 0 | F15: =SUM(F11:F14) -> 0 | G15: =SUM(G11:G14) -> 0 | H15: =SUM(H11:H14) -> 0 | I15: =SUM(I11:I14) -> 0 | J15: =SUM(J11:J14) -> 0 | K15: =SUM(K11:K14) -> 0 | L15: =SUM(L11:L14) -> 0 | ... AW15: =SUM(AW11:AW14) -> 0 | BL15: =SUM(BL11:BL14) -> 0 | BR15: =SUBTOTAL(9,BR11:BR14) -> 0 | BS15: =SUBTOTAL(9,BS11:BS14) -> 0 | BT15: =SUBTOTAL(9,BT11:BT14) -> 0
B17: Field Based Staff
BS18: =SUM(E18:BR18) -> 0 | BT18: =BS18*D18 -> 0
B19: Management, Supervision, Staff | BS19: =SUM(E19:BR19) -> 0 | BT19: =BS19*D19 -> 0
A20: 1 | B20: Project Director | C20: 1 | D20: ='[55]GC Staff (Aux)'!P5 -> 120 | E20: =40*$C20 -> 40 | F20: =40*$C20 -> 40 | G20: =40*$C20 -> 40 | H20: =40*$C20 -> 40 | I20: =40*$C20 -> 40 | J20: =40*$C20 -> 40 | K20: =40*$C20 -> 40 | L20: =40*$C20 -> 40 | ... BL20: =40*$C20 -> 40 | BS20: =SUM(E20:BR20) -> 2400 | BT20: =BS20*D20 -> 288000
A21: 2 | B21: Project Manager | C21: 2 | D21: ='[55]GC Staff (Aux)'!P6 -> 112.5 | E21: =40*$C21 -> 80 | F21: =40*$C21 -> 80 | G21: =40*$C21 -> 80 | H21: =40*$C21 -> 80 | I21: =40*$C21 -> 80 | J21: =40*$C21 -> 80 | K21: =40*$C21 -> 80 | L21: =40*$C21 -> 80 | ... BL21: =40*$C21 -> 80 | BS21: =SUM(E21:BR21) -> 4800 | BT21: =BS21*D21 -> 540000
A22: 3 | B22: Project Manager Deputy | C22: 2 | D22: ='[55]GC Staff (Aux)'!P7 -> 90.45 | I22: =40*$C22 -> 80 | J22: =40*$C22 -> 80 | K22: =40*$C22 -> 80 | L22: =40*$C22 -> 80 | M22: =40*$C22 -> 80 | N22: =40*$C22 -> 80 | O22: =40*$C22 -> 80 | P22: =40*$C22 -> 80 | ... BL22: =40*$C22 -> 80 | BS22: =SUM(E22:BR22) -> 4480 | BT22: =BS22*D22 -> 405216
A23: 4 | B23: Project Engineer | C23: 2 | D23: ='[55]GC Staff (Aux)'!P8 -> 90.45 | I23: =40*$C23 -> 80 | J23: =40*$C23 -> 80 | K23: =40*$C23 -> 80 | L23: =40*$C23 -> 80 | M23: =40*$C23 -> 80 | N23: =40*$C23 -> 80 | O23: =40*$C23 -> 80 | P23: =40*$C23 -> 80 | ... BL23: =40*$C23 -> 80 | BS23: =SUM(E23:BR23) -> 4480 | BT23: =BS23*D23 -> 405216
A24: 5 | B24: Site Manager | C24: 4 | D24: ='[55]GC Staff (Aux)'!P9 -> 84.5 | I24: =40*$C24 -> 160 | J24: =40*$C24 -> 160 | K24: =40*$C24 -> 160 | L24: =40*$C24 -> 160 | M24: =40*$C24 -> 160 | N24: =40*$C24 -> 160 | O24: =40*$C24 -> 160 | P24: =40*$C24 -> 160 | ... BL24: =40*$C24 -> 160 | BS24: =SUM(E24:BR24) -> 8960 | BT24: =BS24*D24 -> 757120
A25: 6 | B25: Planner/Document Control | C25: 2 | D25: ='[55]GC Staff (Aux)'!P10 -> 78.55 | I25: =40*$C25 -> 80 | J25: =40*$C25 -> 80 | K25: =40*$C25 -> 80 | L25: =40*$C25 -> 80 | M25: =40*$C25 -> 80 | N25: =40*$C25 -> 80 | O25: =40*$C25 -> 80 | P25: =40*$C25 -> 80 | ... BL25: =40*$C25 -> 80 | BS25: =SUM(E25:BR25) -> 4480 | BT25: =BS25*D25 -> 351904
A26: 7 | B26: Controller | C26: 2 | D26: ='[55]GC Staff (Aux)'!P11 -> 78.55 | I26: =40*$C26 -> 80 | J26: =40*$C26 -> 80 | K26: =40*$C26 -> 80 | L26: =40*$C26 -> 80 | M26: =40*$C26 -> 80 | N26: =40*$C26 -> 80 | O26: =40*$C26 -> 80 | P26: =40*$C26 -> 80 | ... BL26: =40*$C26 -> 80 | BS26: =SUM(E26:BR26) -> 4480 | BT26: =BS26*D26 -> 351904
A27: 8 | B27: Supply Chain Manager | C27: 1 | D27: ='[55]GC Staff (Aux)'!P12 -> 76 | I27: =40*$C27 -> 40 | J27: =40*$C27 -> 40 | K27: =40*$C27 -> 40 | L27: =40*$C27 -> 40 | M27: =40*$C27 -> 40 | N27: =40*$C27 -> 40 | O27: =40*$C27 -> 40 | P27: =40*$C27 -> 40 | ... BL27: =40*$C27 -> 40 | BS27: =SUM(E27:BR27) -> 2240 | BT27: =BS27*D27 -> 170240
A28: 9 | B28: Quantity Surveyor Electrical | C28: 2 | D28: ='[55]GC Staff (Aux)'!P13 -> 76 | I28: =40*$C28 -> 80 | J28: =40*$C28 -> 80 | K28: =40*$C28 -> 80 | L28: =40*$C28 -> 80 | M28: =40*$C28 -> 80 | N28: =40*$C28 -> 80 | O28: =40*$C28 -> 80 | P28: =40*$C28 -> 80 | ... BL28: =40*$C28 -> 80 | BS28: =SUM(E28:BR28) -> 4480 | BT28: =BS28*D28 -> 340480
A29: 10 | B29: Health & Safety Manager | C29: 1 | D29: ='[55]GC Staff (Aux)'!P14 -> 78.55 | I29: =40*$C29 -> 40 | J29: =40*$C29 -> 40 | K29: =40*$C29 -> 40 | L29: =40*$C29 -> 40 | M29: =40*$C29 -> 40 | N29: =40*$C29 -> 40 | O29: =40*$C29 -> 40 | P29: =40*$C29 -> 40 | ... BL29: =40*$C29 -> 40 | BS29: =SUM(E29:BR29) -> 2240 | BT29: =BS29*D29 -> 175952
A30: 11 | B30: Health & Safety Asst Manager | C30: 4 | D30: ='[55]GC Staff (Aux)'!P15 -> 76 | I30: =40*$C30 -> 160 | J30: =40*$C30 -> 160 | K30: =40*$C30 -> 160 | L30: =40*$C30 -> 160 | M30: =40*$C30 -> 160 | N30: =40*$C30 -> 160 | O30: =40*$C30 -> 160 | P30: =40*$C30 -> 160 | ... BL30: =40*$C30 -> 160 | BS30: =SUM(E30:BR30) -> 8960 | BT30: =BS30*D30 -> 680960
A31: 12 | B31: QA / QC Assistant | C31: 3 | D31: ='[55]GC Staff (Aux)'!P16 -> 76 | I31: =40*$C31 -> 120 | J31: =40*$C31 -> 120 | K31: =40*$C31 -> 120 | L31: =40*$C31 -> 120 | M31: =40*$C31 -> 120 | N31: =40*$C31 -> 120 | O31: =40*$C31 -> 120 | P31: =40*$C31 -> 120 | ... BL31: =40*$C31 -> 120 | BS31: =SUM(E31:BR31) -> 6720 | BT31: =BS31*D31 -> 510720
A32: 13 | B32: Design support | C32: 3 | D32: ='[55]GC Staff (Aux)'!P17 -> 76 | I32: =40*$C32 -> 120 | J32: =40*$C32 -> 120 | K32: =40*$C32 -> 120 | L32: =40*$C32 -> 120 | M32: =40*$C32 -> 120 | N32: =40*$C32 -> 120 | O32: =40*$C32 -> 120 | P32: =40*$C32 -> 120 | ... BL32: =40*$C32 -> 120 | BS32: =SUM(E32:BR32) -> 6720 | BT32: =BS32*D32 -> 510720
A33: 14 | B33: Administration | C33: 2 | D33: ='[55]GC Staff (Aux)'!P18 -> 62.5 | I33: =40*$C33 -> 80 | J33: =40*$C33 -> 80 | K33: =40*$C33 -> 80 | L33: =40*$C33 -> 80 | M33: =40*$C33 -> 80 | N33: =40*$C33 -> 80 | O33: =40*$C33 -> 80 | P33: =40*$C33 -> 80 | ... BL33: =40*$C33 -> 80 | BS33: =SUM(E33:BR33) -> 4480 | BT33: =BS33*D33 -> 280000
... A40: 21 | B40: MEWP Spotter | C40: 10 | D40: ='[55]GC Staff (Aux)'!P25 -> 37.5 | I40: =40*$C40 -> 400 | J40: =40*$C40 -> 400 | K40: =40*$C40 -> 400 | L40: =40*$C40 -> 400 | M40: =40*$C40 -> 400 | N40: =40*$C40 -> 400 | O40: =40*$C40 -> 400 | P40: =40*$C40 -> 400 | ... BL40: =40*$C40 -> 400 | BS40: =SUM(E40:BR40) -> 22400 | BT40: =BS40*D40 -> 840000
A41: 22 | BS41: =SUM(E41:BR41) -> 0 | BT41: =BS41*D41 -> 0
A42: 23 | BS42: =SUM(E42:BR42) -> 0 | BT42: =BS42*D42 -> 0
A43: 24 | BS43: =SUM(E43:BR43) -> 0 | BT43: =BS43*D43 -> 0
A44: 25 | BS44: =SUM(E44:BR44) -> 0 | BT44: =BS44*D44 -> 0
A45: 26 | BS45: =SUM(E45:BR45) -> 0 | BT45: =BS45*D45 -> 0
A46: 27 | BS46: =SUM(E46:BR46) -> 0 | BT46: =BS46*D46 -> 0
A47: 28 | BS47: =SUM(E47:BR47) -> 0 | BT47: =BS47*D47 -> 0
A48: 29 | BS48: =SUM(E48:BR48) -> 0 | BT48: =BS48*D48 -> 0
A49: 30 | BS49: =SUM(E49:BR49) -> 0 | BT49: =BS49*D49 -> 0
A50: 31 | BS50: =SUM(E50:BR50) -> 0 | BT50: =BS50*D50 -> 0
A51: 32 | BS51: =SUM(E51:BR51) -> 0 | BT51: =BS51*D51 -> 0
A52: 33 | BS52: =SUM(E52:BR52) -> 0 | BT52: =BS52*D52 -> 0
... A58: 39 | BS58: =SUM(E58:BR58) -> 0 | BT58: =BS58*D58 -> 0
B60: OTHERS
A61: 58 | B61: Please specify | BS61: =SUM(E61:BR61) -> 0 | BT61: =BS61*D61 -> 0
A62: 59 | B62: Please specify | BS62: =SUM(E62:BR62) -> 0 | BT62: =BS62*D62 -> 0
A63: 60 | B63: Please specify | BS63: =SUM(E63:BR63) -> 0 | BT63: =BS63*D63 -> 0
A64: 61 | B64: Please specify | BS64: =SUM(E64:BR64) -> 0 | BT64: =BS64*D64 -> 0
A65: 62 | B65: Please specify | BS65: =SUM(E65:BR65) -> 0 | BT65: =BS65*D65 -> 0
A66: 63 | B66: Please specify | BS66: =SUM(E66:BR66) -> 0 | BT66: =BS66*D66 -> 0
A67: 64 | B67: Please specify | BS67: =SUM(E67:BR67) -> 0 | BT67: =BS67*D67 -> 0
A68: 65 | B68: Please specify | BS68: =SUM(E68:BR68) -> 0 | BT68: =BS68*D68 -> 0
BS69: =SUM(E69:BR69) -> 0 | BT69: =BS69*D69 -> 0
BS70: =SUM(E70:BR70) -> 0 | BT70: =BS70*D70 -> 0
B71: Field Based Staff | C71: Sub-Total | E71: =SUM(E18:E70) -> 120 | F71: =SUM(F18:F70) -> 120 | G71: =SUM(G18:G70) -> 120 | H71: =SUM(H18:H70) -> 120 | I71: =SUM(I18:I70) -> 3600 | J71: =SUM(J18:J70) -> 3600 | K71: =SUM(K18:K70) -> 3600 | L71: =SUM(L18:L70) -> 3600 | ... BQ71: =SUM(BQ18:BQ70) -> 0 | BS71: =SUBTOTAL(9,BS18:BS70) -> 202080 | BT71: =SUBTOTAL(9,BT18:BT70) -> 13452752
B72: TOTAL STAFF COST & HOURS (DC WORKS) | E72: =E71 -> 120 | F72: =F71 -> 120 | G72: =G71 -> 120 | H72: =H71 -> 120 | I72: =I71 -> 3600 | J72: =J71 -> 3600 | K72: =K71 -> 3600 | L72: =L71 -> 3600 | ... BQ72: =BQ71 -> 0 | BS72: =BS71 -> 202080 | BT72: =BT71 -> 13452752
B73: TOTAL TRAVEL & EXPENSE and STAFF WEEKS (DC WORKS)
B74: TOTAL STAFF COST (DC WORKS) | BS74: =BS71 -> 202080 | BT74: =BT71+BT15 -> 13452752
A77: =BT74 -> 13452752
A82: 1 | B82: Project Director / Contract Manager
A83: 2 | B83: Project Manager - General
A84: 3 | B84: Project Manager - Civils
A85: 4 | B85: Project Manager - Mechanical
A86: 5 | B86: Project Manager - Mechanical
A87: 6 | B87: Project Manager - Electrical
A88: 7 | B88: Project Manager - Electrical
A89: 8 | B89: Project Manager - OFCI Mechanical
A90: 9 | B90: Project Manager - OFCI - Electrical
A91: 10 | B91: Project Engineer - Building
A92: 11 | B92: Project Engineer - Building
A93: 12 | B93: Project Engineer - Mechanical
... A138: 57 | B138: Local Authority Liason Officer

Sheet Programme
A2: Activity ID | B2: Activity Name | C2: Draft Programme Duration | D2: Start | E2: Finish | F2: Velox Scope? | G2: Manpower average (man/day) | H2: Total manhours | I2: Comments
A3: Project Name - Description
A4: Design
A5: Procurement
A6: Construction
A7: Project Number
A8: SIN0201 DC GC3 Arch & MEP Fit-Out [CO/FO] (2-LEVEL STOREY BUILDING)
A9: SIN02 DC GC3 Architectural & MEP Fit-Out Works - Phase 1
A10: SIN02 DC GC3 Architectural & MEP Fit-Out Works - Phase 1 - Excluding Data Hall & Office Building
A11: MEP Fit-Out - Phase 1 - Excluding Data Hall & Office Building + Additional Works for ETO 1 Target
A12: Electrical Fit-Out - Phase 1 - Excluding 1st Data Hall & Office Building
A13: SC.CO.FO.0470 | B13: Install - Primary & Secondary Containment (Including Supports & Cable Trays) for Electrical Areas - Phase 1 (ELEC) | C13: =NETWORKDAYS(D13,E13) -> 57 | D13: 46077 | E13: 46155 | F13: Yes | G13: 20.358247 | H13: 9283.3608
A14: Electricity MV/LV Systems - Phase 1
A15: SC.CO.FO.0480 | B15: Pull - MV/LV Electrical Piping & Cabling to Equipment Termination Points - Phase 1 (ELEC) | C15: =NETWORKDAYS(D15,E15) -> 52 | D15: 46085 | E15: 46156 | F15: Yes | G15: 69.037276 | H15: 28719.507
A16: SC.CO.FO.0490 | B16: Install - Electrical OFCI Equipment (Electrical Skids ) - Phase 1 (ELEC) | C16: 55 | D16: 46114 | E16: 46196 | F16: No
A17: SC.CO.FO.0500 | B17: Install - Electrical OFCI Equipment (Electrical Generators) - Phase 1 (ELEC) | C17: 50 | D17: 46175 | E17: 46246 | F17: No
A18: SC.CO.FO.0510 | B18: Install - Busbar, Tap Offs, and Connection Boxes - Phase 1 & ETO 1 Area (ELEC) | C18: =NETWORKDAYS(D18,E18) -> 116 | D18: 46160 | E18: 46321 | F18: Yes | G18: 75.50085 | H18: 70064.789
A19: SC.CO.FO.0520 | B19: Install - Power Sockets, Distrib.Boards (inc.Critic.Distr.Boards), Switch Boards, Bater., El.Equip.& Isolat.Ph.1&ETO1 | C19: =NETWORKDAYS(D19,E19) -> 40 | D19: 46212 | E19: 46267 | F19: Yes | G19: 4.846269 | H19: 1550.8061
A20: SC.CO.FO.0540 | B20: Install - Earthing & Grounding System - Phase 1 (ELEC) | C20: =NETWORKDAYS(D20,E20) -> 40 | D20: 46217 | E20: 46272 | F20: Yes | G20: 17.51048 | H20: 5603.3535
A21: SC.CO.FO.0530 | B21: Pull - Small Power & Lighting Cabling - Phase 1 (ELEC) | C21: =NETWORKDAYS(D21,E21) -> 40 | D21: 46219 | E21: 46274 | F21: Yes | G21: 18.907719 | H21: 6050.47
A22: SC.CO.FO.0550 | B22: Install - Lighting Fixtures - Phase 1 (ELEC) | C22: =NETWORKDAYS(D22,E22) -> 40 | D22: 46225 | E22: 46280 | F22: Yes | G22: 18.907719 | H22: 6050.47
A23: SC.CO.FO.0560 | B23: Install - Lightning Protection (Including Roof Rods) - Phase 1 (ELEC) | C23: 30 | D23: 46238 | E23: 46279 | F23: No
A24: Fire Detection - Phase 1
A25: SC.CO.FO.0570 | B25: Pull - Fire Detection System Cabling - Phase 1 (ELEC) | C25: 40 | D25: 46182 | E25: 46238 | F25: No
A26: SC.CO.FO.0580 | B26: Install - Fire Detectors - Phase 1 (ELEC) | C26: 30 | D26: 46220 | E26: 46261 | F26: No
A27: SC.CO.FO.0590 | B27: Install - Alarms & Signalling for Fire Detection - Phase 1 (ELEC) | C27: 20 | D27: 46241 | E27: 46268 | F27: No
A28: SC.CO.FO.0600 | B28: Connect & Integrate - Fire Detection System with Fire Alarm & Detection Systems - Phase 1 (ELEC) | C28: 10 | D28: 46262 | E28: 46275 | F28: No
A29: BMS & PMS - Phase 1
A30: SC.CO.FO.0610 | B30: Pull - BMS & PMS Cabling/Fiber Connections - Phase 1 (ELEC) | C30: =NETWORKDAYS(D30,E30) -> 30 | D30: 46209 | E30: 46248 | F30: Yes | G30: 69.037276 | H30: 16568.946
A31: SC.CO.FO.0620 | B31: Install - BMS Panels, Sensors, Valves & Communication Interfaces - Phase 1 (ELEC) | C31: =NETWORKDAYS(D31,E31) -> 30 | D31: 46219 | E31: 46260 | F31: Yes | G31: 0 | H31: 0
A32: SC.CO.FO.0630 | B32: Install - Leak Detection System for BMS & PMS - Phase 1 (ELEC) | C32: 30 | D32: 46239 | E32: 46280 | F32: No
A33: SC.CO.FO.0640 | B33: Install and Connect - BMS with PMS - Phase 1 (ELEC) | C33: 20 | D33: 46253 | E33: 46280 | F33: No
A34: Electrical & Comunication Feeding crossing PH 2 & 3 Areas (ETO 1 and Power On Line Works)
A35: Electricity MV/LV Systems - Feeding to ETO 1 Area crossing PH 2 & 3 Areas and Power Feed to POWER ON
A36: SC.CO.FO.0780 | B36: Install - Primary & Secondary Containment (Incl. Supports & Cable Trays) MV/LV Systems Crossing Ph 2 & 3 Areas (ELEC) | C36: =NETWORKDAYS(D36,E36) -> 32 | D36: 46156 | E36: 46199 | F36: Yes | G36: 20.358247 | H36: 5211.7113
A37: SC.CO.FO.0790 | B37: Pull - MV/LV Electrical Piping & Cabling to Equipment Termination Points - Feed.ETO 1 & POWER ON (ELEC) | C37: =NETWORKDAYS(D37,E37) -> 32 | D37: 46170 | E37: 46213 | F37: Yes | G37: 69.037276 | H37: 17673.543
A38: Ancillary Building - Phase 1
A39: Security Kiosk/Guard House - Phase 1
A40: SC.CO.FO.0820 | B40: Install - Electrical Installations & Fire Detection - Phase 1 (ELEC) | C40: 5 | D40: 46314 | E40: 46318 | F40: No
A41: SC.CO.FO.0830 | B41: Install - BMS, Telecommunications & Security - Phase 1 (ELEC) | C41: 5 | D41: 46321 | E41: 46325 | F41: No
A42: SIN02 DC GC3 Architectural & MEP Fit-Out Works - Phase 1 - Data Hall
A43: MEP Fit-Out - Phase 1 - Data Hall
A44: Electrical Fit-Out - Phase 1 - Data Hall
A45: SC.CO.FO.1100 | B45: Install - Primary & Secondary Containm. (Incl.Supp. & Cable Trays) for Electrical Areas - Phas.1 - 1st Data Hall (ELEC) | C45: =NETWORKDAYS(D45,E45) -> 30 | D45: 46197 | E45: 46238 | F45: Yes | G45: 20.358247 | H45: 4885.9794
A46: Electricity MV/LV Systems Phase 1 -1st Data Hall
A47: SC.CO.FO.1110 | B47: Pull - MV/LV Electrical Piping & Cabling to Equipment Termination Points - Phase 1 - 1st Data Hall (ELEC) | C47: =NETWORKDAYS(D47,E47) -> 30 | D47: 46211 | E47: 46252 | F47: Yes | G47: 69.037276 | H47: 16568.946
A48: SC.CO.FO.1120 | B48: Install - Busbar, Tap Offs, and Connection Boxes - Phase 1- 1st Data Hall (ELEC) | C48: =NETWORKDAYS(D48,E48) -> 95 | D48: 46202 | E48: 46334 | F48: Yes | G48: 75.50085 | H48: 57380.646
A49: SC.CO.FO.1130 | B49: Install - Power Sockets, Distribution Boards (inc.Critic.Distr.Boards), Switch Boards, Bateries, El.Equipment & Isolat. | C49: =NETWORKDAYS(D49,E49) -> 25 | D49: 46260 | E49: 46294 | F49: Yes | G49: 4.846269 | H49: 969.2538
A50: SC.CO.FO.1140 | B50: Pull - Small Power & Lighting Cabling - Phase 1 - 1st Data Hall (ELEC) | C50: =NETWORKDAYS(D50,E50) -> 21 | D50: 46282 | E50: 46310 | F50: Yes | G50: 4.846269 | H50: 814.17319
A51: SC.CO.FO.1150 | B51: Install - Earthing & Grounding System - Phase 1 - 1st Data Hall (ELEC) | C51: =NETWORKDAYS(D51,E51) -> 16 | D51: 46288 | E51: 46309 | F51: Yes | G51: 17.51048 | H51: 2241.3414
A52: SC.CO.FO.1160 | B52: Install - Lighting Fixtures - Phase 1 - 1st Data Hall (ELEC) | C52: =NETWORKDAYS(D52,E52) -> 21 | D52: 46296 | E52: 46324 | F52: Yes | G52: 18.907719 | H52: 3176.4968
A53: Fire Detection - Phase 1 -1st Data Hall
A54: SC.CO.FO.1170 | B54: Pull - Fire Detection System Cabling - Phase 1 - 1st Data Hall (ELEC) | C54: 20 | D54: 46241 | E54: 46268 | F54: No
A55: SC.CO.FO.1180 | B55: Install - Fire Detectors - Phase 1 - 1st Data Hall (ELEC) | C55: 10 | D55: 46269 | E55: 46282 | F55: No
A56: SC.CO.FO.1190 | B56: Install - Alarms & Signalling for Fire Detection - Phase 1 - 1st Data Hall (ELEC) | C56: 10 | D56: 46274 | E56: 46287 | F56: No
A57: SC.CO.FO.1200 | B57: Connect & Integrate - Fire Detection System with Fire Alarm & Detection Systems - Phase 1 - 1st Data Hall (ELEC) | C57: 10 | D57: 46281 | E57: 46294 | F57: No
A58: BMS & PMS - Phase 1 -1st Data Hall
A59: SC.CO.FO.1330 | B59: Pull - BMS & PMS Cabling/Fiber Connections - Phase 1 - 1st Data Hall (ELEC) | C59: =NETWORKDAYS(D59,E59) -> 15 | D59: 46255 | E59: 46275 | F59: Yes | G59: 69.037276 | H59: 8284.4731
A60: SC.CO.FO.1340 | B60: Install - BMS Panels, Sensors, Valves & Communication Interfaces - Phase1 - 1st Data Hall (ELEC) | C60: =NETWORKDAYS(D60,E60) -> 15 | D60: 46262 | E60: 46282 | F60: Yes | G60: 0 | H60: 0
A61: SC.CO.FO.1360 | B61: Install - Leak Detection System for BMS & PMS - Phase 1 - 1st Data Hall (ELEC) | C61: 10 | D61: 46269 | E61: 46282 | F61: No
A62: SC.CO.FO.1350 | B62: Install and Connect - BMS with PMS - Phase 1 - 1st Data Hall (ELEC) | C62: 15 | D62: 46301 | E62: 46321 | F62: No
A63: SIN02 DC GC3 Architectural & MEP Fit-Out Works - Phase 1 - Office Building
A64: MEP Fit-Out - Phase 1 - Office Building
A65: Electrical Fit-Out - Phase 1 - Office Building
A66: SC.CO.FO.1730 | B66: Install - Primary & Secondary Containment (Including Supports & Cable Trays) for Electrical Areas - Phase 1 - Office Bui | C66: =NETWORKDAYS(D66,E66) -> 62 | D66: 46077 | E66: 46162 | F66: Yes | G66: 20.358247 | H66: 10097.691
A67: Fire Detection - Phase 1 - Office Building
A68: SC.CO.FO.1810 | B68: Pull - Fire Detection System Cabling - Phase 1 - Office Building (ELEC) | C68: 40 | D68: 46112 | E68: 46169 | F68: No
A69: SC.CO.FO.1820 | B69: Install - Fire Detectors - Phase 1 - Office Building (ELEC) | C69: 40 | D69: 46149 | E69: 46206 | F69: No
A70: SC.CO.FO.1830 | B70: Install - Alarms & Signalling for Fire Detection - Phase 1 - Office Building (ELEC) | C70: 30 | D70: 46178 | E70: 46220 | F70: No
A71: SC.CO.FO.1840 | B71: Connect & Integrate - Fire Detection System with Fire Alarm & Detection Systems - Phase 1 - Office Building (ELEC) | C71: 15 | D71: 46209 | E71: 46227 | F71: No
A72: Electricity MV/LV Systems - Phase 1 - Office Building
A73: SC.CO.FO.1740 | B73: Pull - MV/LV Electrical Piping & Cabling to Equipment Termination Points - Phase 1 - Office Building (ELEC) | C73: =NETWORKDAYS(D73,E73) -> 63 | D73: 46132 | E73: 46218 | F73: Yes | G73: 69.037276 | H73: 34794.787
A74: SC.CO.FO.1750 | B74: Install - Power Sockets, Distrib.Boards (inc.Critic.Distr.Boards), Switch Boards, Bater., El.Equip.& Isolat.Ph.1&ETO1 | C74: =NETWORKDAYS(D74,E74) -> 42 | D74: 46168 | E74: 46225 | F74: Yes | G74: 4.846269 | H74: 1628.3464
A75: SC.CO.FO.1760 | B75: Pull - Small Power & Lighting Cabling - Phase 1 - Office Building (ELEC) | C75: =NETWORKDAYS(D75,E75) -> 42 | D75: 46175 | E75: 46232 | F75: Yes | G75: 4.846269 | H75: 1628.3464
A76: SC.CO.FO.1800 | B76: Install - Electric.OFCI Equipm.(Electrical Generators)-Supporting Emergency System - Ph.1- Office Building (ELEC) | C76: 20 | D76: 46175 | E76: 46204 | F76: No
A77: SC.CO.FO.1780 | B77: Install - Earthing & Grounding System - Phase 1 - Office Building (ELEC) | C77: =NETWORKDAYS(D77,E77) -> 35 | D77: 46184 | E77: 46232 | F77: Yes | G77: 17.51048 | H77: 4902.9343
A78: SC.CO.FO.1770 | B78: Install - Lighting Fixtures - Phase 1 - Office Building (ELEC) | C78: =NETWORKDAYS(D78,E78) -> 40 | D78: 46184 | E78: 46239 | F78: Yes | G78: 18.907719 | H78: 6050.47
A79: SC.CO.FO.1790 | B79: Install - Lightning Protection (Including Roof Rods) - Phase 1 - Office Building (ELEC) | C79: 30 | D79: 46198 | E79: 46239 | F79: No
A80: BMS & PMS - Phase 1 - Office Building
A81: SC.CO.FO.1850 | B81: Pull - BMS & PMS Cabling/Fiber Connections - Phase 1 - Office Building (ELEC) | C81: =NETWORKDAYS(D81,E81) -> 30 | D81: 46191 | E81: 46232 | F81: Yes | G81: 69.037276 | H81: 16568.946
A82: SC.CO.FO.1860 | B82: Install - BMS Panels, Sensors, Valves & Communication Interfaces - Phase 1 - Office Building (ELEC) | C82: =NETWORKDAYS(D82,E82) -> 30 | D82: 46196 | E82: 46237 | F82: Yes | G82: 0 | H82: 0
A83: SC.CO.FO.1870 | B83: Install - Leak Detection System for BMS & PMS - Phase 1 - Office Building (ELEC) | C83: 30 | D83: 46198 | E83: 46239 | F83: No
A84: SC.CO.FO.1880 | B84: Install and Connect - BMS with PMS - Phase 1 - Office Building (ELEC) | C84: 20 | D84: 46213 | E84: 46240 | F84: No
A85: SIN02 DC GC3 Architectural & MEP Fit-Out Works - Phase 2
A86: MEP Fit-Out - Phase 2
A87: Electrical Fit-Out - Phase 2
A88: SC.CO.FO.2380 | B88: Install - Primary & Secondary Containment (Including Supports & Cable Trays) for Electrical Areas - Phase 2 (ELEC) | C88: =NETWORKDAYS(D88,E88) -> 61 | D88: 46182 | E88: 46266 | F88: Yes | G88: 20.358247 | H88: 9934.8247
A89: Electricity MV/LV Systems Phase 2
A90: SC.CO.FO.2390 | B90: Install - Electrical OFCI Equipment (Electrical Skids) - Phase 2 (ELEC) | C90: 55 | D90: 46197 | E90: 46273 | F90: No
A91: SC.CO.FO.2400 | B91: Pull - MV/LV Electrical Piping & Cabling to Equipment Termination Points - Phase 2 (ELEC) | C91: =NETWORKDAYS(D91,E91) -> 45 | D91: 46232 | E91: 46294 | F91: Yes | G91: 69.037276 | H91: 24853.419
A92: SC.CO.FO.2410 | B92: Install - Electrical OFCI Equipment (Electrical Generators) - Phase 2 (ELEC) | C92: 50 | D92: 46247 | E92: 46317 | F92: No
A93: SC.CO.FO.2420 | B93: Install - Busbar, Tap Offs, and Connection Boxes - Phase 2 (ELEC) | C93: =NETWORKDAYS(D93,E93) -> 107 | D93: 46244 | E93: 46392 | F93: Yes | G93: 75.50085 | H93: 64628.728
A94: SC.CO.FO.2430 | B94: Install - Power Sockets, Distribution Boards (inc.Critic.Distr.Boards), Switch Boards, Bateries, El.Equipment & Isolat. | C94: =NETWORKDAYS(D94,E94) -> 30 | D94: 46304 | E94: 46345 | F94: Yes | G94: 4.846269 | H94: 1163.1046
A95: SC.CO.FO.2440 | B95: Install - Earthing & Grounding System - Phase 2 (ELEC) | C95: =NETWORKDAYS(D95,E95) -> 30 | D95: 46311 | E95: 46352 | F95: Yes | G95: 17.51048 | H95: 4202.5151
A96: SC.CO.FO.2450 | B96: Pull - Small Power & Lighting Cabling - Phase 2 (ELEC) | C96: =NETWORKDAYS(D96,E96) -> 30 | D96: 46311 | E96: 46352 | F96: Yes | G96: 4.846269 | H96: 1163.1046
A97: SC.CO.FO.2460 | B97: Install - Lighting Fixtures - Phase 2 (ELEC) | C97: =NETWORKDAYS(D97,E97) -> 31 | D97: 46317 | E97: 46359 | F97: Yes | G97: 18.907719 | H97: 4689.1143
A98: SC.CO.FO.2470 | B98: Install - Lightning Protection (Including Roof Rods) - Phase 2 (ELEC) | C98: 25 | D98: 46323 | E98: 46358 | F98: No
A99: Fire Detection - Phase 2
A100: SC.CO.FO.2480 | B100: Pull - Fire Detection System Cabling - Phase 2 (ELEC) | C100: 30 | D100: 46274 | E100: 46316 | F100: No
A101: SC.CO.FO.2490 | B101: Install - Fire Detectors - Phase 2 (ELEC) | C101: 20 | D101: 46317 | E101: 46344 | F101: No
...

Sheet DBs_ATS
A1: €/A | D1: Currency
D2: ='[55]Project Input'!E32 -> 11.5
B4: CODE | C4: PRICE NOK | D4: PRICE EUR | E4: UPDATE PRICE DATE | F4: MANUFACTURER | G4: Brand | H4: Reference | I4: No. of poles | J4: Ultimate Withstand (kA) | K4: Input Voltage (V) | L4: Rating (A) | M4: Bypass | N4: Connectivity | O4: Extra features | Q4: Hr
D5: =C5/$D$2 -> 0 | F5: Velox Electro | G5: Schneider Electric | H5: ATS Type 1 | I5: 4 | J5: 50 | K5: 400 | L5: 16 | M5: Dual Line | N5: Aux contacts for status monitoring at BMS | O5: Switch position indicator and source availability indication | Q5: =L5*0.025 -> 0.4
D6: =C6/$D$2 -> 0 | F6: Velox Electro | G6: Schneider Electric | H6: ATS Type 2 | I6: 4 | J6: 50 | K6: 400 | L6: 20 | M6: Dual Line | N6: Aux contacts for status monitoring at BMS | O6: Switch position indicator and source availability indication | Q6: =L6*0.025 -> 0.5
D7: =C7/$D$2 -> 0 | F7: Velox Electro | G7: Schneider Electric | H7: ATS Type 3 | I7: 4 | J7: 50 | K7: 400 | L7: 63 | M7: Dual Line | N7: Aux contacts for status monitoring at BMS | O7: Switch position indicator and source availability indication | Q7: =L7*0.025 -> 1.575
D8: =C8/$D$2 -> 0 | F8: Velox Electro | G8: Schneider Electric | H8: ATS Type 4 | I8: 4 | J8: 50 | K8: 400 | L8: 63 | M8: Dual Line | N8: Aux contacts for status | O8: Switch position indicator and source availability indication | Q8: =L8*0.025 -> 1.575
D9: =C9/$D$2 -> 0 | F9: Velox Electro | G9: Schneider Electric | H9: ATS Type 5 | I9: 4 | J9: 50 | K9: 400 | L9: 80 | M9: Dual Line | N9: Monitoring at BMS | O9: Switch position indicator and source availability indication | Q9: =L9*0.025 -> 2
D10: =C10/$D$2 -> 0 | F10: Velox Electro | G10: Schneider Electric | H10: ATS Type 6 | I10: 4 | J10: 50 | K10: 400 | L10: 125 | M10: Dual Line | N10: Monitoring at BMS | O10: Switch position indicator and source availability indication | Q10: =L10*0.025 -> 3.125
A11: =D11/L11 -> 10.597826 | C11: 19500 | D11: =C11/$D$2 -> 1695.6522 | F11: Velox Electro | G11: Schneider Electric | H11: ATS Type 7 | I11: 4 | J11: 50 | K11: 400 | L11: 160 | M11: Dual Line | N11: Monitoring at BMS | O11: Switch position indicator and source availability indication | Q11: =L11*0.025 -> 4
D12: =C12/$D$2 -> 0 | F12: Velox Electro | G12: Schneider Electric | H12: ATS Type 8 | I12: 4 | J12: 50 | K12: 400 | L12: 320 | M12: Dual Line | N12: Monitoring at BMS | O12: Switch position indicator and source availability indication | Q12: =L12*0.025 -> 8
D13: =C13/$D$2 -> 0 | F13: Velox Electro | G13: Schneider Electric | H13: ATS Type 9 | I13: 4 | J13: 50 | K13: 400 | L13: 400 | M13: Dual Line | N13: Aux contacts for status | O13: Switch position indicator and source availability indication | Q13: =L13*0.025 -> 10
